Workbook

Sheet ENE MXN
A1: SERIE | B1: FACTURA | C1: TRAFICO | D1: FECHA | E1: CLIENTE | F1: CLIENTE NOMBRE | G1: COMPROBADOS | H1: COMPLEMENTARIOS | I1: IVA | J1: SUBTOTAL | K1: ANTICIPO | L1: TOTAL | M1: MONEDA | P1: DOCUMENTACION, ALMACENAJES Y MANIOBRAS ( TER) | Q1: IMPUESTOS ADUANALES (TER) | S1: HONORARIOS | T1: RECONOCIMIENTO ADUANERO | U1: REVALIDACION GUIA / BOL | V1: SERVICIOS COMPLEMENTARIOS | W1: MANIOBRAS | X1: ALMACENAJES | Y1: SERVICIOS LOGISTICOS | Z1: CONSOLIDACION DE ENTRADAS | AA1: SERVICIO EXTRAORDINARIO | AB1: CERTIFICADO DE ORIGEN | AC1: REPARACION DE DAÑOS DE CONTENEDOR | AD1: LIMPIEZA DE CONTENEDOR | AE1: CUOTA | AF1: DEMORAS | AG1: LIBERACION DE DOCUMENTOS | AK1: MXN | AL1: USD | AM1: TOTAL | AN1: PORCENTAJE
B2: 2-002317 | C2: CGL24122402 | D2: 45660 | E2: C0001 | F2: ARMOR MEXICO IMAGING SUPPLIES | G2: 0 | H2: 16362.29 | I2: 2617.96 | J2: =SUM(G2:I2) -> 18980.25 | K2: 0 | L2: =+J2-K2 -> 18980.25 | M2: MXN | Q2: 0 | S2: 4028.96 | T2: 0 | U2: 0 | V2: 0 | W2: 0 | X2: 0 | Y2: 12333.33 | Z2: 0 | AA2: 0 | AB2: 0 | AC2: 0 | AD2: 0 | AE2: 0 | AF2: 0 | AG2: 0 | AH2: =+SUM(S2:AG2)-H2 -> 0 | AJ2: HONORARIOS | AK2: =+S74 -> 280300.43 | AL2: =+'ENE USD '!AE19 -> 508379.54 | AM2: =SUM(AK2:AL2) -> 788679.97 | AN2: =+AM2/AM24 -> 0.20841218
B3: 2-002318 | C3: CGL24122374 | D3: 45660 | E3: C0001 | F3: ARMOR MEXICO IMAGING SUPPLIES | G3: 0 | H3: 17562.29 | I3: 2809.96 | J3: =SUM(G3:I3) -> 20372.25 | K3: 0 | L3: =+J3-K3 -> 20372.25 | M3: MXN | Q3: 0 | S3: 4028.96 | T3: 0 | U3: 0 | V3: 0 | W3: 1200 | X3: 0 | Y3: 12333.33 | Z3: 0 | AA3: 0 | AB3: 0 | AC3: 0 | AD3: 0 | AE3: 0 | AF3: 0 | AG3: 0 | AH3: =+SUM(S3:AG3)-H3 -> 0 | AJ3: RECONOCIMIENTO ADUANERO | AK3: =+T74 -> 4191 | AM3: =SUM(AK3:AL3) -> 4191 | AN3: =+AM3/AM24 -> 0.0011074903
B4: 1-002319 | C4: CGL24112354 | D4: 45660 | E4: C0001 | F4: ARMOR MEXICO IMAGING SUPPLIES | G4: 0 | H4: 112970.32 | I4: 18075.25 | J4: =SUM(G4:I4) -> 131045.57 | K4: 0 | L4: =+J4-K4 -> 131045.57 | M4: MXN | Q4: 0 | S4: 6058.89 | T4: 0 | U4: 0 | V4: 0 | W4: 29072.04 | X4: 8504.39 | Y4: 69335 | Z4: 0 | AA4: 0 | AB4: 0 | AC4: 0 | AD4: 0 | AE4: 0 | AF4: 0 | AG4: 0 | AH4: =+SUM(S4:AG4)-H4 -> 0 | AJ4: REVALIDACION GUIA / BOL | AK4: =+U74 -> 7846.42 | AM4: =SUM(AK4:AL4) -> 7846.42 | AN4: =+AM4/AM24 -> 0.0020734513
B5: 1-002320 | C5: CGL24122437 | D5: 45660 | E5: C0001 | F5: ARMOR MEXICO IMAGING SUPPLIES | G5: 0 | H5: 3540 | I5: 566.4 | J5: =SUM(G5:I5) -> 4106.4 | K5: 0 | L5: =+J5-K5 -> 4106.4 | M5: MXN | Q5: 0 | S5: 0 | T5: 0 | U5: 0 | V5: 0 | W5: 0 | X5: 0 | Y5: 0 | Z5: 0 | AA5: 0 | AB5: 3540 | AC5: 0 | AD5: 0 | AE5: 0 | AF5: 0 | AG5: 0 | AH5: =+SUM(S5:AG5)-H5 -> 0 | AJ5: SERVICIOS COMPLEMENTARIOS | AK5: =+V74 -> 12350 | AM5: =SUM(AK5:AL5) -> 12350 | AN5: =+AM5/AM24 -> 0.0032635423
B6: 2-002321 | C6: CGL24122431 | D6: 45660 | E6: C0001 | F6: ARMOR MEXICO IMAGING SUPPLIES | G6: 0 | H6: 2928.25 | I6: 468.52 | J6: =SUM(G6:I6) -> 3396.77 | K6: 0 | L6: =+J6-K6 -> 3396.77 | M6: MXN | Q6: 0 | S6: 2928.25 | T6: 0 | U6: 0 | V6: 0 | W6: 0 | X6: 0 | Y6: 0 | Z6: 0 | AA6: 0 | AB6: 0 | AC6: 0 | AD6: 0 | AE6: 0 | AF6: 0 | AG6: 0 | AH6: =+SUM(S6:AG6)-H6 -> 0 | AJ6: MANIOBRAS | AK6: =+W74 -> 513327.14 | AL6: =+'ENE USD '!AC19 -> 715330.51 | AM6: =SUM(AK6:AL6) -> 1228657.6 | AN6: =+AM6/AM24 -> 0.32467823
B7: 2-002322 | C7: CGL24122391 | D7: 45660 | E7: C0001 | F7: ARMOR MEXICO IMAGING SUPPLIES | G7: 0 | H7: 16361.73 | I7: 2617.87 | J7: =SUM(G7:I7) -> 18979.6 | K7: 0 | L7: =+J7-K7 -> 18979.6 | M7: MXN | Q7: 0 | S7: 4028.4 | T7: 0 | U7: 0 | V7: 0 | W7: 0 | X7: 0 | Y7: 12333.33 | Z7: 0 | AA7: 0 | AB7: 0 | AC7: 0 | AD7: 0 | AE7: 0 | AF7: 0 | AG7: 0 | AH7: =+SUM(S7:AG7)-H7 -> 0 | AJ7: ALMACENAJES | AK7: =+X74 -> 153351.11 | AM7: =SUM(AK7:AL7) -> 153351.11 | AN7: =+AM7/AM24 -> 0.040523711
B8: 1-002323 | C8: CGL24122418 | D8: 45660 | E8: C0001 | F8: ARMOR MEXICO IMAGING SUPPLIES | G8: 0 | H8: 10620 | I8: 1699.2 | J8: =SUM(G8:I8) -> 12319.2 | K8: 0 | L8: =+J8-K8 -> 12319.2 | M8: MXN | Q8: 0 | S8: 0 | T8: 0 | U8: 0 | V8: 0 | W8: 0 | X8: 0 | Y8: 0 | Z8: 0 | AA8: 0 | AB8: 10620 | AC8: 0 | AD8: 0 | AE8: 0 | AF8: 0 | AG8: 0 | AH8: =+SUM(S8:AG8)-H8 -> 0 | AJ8: SERVICIOS LOGISTICOS | AK8: =+Y74 -> 957587.41 | AL8: =+'ENE USD '!AB19 -> 465070.83 | AM8: =SUM(AK8:AL8) -> 1422658.2 | AN8: =+AM8/AM24 -> 0.37594375
B9: 1-002324 | C9: CGL24112348 | D9: 45660 | E9: C0001 | F9: ARMOR MEXICO IMAGING SUPPLIES | G9: 0 | H9: 79824.55 | I9: 12771.93 | J9: =SUM(G9:I9) -> 92596.48 | K9: 0 | L9: =+J9-K9 -> 92596.48 | M9: MXN | Q9: 0 | S9: 6074.55 | T9: 0 | U9: 0 | V9: 0 | W9: 25750 | X9: 0 | Y9: 48000 | Z9: 0 | AA9: 0 | AB9: 0 | AC9: 0 | AD9: 0 | AE9: 0 | AF9: 0 | AG9: 0 | AH9: =+SUM(S9:AG9)-H9 -> 0 | AJ9: CONSOLIDACION DE ENTRADAS | AK9: =+Z74 -> 20112.16 | AM9: =SUM(AK9:AL9) -> 20112.16 | AN9: =+AM9/AM24 -> 0.0053147275
B10: 2-002325 | C10: CGL24122383 | D10: 45660 | E10: C0002 | F10: NAPS-GUANAJUATO CAM | G10: 336 | H10: 6908.32 | I10: 1105.33 | J10: =SUM(G10:I10) -> 8349.65 | K10: 8349.65 | L10: =+J10-K10 -> 0 | M10: MXN | Q10: 336 | S10: 2958.32 | T10: 0 | U10: 0 | V10: 0 | W10: 0 | X10: 0 | Y10: 3950 | Z10: 0 | AA10: 0 | AB10: 0 | AC10: 0 | AD10: 0 | AE10: 0 | AF10: 0 | AG10: 0 | AH10: =+SUM(S10:AG10)-H10 -> 0 | AJ10: SERVICIO EXTRAORDINARIO | AK10: =+AA74 -> 1800 | AM10: =SUM(AK10:AL10) -> 1800 | AN10: =+AM10/AM24 -> 0.00047565798
B11: 1-002326 | C11: CGL24082033 | D11: 45665 | E11: C0067 | F11: ND AUTOMOTIVE SYSTEMS MEXICO | G11: 761 | H11: 0.01 | I11: 0 | J11: =SUM(G11:I11) -> 761.01 | K11: 0 | L11: =+J11-K11 -> 761.01 | M11: MXN | Q11: 761 | S11: 0.01 | T11: 0 | U11: 0 | V11: 0 | W11: 0 | X11: 0 | Y11: 0 | Z11: 0 | AA11: 0 | AB11: 0 | AC11: 0 | AD11: 0 | AE11: 0 | AF11: 0 | AG11: 0 | AH11: =+SUM(S11:AG11)-H11 -> 0 | AJ11: CERTIFICADO DE ORIGEN | AK11: =+AB74 -> 17700 | AM11: =SUM(AK11:AL11) -> 17700 | AN11: =+AM11/AM24 -> 0.0046773035
B12: 1-002327 | C12: CGL24122395 | D12: 45666 | E12: C0001 | F12: ARMOR MEXICO IMAGING SUPPLIES | G12: 0 | H12: 106812.52 | I12: 17090 | J12: =SUM(G12:I12) -> 123902.52 | K12: 0 | L12: =+J12-K12 -> 123902.52 | M12: MXN | Q12: 0 | S12: 6070.89 | T12: 0 | U12: 0 | V12: 0 | W12: 29072.04 | X12: 5669.59 | Y12: 66000 | Z12: 0 | AA12: 0 | AB12: 0 | AC12: 0 | AD12: 0 | AE12: 0 | AF12: 0 | AG12: 0 | AH12: =+SUM(S12:AG12)-H12 -> 0 | AJ12: REPARACION DE DAÑOS DE CONTENEDOR | AK12: =+AC74 -> 1000 | AM12: =SUM(AK12:AL12) -> 1000 | AN12: =+AM12/AM24 -> 0.00026425444
B13: 1-002328 | C13: CGL24122396 | D13: 45666 | E13: C0001 | F13: ARMOR MEXICO IMAGING SUPPLIES | G13: 0 | H13: 84790.76 | I13: 13566.52 | J13: =SUM(G13:I13) -> 98357.28 | K13: 0 | L13: =+J13-K13 -> 98357.28 | M13: MXN | Q13: 0 | S13: 6132.06 | T13: 0 | U13: 0 | V13: 0 | W13: 25750 | X13: 6573.7 | Y13: 45335 | Z13: 0 | AA13: 0 | AB13: 0 | AC13: 1000 | AD13: 0 | AE13: 0 | AF13: 0 | AG13: 0 | AH13: =+SUM(S13:AG13)-H13 -> 0 | AJ13: LIMPIEZA DE CONTENEDOR | AK13: =+AD74 -> 0 | AM13: =SUM(AK13:AL13) -> 0 | AN13: =+AM13/AM24 -> 0
B14: 2-002329 | C14: CGL24122392 | D14: 45666 | E14: C0001 | F14: ARMOR MEXICO IMAGING SUPPLIES | G14: 0 | H14: 18579.25 | I14: 2972.68 | J14: =SUM(G14:I14) -> 21551.93 | K14: 0 | L14: =+J14-K14 -> 21551.93 | M14: MXN | Q14: 0 | S14: 4157.24 | T14: 0 | U14: 0 | V14: 0 | W14: 0 | X14: 0 | Y14: 14422.01 | Z14: 0 | AA14: 0 | AB14: 0 | AC14: 0 | AD14: 0 | AE14: 0 | AF14: 0 | AG14: 0 | AH14: =+SUM(S14:AG14)-H14 -> 0 | AJ14: LIBERACION DE DOCUMENTOS | AK14: =+AG74 -> 8902 | AL14: =+'ENE USD '!AD19 -> 10756.743 | AM14: =SUM(AK14:AL14) -> 19658.743 | AN14: =+AM14/AM24 -> 0.0051949099
B15: 1-002330 | C15: CGL24112312 | D15: 45666 | E15: C0069 | F15: JOINT PRODUCTION HONOR | G15: 180702 | H15: 205227.85 | I15: 32836.46 | J15: =SUM(G15:I15) -> 418766.31 | K15: 406517.64 | L15: =+J15-K15 -> 12248.67 | M15: MXN | Q15: 180702 | S15: 7350.23 | T15: 0 | U15: 0 | V15: 0 | W15: 93226.54 | X15: 104651.08 | Y15: 0 | Z15: 0 | AA15: 0 | AB15: 0 | AC15: 0 | AD15: 0 | AE15: 0 | AF15: 0 | AG15: 0 | AH15: =+SUM(S15:AG15)-H15 -> 0 | AJ15: DEMORAS | AK15: =+AF74 -> 44880 | AM15: =SUM(AK15:AL15) -> 44880 | AN15: =+AM15/AM24 -> 0.011859739
B16: 1-002331 | C16: CGL24122433 | D16: 45667 | E16: C0001 | F16: ARMOR MEXICO IMAGING SUPPLIES | G16: 0 | H16: 27182.81 | I16: 4349.25 | J16: =SUM(G16:I16) -> 31532.06 | K16: 0 | L16: =+J16-K16 -> 31532.06 | M16: MXN | Q16: 0 | S16: 4031.16 | T16: 0 | U16: 3500 | V16: 500 | W16: 9004.06 | X16: 1372.59 | Y16: 8775 | Z16: 0 | AA16: 0 | AB16: 0 | AC16: 0 | AD16: 0 | AE16: 0 | AF16: 0 | AG16: 0 | AH16: =+SUM(S16:AG16)-H16 -> 0 | AJ16: GASTOS EN DESTINO | AL16: =+'ENE USD '!AF19 -> 56526.293 | AM16: =SUM(AK16:AL16) -> 56526.293 | AN16: =+AM16/AM24 -> 0.014937324
B17: 1-002332 | C17: CGL24122379 | D17: 45670 | E17: C0069 | F17: JOINT PRODUCTION HONOR | G17: 761 | H17: 16728.86 | I17: 2676.62 | J17: =SUM(G17:I17) -> 20166.48 | K17: 20166.48 | L17: =+J17-K17 -> 0 | M17: MXN | Q17: 761 | S17: 7285.06 | T17: 0 | U17: 0 | V17: 0 | W17: 9443.8 | X17: 0 | Y17: 0 | Z17: 0 | AA17: 0 | AB17: 0 | AC17: 0 | AD17: 0 | AE17: 0 | AF17: 0 | AG17: 0 | AH17: =+SUM(S17:AG17)-H17 -> 0 | AJ17: CUOTA | AK17: =+AE74 -> 3277.5 | AL17: =+'ENE USD '!AG19 -> 1542.5775 | AM17: =SUM(AK17:AL17) -> 4820.0775 | AN17: =+AM17/AM24 -> 0.0012737269
B18: 2-002333 | C18: CGL24122390 | D18: 45670 | E18: C0002 | F18: NAPS-GUANAJUATO CAM | G18: 29608 | H18: 15835.71 | I18: 2533.72 | J18: =SUM(G18:I18) -> 47977.43 | K18: 54204.42 | L18: =+J18-K18 -> -6226.99 | M18: MXN | Q18: 29608 | S18: 4134.16 | T18: 0 | U18: 0 | V18: 0 | W18: 0 | X18: 0 | Y18: 3950 | Z18: 7751.55 | AA18: 0 | AB18: 0 | AC18: 0 | AD18: 0 | AE18: 0 | AF18: 0 | AG18: 0 | AH18: =+SUM(S18:AG18)-H18 -> 0 | AM18: =SUM(AK18:AL18) -> 0 | AN18: =+AM18/AM24 -> 0
B19: 1-002335 | C19: CGL24122417 | D19: 45670 | E19: C0067 | F19: ND AUTOMOTIVE SYSTEMS MEXICO | G19: 1192.68 | H19: 26279.86 | I19: 4204.78 | J19: =SUM(G19:I19) -> 31677.32 | K19: 0 | L19: =+J19-K19 -> 31677.32 | M19: MXN | P19: 1192.68 | Q19: 0 | S19: 6029.86 | T19: 0 | U19: 0 | V19: 0 | W19: 0 | X19: 0 | Y19: 20250 | Z19: 0 | AA19: 0 | AB19: 0 | AC19: 0 | AD19: 0 | AE19: 0 | AF19: 0 | AG19: 0 | AH19: =+SUM(S19:AG19)-H19 -> 0
B20: 2-002336 | C20: CGL24122414 | D20: 45671 | E20: C0002 | F20: NAPS-GUANAJUATO CAM | G20: 7626 | H20: 8006.14 | I20: 1280.98 | J20: =SUM(G20:I20) -> 16913.12 | K20: 16913.12 | L20: =+J20-K20 -> 0 | M20: MXN | Q20: 7626 | S20: 4056.14 | T20: 0 | U20: 0 | V20: 3950 | W20: 0 | X20: 0 | Y20: 0 | Z20: 0 | AA20: 0 | AB20: 0 | AC20: 0 | AD20: 0 | AE20: 0 | AF20: 0 | AG20: 0 | AH20: =+SUM(S20:AG20)-H20 -> 0
B21: 2-002337 | C21: CGL25012441 | D21: 45671 | E21: C0002 | F21: NAPS-GUANAJUATO CAM | G21: 781 | H21: 8013.9 | I21: 1282.22 | J21: =SUM(G21:I21) -> 10077.12 | K21: 10077.12 | L21: =+J21-K21 -> 0 | M21: MXN | Q21: 781 | S21: 4063.9 | T21: 0 | U21: 0 | V21: 0 | W21: 0 | X21: 0 | Y21: 3950 | Z21: 0 | AA21: 0 | AB21: 0 | AC21: 0 | AD21: 0 | AE21: 0 | AF21: 0 | AG21: 0 | AH21: =+SUM(S21:AG21)-H21 -> 0
B22: 2-002338 | C22: CGL25012442 | D22: 45671 | E22: C0002 | F22: NAPS-GUANAJUATO CAM | G22: 5735 | H22: 8008.72 | I22: 1281.4 | J22: =SUM(G22:I22) -> 15025.12 | K22: 15025.12 | L22: =+J22-K22 -> 0 | M22: MXN | Q22: 5735 | S22: 4058.72 | T22: 0 | U22: 0 | V22: 0 | W22: 0 | X22: 0 | Y22: 3950 | Z22: 0 | AA22: 0 | AB22: 0 | AC22: 0 | AD22: 0 | AE22: 0 | AF22: 0 | AG22: 0 | AH22: =+SUM(S22:AG22)-H22 -> 0
B23: 2-002339 | C23: CGL25012452 | D23: 45671 | E23: C0002 | F23: NAPS-GUANAJUATO CAM | G23: 781 | H23: 8013.9 | I23: 1282.22 | J23: =SUM(G23:I23) -> 10077.12 | K23: 10077.12 | L23: =+J23-K23 -> 0 | M23: MXN | Q23: 781 | S23: 4063.9 | T23: 0 | U23: 0 | V23: 0 | W23: 0 | X23: 0 | Y23: 3950 | Z23: 0 | AA23: 0 | AB23: 0 | AC23: 0 | AD23: 0 | AE23: 0 | AF23: 0 | AG23: 0 | AH23: =+SUM(S23:AG23)-H23 -> 0 | AK23: 0 | AM23: =SUM(AK23:AL23) -> 0 | AN23: =+AM23/AM24 -> 0
B24: 2-002340 | C24: CGL24122420 | D24: 45671 | E24: C0002 | F24: NAPS-GUANAJUATO CAM | G24: 1231 | H24: 12013.9 | I24: 1922.22 | J24: =SUM(G24:I24) -> 15167.12 | K24: 10526.12 | L24: =+J24-K24 -> 4641 | M24: MXN | Q24: 1231 | S24: 4063.9 | T24: 1500 | U24: 0 | V24: 0 | W24: 2500 | X24: 0 | Y24: 3950 | Z24: 0 | AA24: 0 | AB24: 0 | AC24: 0 | AD24: 0 | AE24: 0 | AF24: 0 | AG24: 0 | AH24: =+SUM(S24:AG24)-H24 -> 0 | AK24: =+SUM(AK2:AK23) -> 2026625.2 | AL24: =+SUM(AL2:AL23) -> 1757606.5 | AM24: =+SUM(AM2:AM23) -> 3784231.7 | AN24: =+SUM(AN2:AN23) -> 1
B25: 2-002341 | C25: CGL24122385 | D25: 45671 | E25: C0002 | F25: NAPS-GUANAJUATO CAM | G25: 336 | H25: 8114.5 | I25: 1298.32 | J25: =SUM(G25:I25) -> 9748.82 | K25: 9748.82 | L25: =+J25-K25 -> 0 | M25: MXN | Q25: 336 | S25: 4164.5 | T25: 0 | U25: 0 | V25: 0 | W25: 0 | X25: 0 | Y25: 3950 | Z25: 0 | AA25: 0 | AB25: 0 | AC25: 0 | AD25: 0 | AE25: 0 | AF25: 0 | AG25: 0 | AH25: =+SUM(S25:AG25)-H25 -> 0
B26: 2-002342 | C26: CGL24122384 | D26: 45672 | E26: C0002 | F26: NAPS-GUANAJUATO CAM | G26: 336 | H26: 8054.06 | I26: 1288.65 | J26: =SUM(G26:I26) -> 9678.71 | K26: 9678.71 | L26: =+J26-K26 -> 0 | M26: MXN | Q26: 336 | S26: 4104.06 | T26: 0 | U26: 0 | V26: 0 | W26: 0 | X26: 0 | Y26: 3950 | Z26: 0 | AA26: 0 | AB26: 0 | AC26: 0 | AD26: 0 | AE26: 0 | AF26: 0 | AG26: 0 | AH26: =+SUM(S26:AG26)-H26 -> 0
B27: 2-002343 | C27: CGL25012444 | D27: 45672 | E27: C0002 | F27: NAPS-GUANAJUATO CAM | G27: 336 | H27: 8026.46 | I27: 1284.23 | J27: =SUM(G27:I27) -> 9646.69 | K27: 9646.69 | L27: =+J27-K27 -> 0 | M27: MXN | Q27: 336 | S27: 4076.46 | T27: 0 | U27: 0 | V27: 0 | W27: 0 | X27: 0 | Y27: 3950 | Z27: 0 | AA27: 0 | AB27: 0 | AC27: 0 | AD27: 0 | AE27: 0 | AF27: 0 | AG27: 0 | AH27: =+SUM(S27:AG27)-H27 -> 0
B28: 1-002344 | C28: CGL24122434 | D28: 45674 | E28: C0069 | F28: JOINT PRODUCTION HONOR | G28: 781 | H28: 38843.08 | I28: 6214.89 | J28: =SUM(G28:I28) -> 45838.97 | K28: 50246.84 | L28: =+J28-K28 -> -4407.87 | M28: MXN | Q28: 781 | S28: 7259.65 | T28: 2691 | U28: 0 | V28: 0 | W28: 28892.43 | X28: 0 | Y28: 0 | Z28: 0 | AA28: 0 | AB28: 0 | AC28: 0 | AD28: 0 | AE28: 0 | AF28: 0 | AG28: 0 | AH28: =+SUM(S28:AG28)-H28 -> 0
B29: 1-002345 | C29: CGL24122393 | D29: 45677 | E29: C0004 | F29: NAPS-GUANAJUATO AMERICAN BOA | G29: 781 | H29: 87814.69 | I29: 14050.35 | J29: =SUM(G29:I29) -> 102646.04 | K29: 102720.56 | L29: =+J29-K29 -> -74.52 | M29: MXN | Q29: 781 | S29: 6114.69 | T29: 0 | U29: 0 | V29: 0 | W29: 25000 | X29: 0 | Y29: 56700 | Z29: 0 | AA29: 0 | AB29: 0 | AC29: 0 | AD29: 0 | AE29: 0 | AF29: 0 | AG29: 0 | AH29: =+SUM(S29:AG29)-H29 -> 0
B30: 2-002346 | C30: CGL25012457 | D30: 45677 | E30: C0084 | F30: JOINT PRODUCTION TECTRAN | G30: 0 | H30: 43000 | I30: 6880 | J30: =SUM(G30:I30) -> 49880 | K30: 49880 | L30: =+J30-K30 -> 0 | M30: MXN | Q30: 0 | S30: 0 | T30: 0 | U30: 0 | V30: 0 | W30: 0 | X30: 0 | Y30: 43000 | Z30: 0 | AA30: 0 | AB30: 0 | AC30: 0 | AD30: 0 | AE30: 0 | AF30: 0 | AG30: 0 | AH30: =+SUM(S30:AG30)-H30 -> 0
B31: 2-002347 | C31: CGL24122428 | D31: 45677 | E31: C0024 | F31: SELLOS Y RETENES DE SAN LUIS | G31: 23360 | H31: 4076.46 | I31: 652.23 | J31: =SUM(G31:I31) -> 28088.69 | K31: 27212.69 | L31: =+J31-K31 -> 876 | M31: MXN | Q31: 23360 | S31: 4076.46 | T31: 0 | U31: 0 | V31: 0 | W31: 0 | X31: 0 | Y31: 0 | Z31: 0 | AA31: 0 | AB31: 0 | AC31: 0 | AD31: 0 | AE31: 0 | AF31: 0 | AG31: 0 | AH31: =+SUM(S31:AG31)-H31 -> 0
B32: 2-002348 | C32: CGL24122429 | D32: 45677 | E32: C0002 | F32: NAPS-GUANAJUATO CAM | G32: 336 | H32: 4738.54 | I32: 758.17 | J32: =SUM(G32:I32) -> 5832.71 | K32: 5832.71 | L32: =+J32-K32 -> 0 | M32: MXN | Q32: 336 | S32: 4138.54 | T32: 0 | U32: 0 | V32: 0 | W32: 0 | X32: 0 | Y32: 0 | Z32: 0 | AA32: 600 | AB32: 0 | AC32: 0 | AD32: 0 | AE32: 0 | AF32: 0 | AG32: 0 | AH32: =+SUM(S32:AG32)-H32 -> 0
B33: 1-002349 | C33: CGL24122404 | D33: 45678 | E33: C0004 | F33: NAPS-GUANAJUATO AMERICAN BOA | G33: 781 | H33: 73564.69 | I33: 11770.35 | J33: =SUM(G33:I33) -> 86116.04 | K33: 86206.6 | L33: =+J33-K33 -> -90.56 | M33: MXN | Q33: 781 | S33: 6114.69 | T33: 0 | U33: 0 | V33: 0 | W33: 20000 | X33: 0 | Y33: 47450 | Z33: 0 | AA33: 0 | AB33: 0 | AC33: 0 | AD33: 0 | AE33: 0 | AF33: 0 | AG33: 0 | AH33: =+SUM(S33:AG33)-H33 -> 0
B34: 2-002350 | C34: CGL25012465 | D34: 45679 | E34: C0084 | F34: JOINT PRODUCTION TECTRAN | G34: 0 | H34: 7450 | I34: 1192 | J34: =SUM(G34:I34) -> 8642 | K34: 8642 | L34: =+J34-K34 -> 0 | M34: MXN | Q34: 0 | S34: 0 | T34: 0 | U34: 0 | V34: 0 | W34: 0 | X34: 0 | Y34: 7450 | Z34: 0 | AA34: 0 | AB34: 0 | AC34: 0 | AD34: 0 | AE34: 0 | AF34: 0 | AG34: 0 | AH34: =+SUM(S34:AG34)-H34 -> 0
B35: 1-002351 | C35: CGL25012440 | D35: 45679 | E35: C0001 | F35: ARMOR MEXICO IMAGING SUPPLIES | G35: 0 | H35: 101167.89 | I35: 16186.87 | J35: =SUM(G35:I35) -> 117354.76 | K35: 0 | L35: =+J35-K35 -> 117354.76 | M35: MXN | Q35: 0 | S35: 6095.85 | T35: 0 | U35: 0 | V35: 0 | W35: 29072.04 | X35: 0 | Y35: 66000 | Z35: 0 | AA35: 0 | AB35: 0 | AC35: 0 | AD35: 0 | AE35: 0 | AF35: 0 | AG35: 0 | AH35: =+SUM(S35:AG35)-H35 -> 0
B36: 2-002352 | C36: CGL25012474 | D36: 45679 | E36: C0084 | F36: JOINT PRODUCTION TECTRAN | G36: 0 | H36: 20000 | I36: 3200 | J36: =SUM(G36:I36) -> 23200 | K36: 23200 | L36: =+J36-K36 -> 0 | M36: MXN | Q36: 0 | S36: 0 | T36: 0 | U36: 0 | V36: 0 | W36: 0 | X36: 0 | Y36: 20000 | Z36: 0 | AA36: 0 | AB36: 0 | AC36: 0 | AD36: 0 | AE36: 0 | AF36: 0 | AG36: 0 | AH36: =+SUM(S36:AG36)-H36 -> 0
... B54: 1-002374 | C54: CGL25012439 | D54: 45685 | E54: C0004 | F54: NAPS-GUANAJUATO AMERICAN BOA | G54: 781 | H54: 86910 | I54: 13905.6 | J54: =SUM(G54:I54) -> 101596.6 | K54: 101596.6 | L54: =+J54-K54 -> 0 | M54: MXN | Q54: 781 | S54: 6210 | T54: 0 | U54: 0 | V54: 0 | W54: 24000 | X54: 0 | Y54: 56700 | Z54: 0 | AA54: 0 | AB54: 0 | AC54: 0 | AD54: 0 | AE54: 0 | AF54: 0 | AG54: 0 | AH54: =+SUM(S54:AG54)-H54 -> 0
B55: 1-002375 | C55: CGL25012485 | D55: 45685 | E55: C0004 | F55: NAPS-GUANAJUATO AMERICAN BOA | G55: 3599.6 | H55: 1627.5 | I55: 0 | J55: =SUM(G55:I55) -> 5227.1 | K55: 5227.1 | L55: =+J55-K55 -> 0 | M55: MXN | P55: 3599.6 | Q55: 0 | S55: 0 | T55: 0 | U55: 0 | V55: 0 | W55: 0 | X55: 0 | Y55: 0 | Z55: 0 | AA55: 0 | AB55: 0 | AC55: 0 | AD55: 0 | AE55: 1627.5 | AF55: 0 | AG55: 0 | AH55: =+SUM(S55:AG55)-H55 -> 0
B56: 2-002376 | C56: CGL24122407 | D56: 45685 | E56: C0002 | F56: NAPS-GUANAJUATO CAM | G56: 47221 | H56: 15815.59 | I56: 2530.5 | J56: =SUM(G56:I56) -> 65567.09 | K56: 65787.08 | L56: =+J56-K56 -> -219.99 | M56: MXN | Q56: 47221 | S56: 4127.16 | T56: 0 | U56: 0 | V56: 0 | W56: 0 | X56: 0 | Y56: 3950 | Z56: 7738.43 | AA56: 0 | AB56: 0 | AC56: 0 | AD56: 0 | AE56: 0 | AF56: 0 | AG56: 0 | AH56: =+SUM(S56:AG56)-H56 -> 0
B57: 1-002377 | C57: CGL25012473 | D57: 45687 | E57: C0069 | F57: JOINT PRODUCTION HONOR | G57: 781 | H57: 14016.38 | I57: 2242.62 | J57: =SUM(G57:I57) -> 17040 | K57: 21121.67 | L57: =+J57-K57 -> -4081.67 | M57: MXN | Q57: 781 | S57: 7370.71 | T57: 0 | U57: 608.92 | V57: 0 | W57: 2121.75 | X57: 0 | Y57: 3915 | Z57: 0 | AA57: 0 | AB57: 0 | AC57: 0 | AD57: 0 | AE57: 0 | AF57: 0 | AG57: 0 | AH57: =+SUM(S57:AG57)-H57 -> 0
B58: 1-002378 | C58: CGL25012494 | D58: 45687 | E58: C0069 | F58: JOINT PRODUCTION HONOR | G58: 781 | H58: 34614.5 | I58: 5538.32 | J58: =SUM(G58:I58) -> 40933.82 | K58: 145355.37 | L58: =+J58-K58 -> -104421.55 | M58: MXN | Q58: 781 | S58: 7478.35 | T58: 0 | U58: 0 | V58: 0 | W58: 27136.15 | X58: 0 | Y58: 0 | Z58: 0 | AA58: 0 | AB58: 0 | AC58: 0 | AD58: 0 | AE58: 0 | AF58: 0 | AG58: 0 | AH58: =+SUM(S58:AG58)-H58 -> 0
B59: 2-002379 | C59: CGL25012498 | D59: 45687 | E59: C0081 | F59: JOINT PRODUCTION BLACK SMITH | G59: 0 | H59: 22000 | I59: 3520 | J59: =SUM(G59:I59) -> 25520 | K59: 25520 | L59: =+J59-K59 -> 0 | M59: MXN | Q59: 0 | S59: 0 | T59: 0 | U59: 0 | V59: 0 | W59: 0 | X59: 0 | Y59: 22000 | Z59: 0 | AA59: 0 | AB59: 0 | AC59: 0 | AD59: 0 | AE59: 0 | AF59: 0 | AG59: 0 | AH59: =+SUM(S59:AG59)-H59 -> 0
B60: 2-002383 | C60: CGL25012482 | D60: 45687 | E60: C0084 | F60: JOINT PRODUCTION TECTRAN | G60: 0 | H60: 27288.7 | I60: 4366.19 | J60: =SUM(G60:I60) -> 31654.89 | K60: 31654.89 | L60: =+J60-K60 -> 0 | M60: MXN | Q60: 0 | S60: 0 | T60: 0 | U60: 0 | V60: 0 | W60: 0 | X60: 0 | Y60: 27288.7 | Z60: 0 | AA60: 0 | AB60: 0 | AC60: 0 | AD60: 0 | AE60: 0 | AF60: 0 | AG60: 0 | AH60: =+SUM(S60:AG60)-H60 -> 0
B61: 2-002384 | C61: CGL25012484 | D61: 45688 | E61: C0012 | F61: MEGALUMINIO SERVICIOS | G61: 45257 | H61: 7483.43 | I61: 1197.35 | J61: =SUM(G61:I61) -> 53937.78 | K61: 53937.78 | L61: =+J61-K61 -> 0 | M61: MXN | Q61: 45257 | S61: 4449.6 | T61: 0 | U61: 0 | V61: 0 | W61: 0 | X61: 0 | Y61: 3033.83 | Z61: 0 | AA61: 0 | AB61: 0 | AC61: 0 | AD61: 0 | AE61: 0 | AF61: 0 | AG61: 0 | AH61: =+SUM(S61:AG61)-H61 -> 0
B62: 1-002385 | C62: CGL24112357 | D62: 45688 | E62: C0012 | F62: MEGALUMINIO SERVICIOS | G62: 0 | H62: 2170 | I62: 0 | J62: =SUM(G62:I62) -> 2170 | K62: 2170 | L62: =+J62-K62 -> 0 | M62: MXN | Q62: 0 | S62: 0 | T62: 0 | U62: 0 | V62: 0 | W62: 0 | X62: 0 | Y62: 0 | Z62: 0 | AA62: 0 | AB62: 0 | AC62: 0 | AD62: 0 | AE62: 0 | AF62: 0 | AG62: 2170 | AH62: =+SUM(S62:AG62)-H62 -> 0
B63: 2-002386 | C63: CGL25012504 | D63: 45688 | E63: C0002 | F63: NAPS-GUANAJUATO | G63: 336 | H63: 14110.06 | I63: 2257.61 | J63: =SUM(G63:I63) -> 16703.67 | K63: 16703.67 | L63: =+J63-K63 -> 0 | M63: MXN | Q63: 336 | S63: 6210.06 | T63: 0 | U63: 0 | V63: 0 | W63: 0 | X63: 0 | Y63: 7900 | Z63: 0 | AA63: 0 | AB63: 0 | AC63: 0 | AD63: 0 | AE63: 0 | AF63: 0 | AG63: 0 | AH63: =+SUM(S63:AG63)-H63 -> 0
B64: 2-002388 | C64: CGL25012503 | D64: 45688 | E64: C0002 | F64: NAPS-GUANAJUATO | G64: 336 | H64: 14710.06 | I64: 2353.61 | J64: =SUM(G64:I64) -> 17399.67 | K64: 17399.67 | L64: =+J64-K64 -> 0 | M64: MXN | Q64: 336 | S64: 6210.06 | T64: 0 | U64: 0 | V64: 0 | W64: 0 | X64: 0 | Y64: 7900 | Z64: 0 | AA64: 600 | AB64: 0 | AC64: 0 | AD64: 0 | AE64: 0 | AF64: 0 | AG64: 0 | AH64: =+SUM(S64:AG64)-H64 -> 0
B65: 1-002389 | C65: CGL25012438 | D65: 45688 | E65: C0079 | F65: CORE GLOBAL TRANSPORT | G65: 32365 | H65: 29447.57 | I65: 4711.61 | J65: =SUM(G65:I65) -> 66524.18 | K65: 66524.18 | L65: =+J65-K65 -> 0 | M65: MXN | Q65: 32365 | S65: 8179.88 | T65: 0 | U65: 0 | V65: 0 | W65: 9815.86 | X65: 0 | Y65: 11451.83 | Z65: 0 | AA65: 0 | AB65: 0 | AC65: 0 | AD65: 0 | AE65: 0 | AF65: 0 | AG65: 0 | AH65: =+SUM(S65:AG65)-H65 -> 0
B66: 2-002390 | C66: CGL25012520 | D66: 45688 | E66: C0084 | F66: JOINT PRODUCTION | G66: 0 | H66: 21730.96 | I66: 3476.95 | J66: =SUM(G66:I66) -> 25207.91 | K66: 25207.92 | L66: =+J66-K66 -> -0.01 | M66: MXN | Q66: 0 | S66: 0 | T66: 0 | U66: 0 | V66: 0 | W66: 0 | X66: 0 | Y66: 21730.96 | Z66: 0 | AA66: 0 | AB66: 0 | AC66: 0 | AD66: 0 | AE66: 0 | AF66: 0 | AG66: 0 | AH66: =+SUM(S66:AG66)-H66 -> 0
B67: 2-002391 | C67: CGL25012500 | D67: 45688 | E67: C0084 | F67: JOINT PRODUCTION | G67: 0 | H67: 17400 | I67: 2784 | J67: =SUM(G67:I67) -> 20184 | K67: 20184 | L67: =+J67-K67 -> 0 | M67: MXN | Q67: 0 | S67: 0 | T67: 0 | U67: 0 | V67: 0 | W67: 0 | X67: 0 | Y67: 17400 | Z67: 0 | AA67: 0 | AB67: 0 | AC67: 0 | AD67: 0 | AE67: 0 | AF67: 0 | AG67: 0 | AH67: =+SUM(S67:AG67)-H67 -> 0
... B69: 1-002393 | C69: CGL25012483 | D69: 45688 | E69: C0004 | F69: NAPS-GUANAJUATO | G69: 781 | H69: 98665 | I69: 15786.4 | J69: =SUM(G69:I69) -> 115232.4 | K69: 115232.4 | L69: =+J69-K69 -> 0 | M69: MXN | Q69: 781 | S69: 6210 | T69: 0 | U69: 0 | V69: 0 | W69: 32455 | X69: 0 | Y69: 60000 | Z69: 0 | AA69: 0 | AB69: 0 | AC69: 0 | AD69: 0 | AE69: 0 | AF69: 0 | AG69: 0 | AH69: =+SUM(S69:AG69)-H69 -> 0
M73: MXN | AH73: =+SUM(S73:AG73)-H73 -> 0
G74: =+SUM(G2:G73) -> 863944.28 | H74: =+SUM(H2:H73) -> 2026625.2 | I74: =+SUM(I2:I73) -> 315130.48 | J74: =+SUM(J2:J73) -> 3205699.9 | K74: =+SUM(K2:K73) -> 2488411.8 | L74: =+SUM(L2:L73) -> 717288.08 | P74: =+SUM(P2:P73) -> 4792.28 | Q74: =+SUM(Q2:Q73) -> 859152 | S74: =+SUM(S2:S73) -> 280300.43 | T74: =+SUM(T2:T73) -> 4191 | U74: =+SUM(U2:U73) -> 7846.42 | V74: =+SUM(V2:V73) -> 12350 | W74: =+SUM(W2:W73) -> 513327.14 | X74: =+SUM(X2:X73) -> 153351.11 | Y74: =+SUM(Y2:Y73) -> 957587.41 | Z74: =+SUM(Z2:Z73) -> 20112.16 | ... AH74: =+SUM(AH2:AH73) -> 0
H78: BASE 16% | I78: BASE 0% | J78: IVA 16% | K78: T O T A L
B79: TOTAL FACTURACION | D79: =+H81+I81 -> 3784231.7 | G79: TOTAL MXN | H79: =+H74-I79 -> 1969565.7 | I79: =+H62+H55+H40+H11 -> 57059.51 | J79: =+H79*0.16 -> 315130.51 | K79: =+SUM(H79:J79) -> 2341755.7
A80: ( vs ) | B80: TOTAL SAT | D80: =2026625.17+'ENE USD '!N19 -> 3784231.7 | G80: TOTAL USD | H80: =+'ENE USD '!N9 -> 7712.8875 | I80: =+'ENE USD '!N3+'ENE USD '!N4+'ENE USD '!N5+'ENE USD '!N6+'ENE USD '!N7+'ENE USD '!N8+'ENE USD '!N10+'ENE USD '!N11 -> 1749893.6 | J80: =+H80*0.16 -> 1234.062 | K80: =+SUM(H80:J80) -> 1758840.6
A81: ( = ) | B81: DIFERENCIA | D81: =+D79-D80 -> 0 | H81: =+SUM(H79:H80) -> 1977278.5 | I81: =+SUM(I79:I80) -> 1806953.1 | J81: =+SUM(J79:J80) -> 316364.57 | K81: =+SUM(K79:K80) -> 4100596.2
G83: TOTAL FACTURADOS | H83: =+H81+I81 -> 3784231.7

Sheet ENE USD 
G1: INFORMACION EN USD | N1: INFORMACION EN MXN
A2: SERIE | B2: FACTURA | C2: TRAFICO | D2: FECHA | E2: CLIENTE | F2: CLIENTENOMBRE | G2: COMPROBADOS | H2: COMPLEMENTARIOS | I2: IVA | J2: SUBTOTAL | K2: ANTICIPO | L2: TOTAL | M2: TIPOCAMBIO | N2: COMPLEMENTARIOS | O2: IVA | P2: SUBTOTAL | Q2: ANTICIPO | R2: TOTAL | U2: SERVICIO LOGISTICO | V2: MANIOBRAS | W2: LIBERACION DE DOCUMENTOS | X2: HONORARIOS | Y2: GASTOS EN DESTINO | Z2: CUOTA | AB2: SERVICIO LOGISTICO | AC2: MANIOBRAS | AD2: LIBERACION DE DOCUMENTOS | AE2: HONORARIOS | AF2: GASTOS EN DESTINO | AG2: CUOTA
B3: 1-002334 | C3: CGL24122417 | D3: 45670 | E3: C0067 | F3: ND AUTOMOTIVE SYSTEMS MEXICO | G3: 0 | H3: =994+525.49 -> 1519.49 | I3: 0 | J3: =SUM(G3:I3) -> 1519.49 | K3: 0 | L3: =J3-K3 -> 1519.49 | M3: 20.7045 | N3: =H3*M3 -> 31460.281 | O3: =I3*M3 -> 0 | P3: =J3*M3 -> 31460.281 | Q3: =M3*K3 -> 0 | R3: =L3*M3 -> 31460.281 | U3: 994 | Y3: 525.49 | AB3: =U3*M3 -> 20580.273 | AC3: =+V3*M3 -> 0 | AD3: =+M3*W3 -> 0 | AE3: =+X3*M3 -> 0 | AF3: =+Y3*M3 -> 10880.008 | AG3: =+Z3*M3 -> 0
B4: 2-002356 | C4: CGL24112355 | D4: 45680 | E4: C0084 | F4: JOINT PRODUCTION TECTRAN | G4: 0 | H4: 875 | I4: 0 | J4: =SUM(G4:I4) -> 875 | K4: 0 | L4: =J4-K4 -> 875 | M4: 20.7045 | N4: =H4*M4 -> 18116.438 | O4: =I4*M4 -> 0 | P4: =J4*M4 -> 18116.438 | Q4: =M4*K4 -> 0 | R4: =L4*M4 -> 18116.438 | U4: 875 | AB4: =U4*M4 -> 18116.438 | AC4: =+V4*M4 -> 0 | AD4: =+M4*W4 -> 0 | AE4: =+X4*M4 -> 0 | AF4: =+Y4*M4 -> 0 | AG4: =+Z4*M4 -> 0
B5: 2-002357 | C5: CGL24122435 | D5: 45680 | E5: C0084 | F5: JOINT PRODUCTION TECTRAN | G5: 0 | H5: 6850 | I5: 0 | J5: =SUM(G5:I5) -> 6850 | K5: 0 | L5: =J5-K5 -> 6850 | M5: 20.482 | N5: =H5*M5 -> 140301.7 | O5: =I5*M5 -> 0 | P5: =J5*M5 -> 140301.7 | Q5: =M5*K5 -> 0 | R5: =L5*M5 -> 140301.7 | U5: 6850 | AB5: =U5*M5 -> 140301.7 | AC5: =+V5*M5 -> 0 | AD5: =+M5*W5 -> 0 | AE5: =+X5*M5 -> 0 | AF5: =+Y5*M5 -> 0 | AG5: =+Z5*M5 -> 0
B6: 1-002358 | C6: CGL24122430 | D6: 45681 | E6: C0089 | F6: CHEMICAL COLOR DE MEXICO | G6: 0 | H6: =3750+360 -> 4110 | I6: 0 | J6: =SUM(G6:I6) -> 4110 | K6: 4110 | L6: =J6-K6 -> 0 | M6: 20.3943 | N6: =H6*M6 -> 83820.573 | O6: =I6*M6 -> 0 | P6: =J6*M6 -> 83820.573 | Q6: =M6*K6 -> 83820.573 | R6: =L6*M6 -> 0 | U6: 3750 | Y6: 360 | AB6: =U6*M6 -> 76478.625 | AC6: =+V6*M6 -> 0 | AD6: =+M6*W6 -> 0 | AE6: =+X6*M6 -> 0 | AF6: =+Y6*M6 -> 7341.948 | AG6: =+Z6*M6 -> 0
B7: 1-002360 | C7: CGL24122432 | D7: 45681 | E7: C0001 | F7: ARMOR MEXICO IMAGING SUPPLIES | G7: 0 | H7: =4100+1500 -> 5600 | I7: 0 | J7: =SUM(G7:I7) -> 5600 | K7: 0 | L7: =J7-K7 -> 5600 | M7: 20.3943 | N7: =H7*M7 -> 114208.08 | O7: =I7*M7 -> 0 | P7: =J7*M7 -> 114208.08 | Q7: =M7*K7 -> 0 | R7: =L7*M7 -> 114208.08 | U7: 4100 | Y7: 1500 | AB7: =U7*M7 -> 83616.63 | AC7: =+V7*M7 -> 0 | AD7: =+M7*W7 -> 0 | AE7: =+X7*M7 -> 0 | AF7: =+Y7*M7 -> 30591.45 | AG7: =+Z7*M7 -> 0
B8: 2-002380 | C8: CGL25012470 | D8: 45687 | E8: C0084 | F8: JOINT PRODUCTION TECTRAN | G8: 0 | H8: 6125 | I8: 0 | J8: =SUM(G8:I8) -> 6125 | K8: 0 | L8: =J8-K8 -> 6125 | M8: 20.5677 | N8: =H8*M8 -> 125977.16 | O8: =I8*M8 -> 0 | P8: =J8*M8 -> 125977.16 | Q8: =M8*K8 -> 0 | R8: =L8*M8 -> 125977.16 | U8: 6125 | AB8: =U8*M8 -> 125977.16 | AC8: =+V8*M8 -> 0 | AD8: =+M8*W8 -> 0 | AE8: =+X8*M8 -> 0 | AF8: =+Y8*M8 -> 0 | AG8: =+Z8*M8 -> 0
B9: 1-002381 | C9: CGL24122397 | D9: 45687 | E9: C0067 | F9: ND AUTOMOTIVE SYSTEMS MEXICO | G9: 0 | H9: 375 | I9: =+H9*0.16 -> 60 | J9: =SUM(G9:I9) -> 435 | K9: 0 | L9: =J9-K9 -> 435 | M9: 20.5677 | N9: =H9*M9 -> 7712.8875 | O9: =I9*M9 -> 1234.062 | P9: =J9*M9 -> 8946.9495 | Q9: =M9*K9 -> 0 | R9: =L9*M9 -> 8946.9495 | Y9: 375 | AB9: =U9*M9 -> 0 | AC9: =+V9*M9 -> 0 | AD9: =+M9*W9 -> 0 | AE9: =+X9*M9 -> 0 | AF9: =+Y9*M9 -> 7712.8875 | AG9: =+Z9*M9 -> 0
B10: 1-002382 | C10: CGL24071864 | D10: 45687 | E10: C0067 | F10: ND AUTOMOTIVE SYSTEMS MEXICO | G10: =36232.6+539.4 -> 36772 | H10: =75+175 -> 250 | I10: 0 | J10: =SUM(G10:I10) -> 37022 | K10: 36482.6 | L10: =J10-K10 -> 539.4 | M10: 20.5677 | N10: =H10*M10 -> 5141.925 | O10: =I10*M10 -> 0 | P10: =J10*M10 -> 761457.39 | Q10: =M10*K10 -> 750363.17 | R10: =L10*M10 -> 11094.217 | W10: 175 | Z10: 75 | AB10: =U10*M10 -> 0 | AC10: =+V10*M10 -> 0 | AD10: =+M10*W10 -> 3599.3475 | AE10: =+X10*M10 -> 0 | AF10: =+Y10*M10 -> 0 | AG10: =+Z10*M10 -> 1542.5775
B11: 1-002387 | C11: CGL25012469 | D11: 45688 | E11: C0090 | F11: INVICONT OÜ | G11: 0 | H11: 60190 | I11: 0 | J11: =SUM(G11:I11) -> 60190 | K11: 60190 | L11: =J11-K11 -> 0 | M11: 20.4497 | N11: =H11*M11 -> 1230867.4 | O11: =I11*M11 -> 0 | P11: =J11*M11 -> 1230867.4 | Q11: =M11*K11 -> 1230867.4 | R11: =L11*M11 -> 0 | V11: 34980 | W11: 350 | X11: 24860 | AB11: =U11*M11 -> 0 | AC11: =+V11*M11 -> 715330.51 | AD11: =+M11*W11 -> 7157.395 | AE11: =+X11*M11 -> 508379.54 | AF11: =+Y11*M11 -> 0 | AG11: =+Z11*M11 -> 0
J12: =SUM(G12:I12) -> 0 | L12: =J12-K12 -> 0 | N12: =H12*M12 -> 0 | O12: =I12*M12 -> 0 | P12: =J12*M12 -> 0 | Q12: =M12*K12 -> 0 | R12: =L12*M12 -> 0 | AB12: =U12*M12 -> 0 | AC12: =+V12*M12 -> 0 | AD12: =+M12*W12 -> 0 | AE12: =+X12*M12 -> 0 | AF12: =+Y12*M12 -> 0 | AG12: =+Z12*M12 -> 0
J13: =SUM(G13:I13) -> 0 | L13: =J13-K13 -> 0 | N13: =H13*M13 -> 0 | O13: =I13*M13 -> 0 | P13: =J13*M13 -> 0 | Q13: =M13*K13 -> 0 | R13: =L13*M13 -> 0 | AB13: =U13*M13 -> 0 | AC13: =+V13*M13 -> 0 | AD13: =+M13*W13 -> 0 | AE13: =+X13*M13 -> 0 | AF13: =+Y13*M13 -> 0 | AG13: =+Z13*M13 -> 0
J14: =SUM(G14:I14) -> 0 | L14: =J14-K14 -> 0 | N14: =H14*M14 -> 0 | O14: =I14*M14 -> 0 | P14: =J14*M14 -> 0 | Q14: =M14*K14 -> 0 | R14: =L14*M14 -> 0 | AB14: =U14*M14 -> 0 | AC14: =+V14*M14 -> 0 | AD14: =+M14*W14 -> 0 | AE14: =+X14*M14 -> 0 | AF14: =+Y14*M14 -> 0 | AG14: =+Z14*M14 -> 0
J15: =SUM(G15:I15) -> 0 | L15: =J15-K15 -> 0 | N15: =H15*M15 -> 0 | O15: =I15*M15 -> 0 | P15: =J15*M15 -> 0 | Q15: =M15*K15 -> 0 | R15: =L15*M15 -> 0 | AB15: =U15*M15 -> 0 | AC15: =+V15*M15 -> 0 | AD15: =+M15*W15 -> 0 | AE15: =+X15*M15 -> 0 | AF15: =+Y15*M15 -> 0 | AG15: =+Z15*M15 -> 0
J16: =SUM(G16:I16) -> 0 | L16: =J16-K16 -> 0 | N16: =H16*M16 -> 0 | O16: =I16*M16 -> 0 | P16: =J16*M16 -> 0 | Q16: =M16*K16 -> 0 | R16: =L16*M16 -> 0 | AB16: =U16*M16 -> 0 | AC16: =+V16*M16 -> 0 | AD16: =+M16*W16 -> 0 | AE16: =+X16*M16 -> 0 | AF16: =+Y16*M16 -> 0 | AG16: =+Z16*M16 -> 0
J17: =SUM(G17:I17) -> 0 | L17: =J17-K17 -> 0 | N17: =H17*M17 -> 0 | O17: =I17*M17 -> 0 | P17: =J17*M17 -> 0 | Q17: =M17*K17 -> 0 | R17: =L17*M17 -> 0 | AB17: =U17*M17 -> 0 | AC17: =+V17*M17 -> 0 | AD17: =+M17*W17 -> 0 | AE17: =+X17*M17 -> 0 | AF17: =+Y17*M17 -> 0 | AG17: =+Z17*M17 -> 0
J18: =SUM(G18:I18) -> 0 | L18: =J18-K18 -> 0 | N18: =H18*M18 -> 0 | O18: =I18*M18 -> 0 | P18: =J18*M18 -> 0 | Q18: =M18*K18 -> 0 | R18: =L18*M18 -> 0 | AB18: =U18*M18 -> 0 | AC18: =+V18*M18 -> 0 | AD18: =+M18*W18 -> 0 | AE18: =+X18*M18 -> 0 | AF18: =+Y18*M18 -> 0 | AG18: =+Z18*M18 -> 0
G19: =+SUM(G3:G18) -> 36772 | H19: =+SUM(H3:H18) -> 85894.49 | I19: =+SUM(I3:I18) -> 60 | J19: =+SUM(J3:J18) -> 122726.49 | K19: =+SUM(K3:K18) -> 100782.6 | L19: =+SUM(L3:L18) -> 21943.89 | N19: =+SUM(N3:N18) -> 1757606.5 | O19: =+SUM(O3:O18) -> 1234.062 | P19: =+SUM(P3:P18) -> 2515156 | Q19: =+SUM(Q3:Q18) -> 2065051.2 | R19: =+SUM(R3:R18) -> 450104.83 | U19: =+SUM(U3:U18) -> 22694 | V19: =+SUM(V3:V18) -> 34980 | W19: =+SUM(W3:W18) -> 525 | X19: =+SUM(X3:X18) -> 24860 | Y19: =+SUM(Y3:Y18) -> 2760.49 | Z19: =+SUM(Z3:Z18) -> 75 | AB19: =+SUM(AB3:AB18) -> 465070.83 | AC19: =+SUM(AC3:AC18) -> 715330.51 | AD19: =+SUM(AD3:AD18) -> 10756.743 | AE19: =+SUM(AE3:AE18) -> 508379.54 | AF19: =+SUM(AF3:AF18) -> 56526.293 | AG19: =+SUM(AG3:AG18) -> 1542.5775
Z20: =+SUM(T19:Z19) -> 85894.49 | AG20: =+SUM(AB19:AG19) -> 1757606.5
Z21: =+Z20-H19 -> 0 | AG21: =+AG20-N19 -> 0

Sheet FEB MXN
A1: SERIE | B1: FACTURA | C1: TRAFICO | D1: FECHA | E1: CLIENTE | F1: CLIENTE NOMBRE | G1: COMPROBADOS | H1: COMPLEMENTARIOS | I1: IVA | J1: SUBTOTAL | K1: ANTICIPO | L1: TOTAL | M1: MONEDA | P1: DOCUMENTACION, ALMACENAJES Y MANIOBRAS ( TER) | Q1: IMPUESTOS ADUANALES (TER) | S1: HONORARIOS | T1: REVALIDACION GUIA / BOL | U1: MANIOBRAS | V1: ALMACENAJES | W1: SERVICIOS LOGISTICOS | X1: CONSOLIDACION DE ENTRADAS | Y1: SERVICIO EXTRAORDINARIO | Z1: ACONDICIONAMIENTO DE EMBALAJE | AA1: LIBERACION DE DOCUMENTOS | AE1: MXN | AF1: USD | AG1: TOTAL | AH1: PORCENTAJE
B2: 1-002395 | C2: CGL24122432 | D2: 45694 | E2: C0001 | F2: ARMOR MEXICO IMAGING SUPPLIES | G2: 0 | H2: 107360.24 | I2: 17177.64 | J2: =SUM(G2:I2) -> 124537.88 | K2: 0 | L2: =+J2-K2 -> 124537.88 | M2: MXN | P2: 0 | Q2: 0 | S2: 6162.9 | T2: 0 | U2: 29072.04 | V2: 2790.3 | W2: 69335 | X2: 0 | Y2: 0 | Z2: 0 | AA2: 0 | AB2: =+SUM(S2:AA2)-H2 -> 0 | AD2: HONORARIOS | AE2: =+S77 -> 421824.29 | AG2: =SUM(AE2:AF2) -> 421824.29 | AH2: =+AG2/AG24 -> 0.1948623
B3: 1-002396 | C3: CGL25012475 | D3: 45694 | E3: C0001 | F3: ARMOR MEXICO IMAGING SUPPLIES | G3: 0 | H3: 73868.29 | I3: 11818.93 | J3: =SUM(G3:I3) -> 85687.22 | K3: 0 | L3: =+J3-K3 -> 85687.22 | M3: MXN | P3: 0 | Q3: 0 | S3: 6118.29 | T3: 0 | U3: 25750 | V3: 0 | W3: 42000 | X3: 0 | Y3: 0 | Z3: 0 | AA3: 0 | AB3: =+SUM(S3:AA3)-H3 -> 0 | AD3: REVALIDACION GUIA / BOL | AE3: =+T77 -> 13310.6 | AF3: =+'FEB USD '!AC19 -> 10188.894 | AG3: =SUM(AE3:AF3) -> 23499.494 | AH3: =+AG3/AG24 -> 0.010855623
B4: 1-002397 | C4: CGL25012515 | D4: 45694 | E4: C0069 | F4: JOINT PRODUCTION HONOR | G4: 781 | H4: 13293.3 | I4: 2126.93 | J4: =SUM(G4:I4) -> 16201.23 | K4: 25378.07 | L4: =+J4-K4 -> -9176.84 | M4: MXN | P4: 0 | Q4: 781 | S4: 7404.37 | T4: 0 | U4: 5888.93 | V4: 0 | X4: 0 | Y4: 0 | Z4: 0 | AA4: 0 | AB4: =+SUM(S4:AA4)-H4 -> 0 | AD4: MANIOBRAS | AE4: =+U77 -> 420886.31 | AG4: =SUM(AE4:AF4) -> 420886.31 | AH4: =+AG4/AG24 -> 0.19442899
B5: 1-002399 | C5: CGL25012513 | D5: 45694 | E5: C0004 | F5: NAPS-GUANAJUATO AMERICAN BOA | G5: =781+295 -> 1076 | H5: 143742.45 | I5: 22998.79 | J5: =SUM(G5:I5) -> 167817.24 | K5: 167817.25 | L5: =+J5-K5 -> -0.01 | M5: MXN | P5: 295 | Q5: 781 | S5: 30125.61 | T5: 0 | U5: 65911.84 | V5: 0 | W5: 47705 | X5: 0 | Y5: 0 | Z5: 0 | AA5: 0 | AB5: =+SUM(S5:AA5)-H5 -> 0 | AD5: ALMACENAJES | AE5: =+V77 -> 3967.78 | AG5: =SUM(AE5:AF5) -> 3967.78 | AH5: =+AG5/AG24 -> 0.0018329213
B6: 2-002401 | C6: CGL25012522 | D6: 45695 | E6: C0001 | F6: ARMOR MEXICO IMAGING SUPPLIES | G6: 0 | H6: 26000.04 | I6: 4160.01 | J6: =SUM(G6:I6) -> 30160.05 | K6: 0 | L6: =+J6-K6 -> 30160.05 | M6: MXN | P6: 0 | Q6: 0 | S6: 4140.04 | T6: 0 | U6: 0 | V6: 0 | W6: 21860 | X6: 0 | Y6: 0 | Z6: 0 | AA6: 0 | AB6: =+SUM(S6:AA6)-H6 -> 0 | AD6: SERVICIOS LOGISTICOS | AE6: =+W77 -> 999662.55 | AF6: =+'FEB USD '!AB19 -> 160463.12 | AG6: =SUM(AE6:AF6) -> 1160125.7 | AH6: =+AG6/AG24 -> 0.53592161
B7: 2-002402 | C7: CGL25012464 | D7: 45695 | E7: C0069 | F7: JOINT PRODUCTION HONOR | G7: =336+336 -> 672 | H7: 15295.72 | I7: 2447.32 | J7: =SUM(G7:I7) -> 18415.04 | K7: 18415.04 | L7: =+J7-K7 -> 0 | M7: MXN | P7: 0 | Q7: =336+336 -> 672 | S7: =7647.86+7647.86 -> 15295.72 | T7: 0 | U7: 0 | V7: 0 | W7: 0 | X7: 0 | Y7: 0 | Z7: 0 | AA7: 0 | AB7: =+SUM(S7:AA7)-H7 -> 0 | AD7: CONSOLIDACION DE ENTRADAS | AE7: =+X77 -> 38326.46 | AG7: =SUM(AE7:AF7) -> 38326.46 | AH7: =+AG7/AG24 -> 0.01770496
B8: 1-002403 | C8: CGL25012501 | D8: 45699 | E8: C0084 | F8: JOINT PRODUCTION TECTRAN | G8: 0 | H8: 21320.23 | I8: 3411.24 | J8: =SUM(G8:I8) -> 24731.47 | K8: 24731.47 | L8: =+J8-K8 -> 0 | M8: MXN | P8: 0 | Q8: 0 | S8: 0 | T8: 0 | U8: 0 | V8: 0 | W8: 21320.23 | X8: 0 | Y8: 0 | Z8: 0 | AA8: 0 | AB8: =+SUM(S8:AA8)-H8 -> 0 | AD8: SERVICIO EXTRAORDINARIO | AE8: =+Y77 -> 71000 | AG8: =SUM(AE8:AF8) -> 71000 | AH8: =+AG8/AG24 -> 0.032798545
B9: 2-002404 | C9: CGL25022547 | D9: 45699 | E9: C0081 | F9: JOINT PRODUCTION BLACK SMITH | G9: 0 | H9: 66000 | I9: 10560 | J9: =SUM(G9:I9) -> 76560 | K9: 76560 | L9: =+J9-K9 -> 0 | M9: MXN | P9: 0 | Q9: 0 | S9: 0 | T9: 0 | U9: 0 | V9: 0 | W9: 66000 | X9: 0 | Y9: 0 | Z9: 0 | AA9: 0 | AB9: =+SUM(S9:AA9)-H9 -> 0 | AD9: ACONDICIONAMIENTO DE EMBALAJE | AE9: =+Z77 -> 2550 | AG9: =SUM(AE9:AF9) -> 2550 | AH9: =+AG9/AG24 -> 0.0011779759
B10: 2-002405 | C10: CGL25012488 | D10: 45699 | E10: C0002 | F10: NAPS-GUANAJUATO CAM | G10: 1695 | H10: 8039.94 | I10: 1286.39 | J10: =SUM(G10:I10) -> 11021.33 | K10: 11021.33 | L10: =+J10-K10 -> 0 | M10: MXN | P10: 0 | Q10: 1695 | S10: 4089.94 | T10: 0 | U10: 0 | V10: 0 | W10: 3950 | X10: 0 | Y10: 0 | Z10: 0 | AA10: 0 | AB10: =+SUM(S10:AA10)-H10 -> 0 | AD10: LIBERACION DE DOCUMENTOS | AE10: =+AA77 -> 1597.5 | AF10: =+'FEB USD '!AD19 -> 4815.5495 | AG10: =SUM(AE10:AF10) -> 6413.0495 | AH10: =+AG10/AG24 -> 0.0029625168
B11: 2-002406 | C11: CGL25012528 | D11: 45699 | E11: C0002 | F11: NAPS-GUANAJUATO CAM | G11: 336 | H11: 4121.36 | I11: 659.42 | J11: =SUM(G11:I11) -> 5116.78 | K11: 5116.78 | L11: =+J11-K11 -> 0 | M11: MXN | P11: 0 | Q11: 336 | S11: 4121.36 | T11: 0 | U11: 0 | V11: 0 | W11: 0 | X11: 0 | Y11: 0 | Z11: 0 | AA11: 0 | AB11: =+SUM(S11:AA11)-H11 -> 0 | AD11: GASTOS EN DESTINO | AF11: =+'FEB USD '!AF19 -> 14600.236 | AG11: =SUM(AE11:AF11) -> 14600.236 | AH11: =+AG11/AG24 -> 0.0067445984
B12: 2-002407 | C12: CGL24122416 | D12: 45699 | E12: C0002 | F12: NAPS-GUANAJUATO CAM | G12: 19120 | H12: 8071.36 | I12: 1291.42 | J12: =SUM(G12:I12) -> 28482.78 | K12: 28482.78 | L12: =+J12-K12 -> 0 | M12: MXN | P12: 0 | Q12: 19120 | S12: 4121.36 | T12: 0 | U12: 0 | V12: 0 | W12: 3950 | X12: 0 | Y12: 0 | Z12: 0 | AA12: 0 | AB12: =+SUM(S12:AA12)-H12 -> 0 | AD12: CUOTA | AF12: =+'FEB USD '!AG19 -> 1536.8775 | AG12: =SUM(AE12:AF12) -> 1536.8775 | AH12: =+AG12/AG24 -> 0.00070996262
B13: 2-002408 | C13: CGL25022551 | D13: 45699 | E13: C0002 | F13: NAPS-GUANAJUATO CAM | G13: 781 | H13: 8035.36 | I13: 1285.66 | J13: =SUM(G13:I13) -> 10102.02 | K13: 10102.02 | L13: =+J13-K13 -> 0 | M13: MXN | P13: 0 | Q13: 781 | S13: 4085.36 | T13: 0 | U13: 0 | V13: 0 | W13: 3950 | X13: 0 | Y13: 0 | Z13: 0 | AA13: 0 | AB13: =+SUM(S13:AA13)-H13 -> 0 | AG13: =SUM(AE13:AF13) -> 0 | AH13: =+AG13/AG24 -> 0
B14: 2-002409 | C14: CGL25012511 | D14: 45699 | E14: C0002 | F14: NAPS-GUANAJUATO CAM | G14: 781 | H14: 8035.36 | I14: 1285.66 | J14: =SUM(G14:I14) -> 10102.02 | K14: 10102.02 | L14: =+J14-K14 -> 0 | M14: MXN | P14: 0 | Q14: 781 | S14: 4085.36 | T14: 0 | U14: 0 | V14: 0 | W14: 3950 | X14: 0 | Y14: 0 | Z14: 0 | AA14: 0 | AB14: =+SUM(S14:AA14)-H14 -> 0 | AG14: =SUM(AE14:AF14) -> 0 | AH14: =+AG14/AG24 -> 0
B15: 2-002410 | C15: CGL25012507 | D15: 45699 | E15: C0002 | F15: NAPS-GUANAJUATO CAM | G15: 1782 | H15: 8022.43 | I15: 1283.59 | J15: =SUM(G15:I15) -> 11088.02 | K15: 11088.02 | L15: =+J15-K15 -> 0 | M15: MXN | P15: 0 | Q15: 1782 | S15: 4072.43 | T15: 0 | U15: 0 | V15: 0 | W15: 3950 | X15: 0 | Y15: 0 | Z15: 0 | AA15: 0 | AB15: =+SUM(S15:AA15)-H15 -> 0 | AG15: =SUM(AE15:AF15) -> 0 | AH15: =+AG15/AG24 -> 0
B16: 2-002411 | C16: CGL25012456 | D16: 45699 | E16: C0002 | F16: NAPS-GUANAJUATO CAM | G16: 1515 | H16: 8025.02 | I16: 1284 | J16: =SUM(G16:I16) -> 10824.02 | K16: 10824.02 | L16: =+J16-K16 -> 0 | M16: MXN | P16: 0 | Q16: 1515 | S16: 4075.02 | T16: 0 | U16: 0 | V16: 0 | W16: 3950 | X16: 0 | Y16: 0 | Z16: 0 | AA16: 0 | AB16: =+SUM(S16:AA16)-H16 -> 0 | AG16: =SUM(AE16:AF16) -> 0 | AH16: =+AG16/AG24 -> 0
B17: 2-002412 | C17: CGL25012539 | D17: 45699 | E17: C0001 | F17: ARMOR MEXICO IMAGING SUPPLIES | G17: 0 | H17: 9013.77 | I17: 1442.2 | J17: =SUM(G17:I17) -> 10455.97 | K17: 0 | L17: =+J17-K17 -> 10455.97 | M17: MXN | P17: 0 | Q17: 0 | S17: 4085.2 | T17: 0 | U17: 0 | V17: 0 | W17: 4928.57 | X17: 0 | Y17: 0 | Z17: 0 | AA17: 0 | AB17: =+SUM(S17:AA17)-H17 -> 0 | AG17: =SUM(AE17:AF17) -> 0 | AH17: =+AG17/AG24 -> 0
B18: 2-002413 | C18: CGL25012479 | D18: 45700 | E18: C0002 | F18: NAPS-GUANAJUATO CAM | G18: 2305 | H18: 9677.26 | I18: 1548.36 | J18: =SUM(G18:I18) -> 13530.62 | K18: 11674.62 | L18: =+J18-K18 -> 1856 | M18: MXN | P18: 0 | Q18: 2305 | S18: 4127.26 | T18: 0 | U18: 0 | V18: 0 | W18: 3950 | X18: 0 | Y18: 1600 | Z18: 0 | AA18: 0 | AB18: =+SUM(S18:AA18)-H18 -> 0 | AG18: =SUM(AE18:AF18) -> 0 | AH18: =+AG18/AG24 -> 0
B19: 2-002414 | C19: CGL25012512 | D19: 45700 | E19: C0002 | F19: NAPS-GUANAJUATO CAM | G19: 38418 | H19: 20291.44 | I19: 3246.63 | J19: =SUM(G19:I19) -> 61956.07 | K19: 61956.07 | L19: =+J19-K19 -> 0 | M19: MXN | P19: 0 | Q19: 38418 | S19: 4085.36 | T19: 0 | U19: 0 | V19: 0 | W19: 3950 | X19: 12256.08 | Y19: 0 | Z19: 0 | AA19: 0 | AB19: =+SUM(S19:AA19)-H19 -> 0
B20: 1-002415 | C20: CGL25022546 | D20: 45700 | E20: C0001 | F20: ARMOR MEXICO IMAGING SUPPLIES | G20: 0 | H20: 38816.61 | I20: 6210.66 | J20: =SUM(G20:I20) -> 45027.27 | K20: 0 | L20: =+J20-K20 -> 45027.27 | M20: MXN | P20: 0 | Q20: 0 | S20: 4102.5 | T20: 3737.5 | U20: 19501.61 | V20: 0 | W20: 11475 | X20: 0 | Y20: 0 | Z20: 0 | AA20: 0 | AB20: =+SUM(S20:AA20)-H20 -> 0
B21: 2-002417 | C21: CGL25022550 | D21: 45701 | E21: C0081 | F21: JOINT PRODUCTION BLACK SMITH | G21: 0 | H21: 22000 | I21: 3520 | J21: =SUM(G21:I21) -> 25520 | K21: 25520 | L21: =+J21-K21 -> 0 | M21: MXN | P21: 0 | Q21: 0 | S21: 0 | T21: 0 | U21: 0 | V21: 0 | W21: 22000 | X21: 0 | Y21: 0 | Z21: 0 | AA21: 0 | AB21: =+SUM(S21:AA21)-H21 -> 0
B22: 1-002418 | C22: CGL25012491 | D22: 45701 | E22: C0012 | F22: MEGALUMINIO SERVICIOS | G22: 5295 | H22: 21926.3 | I22: 3508.21 | J22: =SUM(G22:I22) -> 30729.51 | K22: 31002.76 | L22: =+J22-K22 -> -273.25 | M22: MXN | P22: 0 | Q22: 5295 | S22: 6500 | T22: 0 | U22: 10348.6 | V22: 0 | W22: 5077.7 | X22: 0 | Y22: 0 | Z22: 0 | AA22: 0 | AB22: =+SUM(S22:AA22)-H22 -> 0
B23: 1-002419 | C23: CGL25012492 | D23: 45701 | E23: C0012 | F23: MEGALUMINIO SERVICIOS | G23: 30380 | H23: 22092.27 | I23: 3534.77 | J23: =SUM(G23:I23) -> 56007.04 | K23: 56009.76 | L23: =+J23-K23 -> -2.72 | M23: MXN | P23: 0 | Q23: 30380 | S23: 6500 | T23: 652.6 | U23: =9760+4079.67 -> 13839.67 | V23: 0 | W23: 1100 | X23: 0 | Y23: 0 | Z23: 0 | AA23: 0 | AB23: =+SUM(S23:AA23)-H23 -> 0 | AE23: 0 | AG23: =SUM(AE23:AF23) -> 0 | AH23: =+AG23/AG24 -> 0
B24: 1-002420 | C24: CGL25012510 | D24: 45701 | E24: C0069 | F24: JOINT PRODUCTION HONOR | G24: 781 | H24: 61555.79 | I24: 9848.93 | J24: =SUM(G24:I24) -> 72185.72 | K24: 971053.49 | L24: =+J24-K24 -> -898867.77 | M24: MXN | P24: 0 | Q24: 781 | S24: 7341.94 | T24: 0 | U24: 54213.85 | V24: 0 | W24: 0 | X24: 0 | Y24: 0 | Z24: 0 | AA24: 0 | AB24: =+SUM(S24:AA24)-H24 -> 0 | AE24: =+SUM(AE2:AE23) -> 1973125.5 | AF24: =+SUM(AF2:AF23) -> 191604.67 | AG24: =+SUM(AG2:AG23) -> 2164730.2 | AH24: =+SUM(AH2:AH23) -> 1
B25: 1-002423 | C25: CGL25022541 | D25: 45701 | E25: C0069 | F25: JOINT PRODUCTION HONOR | G25: 781 | H25: 10776.17 | I25: 1724.18 | J25: =SUM(G25:I25) -> 13281.35 | K25: 19752.67 | L25: =+J25-K25 -> -6471.32 | M25: MXN | P25: 0 | Q25: 781 | S25: 7361.89 | T25: 0 | U25: 3414.28 | V25: 0 | W25: 0 | X25: 0 | Y25: 0 | Z25: 0 | AA25: 0 | AB25: =+SUM(S25:AA25)-H25 -> 0
B26: 1-002424 | C26: CGL25012463 | D26: 45701 | E26: C0005 | F26: HAHN AUTOMATION | G26: 12384 | H26: 9336.15 | I26: 1493.79 | J26: =SUM(G26:I26) -> 23213.94 | K26: 23213.94 | L26: =+J26-K26 -> 0 | M26: MXN | P26: 0 | Q26: 12384 | S26: 4447.41 | T26: 0 | U26: 2788.74 | V26: 0 | W26: 2100 | X26: 0 | Y26: 0 | Z26: 0 | AA26: 0 | AB26: =+SUM(S26:AA26)-H26 -> 0
B27: 2-002425 | C27: CGL25022548 | D27: 45701 | E27: C0081 | F27: JOINT PRODUCTION BLACK SMITH | G27: 0 | H27: 20000 | I27: 3200 | J27: =SUM(G27:I27) -> 23200 | K27: 23200 | L27: =+J27-K27 -> 0 | M27: MXN | P27: 0 | Q27: 0 | S27: 0 | T27: 0 | U27: 0 | V27: 0 | W27: 20000 | X27: 0 | Y27: 0 | Z27: 0 | AA27: 0 | AB27: =+SUM(S27:AA27)-H27 -> 0
B28: 2-002428 | C28: CGL25012530 | D28: 45705 | E28: C0069 | F28: JOINT PRODUCTION HONOR | G28: 336 | H28: 100458.15 | I28: 16073.3 | J28: =SUM(G28:I28) -> 116867.45 | K28: 116867.45 | L28: =+J28-K28 -> 0 | M28: MXN | P28: 0 | Q28: 336 | S28: 100458.15 | T28: 0 | U28: 0 | V28: 0 | W28: 0 | X28: 0 | Y28: 0 | Z28: 0 | AA28: 0 | AB28: =+SUM(S28:AA28)-H28 -> 0
B29: 1-002429 | C29: CGL25022559 | D29: 45705 | E29: C0001 | F29: ARMOR MEXICO IMAGING SUPPLIES | G29: 0 | H29: 11406.38 | I29: 1825.03 | J29: =SUM(G29:I29) -> 13231.41 | K29: 0 | L29: =+J29-K29 -> 13231.41 | M29: MXN | P29: 0 | Q29: 0 | S29: 4113.36 | T29: 1500 | U29: 2115.54 | V29: 1177.48 | W29: 2500 | X29: 0 | Y29: 0 | Z29: 0 | AA29: 0 | AB29: =+SUM(S29:AA29)-H29 -> 0
B30: 2-002430 | C30: CGL25022560 | D30: 45705 | E30: C0001 | F30: ARMOR MEXICO IMAGING SUPPLIES | G30: 0 | H30: 41110.24 | I30: 6577.64 | J30: =SUM(G30:I30) -> 47687.88 | K30: 0 | L30: =+J30-K30 -> 47687.88 | M30: MXN | P30: 0 | Q30: 0 | S30: 4110.24 | T30: 0 | U30: 0 | V30: 0 | W30: 37000 | X30: 0 | Y30: 0 | Z30: 0 | AA30: 0 | AB30: =+SUM(S30:AA30)-H30 -> 0
B31: 2-002431 | C31: CGL25022555 | D31: 45706 | E31: C0002 | F31: NAPS-GUANAJUATO CAM | G31: 336 | H31: 6985.2 | I31: 1117.63 | J31: =SUM(G31:I31) -> 8438.83 | K31: 8438.83 | L31: =+J31-K31 -> 0 | M31: MXN | P31: 0 | Q31: 336 | S31: 3035.2 | T31: 0 | U31: 0 | V31: 0 | W31: 3950 | X31: 0 | Y31: 0 | Z31: 0 | AA31: 0 | AB31: =+SUM(S31:AA31)-H31 -> 0
B32: 2-002432 | C32: CGL25022565 | D32: 45706 | E32: C0001 | F32: ARMOR MEXICO IMAGING SUPPLIES | G32: 0 | H32: 41113.6 | I32: 6578.18 | J32: =SUM(G32:I32) -> 47691.78 | K32: 0 | L32: =+J32-K32 -> 47691.78 | M32: MXN | P32: 0 | Q32: 0 | S32: 4113.6 | T32: 0 | U32: 0 | V32: 0 | W32: 37000 | X32: 0 | Y32: 0 | Z32: 0 | AA32: 0 | AB32: =+SUM(S32:AA32)-H32 -> 0
B33: 2-002433 | C33: CGL25012533 | D33: 45706 | E33: C0002 | F33: NAPS-GUANAJUATO CAM | G33: 336 | H33: 7045.45 | I33: 1127.27 | J33: =SUM(G33:I33) -> 8508.72 | K33: 8508.72 | L33: =+J33-K33 -> 0 | M33: MXN | P33: 0 | Q33: 336 | S33: 3095.45 | T33: 0 | U33: 0 | V33: 0 | W33: 3950 | X33: 0 | Y33: 0 | Z33: 0 | AA33: 0 | AB33: =+SUM(S33:AA33)-H33 -> 0
B34: 2-002434 | C34: CGL25012532 | D34: 45706 | E34: C0002 | F34: NAPS-GUANAJUATO CAM | G34: 336 | H34: 14090.89 | I34: 2254.54 | J34: =SUM(G34:I34) -> 16681.43 | K34: 16681.43 | L34: =+J34-K34 -> 0 | M34: MXN | P34: 0 | Q34: 336 | S34: 6190.89 | T34: 0 | U34: 0 | V34: 0 | W34: 7900 | X34: 0 | Y34: 0 | Z34: 0 | AA34: 0 | AB34: =+SUM(S34:AA34)-H34 -> 0
B35: 1-002435 | C35: CGL25012538 | D35: 45706 | E35: C0001 | F35: ARMOR MEXICO IMAGING SUPPLIES | G35: 0 | H35: 16244.3 | I35: 2599.09 | J35: =SUM(G35:I35) -> 18843.39 | K35: 0 | L35: =+J35-K35 -> 18843.39 | M35: MXN | P35: 0 | Q35: 0 | S35: 8220.48 | T35: 0 | U35: 3373.82 | V35: 0 | W35: 2100 | X35: 0 | Y35: 0 | Z35: 2550 | AA35: 0 | AB35: =+SUM(S35:AA35)-H35 -> 0
B36: 1-002438 | C36: CGL24112357 | D36: 45707 | E36: C0012 | F36: MEGALUMINIO SERVICIOS | G36: 359364 | H36: 94500 | I36: 15120 | J36: =SUM(G36:I36) -> 468984 | K36: 468984 | L36: =+J36-K36 -> 0 | M36: MXN | P36: 0 | Q36: 359364 | S36: 7500 | T36: 0 | U36: 24000 | V36: 0 | W36: 63000 | X36: 0 | Y36: 0 | Z36: 0 | AA36: 0 | AB36: =+SUM(S36:AA36)-H36 -> 0
... B43: 1-002445 | C43: CGL25012540 | D43: 45707 | E43: C0084 | F43: JOINT PRODUCTION TECTRAN | G43: 0 | H43: 25000 | I43: 4000 | J43: =SUM(G43:I43) -> 29000 | K43: 29000 | L43: =+J43-K43 -> 0 | M43: MXN | P43: 0 | Q43: 0 | S43: 0 | T43: 0 | U43: 0 | V43: 0 | W43: 25000 | X43: 0 | Y43: 0 | Z43: 0 | AA43: 0 | AB43: =+SUM(S43:AA43)-H43 -> 0
B44: 2-002446 | C44: CGL25012536 | D44: 45708 | E44: C0024 | F44: SELLOS Y RETENES DE SAN LUIS | G44: 183058 | H44: 10275.6 | I44: 1644.1 | J44: =SUM(G44:I44) -> 194977.7 | K44: 187725.4 | L44: =+J44-K44 -> 7252.3 | M44: MXN | P44: 0 | Q44: 183058 | S44: =4110.24+6165.36 -> 10275.6 | T44: 0 | U44: 0 | V44: 0 | W44: 0 | X44: 0 | Y44: 0 | Z44: 0 | AA44: 0 | AB44: =+SUM(S44:AA44)-H44 -> 0
B45: 1-002447 | C45: CGL25012485 | D45: 45708 | E45: C0004 | F45: NAPS-GUANAJUATO AMERICAN BOA | G45: 781 | H45: 87882.04 | I45: 14061.13 | J45: =SUM(G45:I45) -> 102724.17 | K45: 102759.32 | L45: =+J45-K45 -> -35.15 | M45: MXN | P45: 0 | Q45: 781 | S45: 6182.04 | T45: 0 | U45: 25000 | V45: 0 | W45: 56700 | X45: 0 | Y45: 0 | Z45: 0 | AA45: 0 | AB45: =+SUM(S45:AA45)-H45 -> 0
B46: 2-002448 | C46: CGL24122389 | D46: 45708 | E46: C0002 | F46: NAPS-GUANAJUATO CAM | G46: 29189 | H46: 4713.54 | I46: 754.17 | J46: =SUM(G46:I46) -> 34656.71 | K46: 34656.71 | L46: =+J46-K46 -> 0 | M46: MXN | P46: 0 | Q46: 29189 | S46: 4113.54 | T46: 0 | U46: 0 | V46: 0 | W46: 0 | X46: 0 | Y46: 600 | Z46: 0 | AA46: 0 | AB46: =+SUM(S46:AA46)-H46 -> 0
B47: 2-002449 | C47: CGL25022563 | D47: 45708 | E47: C0002 | F47: NAPS-GUANAJUATO CAM | G47: 5115 | H47: 8047.47 | I47: 1287.6 | J47: =SUM(G47:I47) -> 14450.07 | K47: 14450.07 | L47: =+J47-K47 -> 0 | M47: MXN | P47: 0 | Q47: 5115 | S47: 4097.47 | T47: 0 | U47: 0 | V47: 0 | W47: 3950 | X47: 0 | Y47: 0 | Z47: 0 | AA47: 0 | AB47: =+SUM(S47:AA47)-H47 -> 0
B48: 1-002450 | C48: CGL24122430 | D48: 45709 | E48: C0089 | F48: CHEMICAL COLOR DE MEXICO | G48: 102252 | H48: 95976 | I48: 15356.16 | J48: =SUM(G48:I48) -> 213584.16 | K48: 213584.16 | L48: =+J48-K48 -> 0 | M48: MXN | P48: 0 | Q48: 102252 | S48: 8170 | T48: 0 | U48: 19350 | V48: 0 | W48: 68456 | X48: 0 | Y48: 0 | Z48: 0 | AA48: 0 | AB48: =+SUM(S48:AA48)-H48 -> 0
B49: 1-002451 | C49: CGL24122430 | D49: 45709 | E49: C0089 | F49: CHEMICAL COLOR DE MEXICO | G49: 0 | H49: 1333 | I49: 0 | J49: =SUM(G49:I49) -> 1333 | K49: 1333 | L49: =+J49-K49 -> 0 | M49: MXN | P49: 0 | Q49: 0 | S49: 0 | T49: 1333 | U49: 0 | V49: 0 | W49: 0 | X49: 0 | Y49: 0 | Z49: 0 | AA49: 0 | AB49: =+SUM(S49:AA49)-H49 -> 0
B50: 2-002452 | C50: CGL25022554 | D50: 45709 | E50: C0002 | F50: NAPS-GUANAJUATO CAM | G50: 781 | H50: 4133.86 | I50: 661.42 | J50: =SUM(G50:I50) -> 5576.28 | K50: 5576.28 | L50: =+J50-K50 -> 0 | M50: MXN | P50: 0 | Q50: 781 | S50: 4133.86 | T50: 0 | U50: 0 | V50: 0 | W50: 0 | X50: 0 | Y50: 0 | Z50: 0 | AA50: 0 | AB50: =+SUM(S50:AA50)-H50 -> 0
B51: 2-002453 | C51: CGL25012447 | D51: 45709 | E51: C0002 | F51: NAPS-GUANAJUATO CAM | G51: 32709 | H51: 20348.24 | I51: 3255.72 | J51: =SUM(G51:I51) -> 56312.96 | K51: 56312.96 | L51: =+J51-K51 -> 0 | M51: MXN | P51: 0 | Q51: 32709 | S51: 4099.56 | T51: 0 | U51: 0 | V51: 0 | W51: 3950 | X51: 12298.68 | Y51: 0 | Z51: 0 | AA51: 0 | AB51: =+SUM(S51:AA51)-H51 -> 0
B52: 2-002455 | C52: CGL25022581 | D52: 45712 | E52: C0001 | F52: ARMOR MEXICO IMAGING SUPPLIES | G52: 0 | H52: 41061.64 | I52: 6569.86 | J52: =SUM(G52:I52) -> 47631.5 | K52: 0 | L52: =+J52-K52 -> 47631.5 | M52: MXN | P52: 0 | Q52: 0 | S52: 4061.64 | T52: 0 | U52: 0 | V52: 0 | W52: 37000 | X52: 0 | Y52: 0 | Z52: 0 | AA52: 0 | AB52: =+SUM(S52:AA52)-H52 -> 0
B53: 1-002456 | C53: CGL25022586 | D53: 45713 | E53: C0001 | F53: ARMOR MEXICO IMAGING SUPPLIES | G53: 0 | H53: 31019.93 | I53: 4963.19 | J53: =SUM(G53:I53) -> 35983.12 | K53: 0 | L53: =+J53-K53 -> 35983.12 | M53: MXN | P53: 0 | Q53: 0 | S53: 4084.16 | T53: 3737.5 | U53: 11723.27 | V53: 0 | W53: 11475 | X53: 0 | Y53: 0 | Z53: 0 | AA53: 0 | AB53: =+SUM(S53:AA53)-H53 -> 0
B54: 2-002457 | C54: CGL25022572 | D54: 45713 | E54: C0001 | F54: ARMOR MEXICO IMAGING SUPPLIES | G54: 0 | H54: 2982.36 | I54: 477.18 | J54: =SUM(G54:I54) -> 3459.54 | K54: 0 | L54: =+J54-K54 -> 3459.54 | M54: MXN | P54: 0 | Q54: 0 | S54: 2982.36 | T54: 0 | U54: 0 | V54: 0 | W54: 0 | X54: 0 | Y54: 0 | Z54: 0 | AA54: 0 | AB54: =+SUM(S54:AA54)-H54 -> 0
B55: 1-002458 | C55: CGL25022569 | D55: 45713 | E55: C0004 | F55: NAPS-GUANAJUATO AMERICAN BOA | G55: 781 | H55: 42337.5 | I55: 6774 | J55: =SUM(G55:I55) -> 49892.5 | K55: 69612.5 | L55: =+J55-K55 -> -19720 | M55: MXN | P55: 0 | Q55: 781 | S55: 6390 | T55: 2350 | U55: 18000 | V55: 0 | W55: 14000 | X55: 0 | Y55: 0 | Z55: 0 | AA55: 1597.5 | AB55: =+SUM(S55:AA55)-H55 -> 0
B56: 2-002459 | C56: CGL25022552 | D56: 45713 | E56: C0081 | F56: JOINT PRODUCTION BLACK SMITH | G56: 0 | H56: 22000 | I56: 3520 | J56: =SUM(G56:I56) -> 25520 | K56: 25520 | L56: =+J56-K56 -> 0 | M56: MXN | P56: 0 | Q56: 0 | S56: 0 | T56: 0 | U56: 0 | V56: 0 | W56: 22000 | X56: 0 | Y56: 0 | Z56: 0 | AA56: 0 | AB56: =+SUM(S56:AA56)-H56 -> 0
... B73: 2-002479 | C73: CGL25022605 | D73: 45716 | E73: C0081 | F73: JOINT PRODUCTION BLACK SMITH | G73: 0 | H73: 22000 | I73: 3520 | J73: =SUM(G73:I73) -> 25520 | K73: 25520 | L73: =+J73-K73 -> 0 | M73: MXN | P73: 0 | Q73: 0 | S73: 0 | T73: 0 | U73: 0 | V73: 0 | W73: 22000 | X73: 0 | Y73: 0 | Z73: 0 | AA73: 0 | AB73: =+SUM(S73:AA73)-H73 -> 0
J74: =SUM(G74:I74) -> 0 | L74: =+J74-K74 -> 0 | AB74: =+SUM(S74:AA74)-H74 -> 0
J75: =SUM(G75:I75) -> 0 | L75: =+J75-K75 -> 0 | AB75: =+SUM(S75:AA75)-H75 -> 0
M76: MXN | AB76: =+SUM(S76:AA76)-H76 -> 0
G77: =+SUM(G2:G76) -> 1381970 | H77: =+SUM(H2:H76) -> 1973125.5 | I77: =+SUM(I2:I76) -> 315486.86 | J77: =+SUM(J2:J76) -> 3670582.4 | K77: =+SUM(K2:K76) -> 3930425.2 | L77: =+SUM(L2:L76) -> -259842.89 | P77: =+SUM(P2:P76) -> 295 | Q77: =+SUM(Q2:Q76) -> 1381675 | S77: =+SUM(S2:S76) -> 421824.29 | T77: =+SUM(T2:T76) -> 13310.6 | U77: =+SUM(U2:U76) -> 420886.31 | V77: =+SUM(V2:V76) -> 3967.78 | W77: =+SUM(W2:W76) -> 999662.55 | X77: =+SUM(X2:X76) -> 38326.46 | Y77: =+SUM(Y2:Y76) -> 71000 | Z77: =+SUM(Z2:Z76) -> 2550 | ... AB77: =+SUM(AB2:AB76) -> 0
H81: BASE 16% | I81: BASE 0% | J81: IVA 16% | K81: T O T A L
B82: TOTAL FACTURACION | D82: =+H84+I84 -> 2164730.2 | G82: TOTAL MXN | H82: =+H77-I82 -> 1971792.5 | I82: =+H49 -> 1333 | J82: =+H82*0.16 -> 315486.8 | K82: =+SUM(H82:J82) -> 2288612.3
A83: ( vs ) | B83: TOTAL SAT | D83: =1973125.49+'FEB USD '!N19 -> 2164730.2 | G83: TOTAL USD | H83: =+'FEB USD '!N22 -> 17126.046 | I83: =+'FEB USD '!N23 -> 174478.63 | J83: =+H83*0.16 -> 2740.1674 | K83: =+SUM(H83:J83) -> 194344.84
A84: ( = ) | B84: DIFERENCIA | D84: =+D82-D83 -> 0 | H84: =+SUM(H82:H83) -> 1988918.5 | I84: =+SUM(I82:I83) -> 175811.63 | J84: =+SUM(J82:J83) -> 318226.97 | K84: =+SUM(K82:K83) -> 2482957.1
G86: TOTAL FACTURADOS | H86: =+H84+I84 -> 2164730.2

Sheet FEB USD 
G1: INFORMACION EN USD | N1: INFORMACION EN MXN
A2: SERIE | B2: FACTURA | C2: TRAFICO | D2: FECHA | E2: CLIENTE | F2: CLIENTENOMBRE | G2: COMPROBADOS | H2: COMPLEMENTARIOS | I2: IVA | J2: SUBTOTAL | K2: ANTICIPO | L2: TOTAL | M2: TIPOCAMBIO | N2: COMPLEMENTARIOS | O2: IVA | P2: SUBTOTAL | Q2: ANTICIPO | R2: TOTAL | U2: SERVICIO LOGISTICO | V2: REVALIDACION GUIA | W2: LIBERACION DE DOCUMENTOS | X2: HONORARIOS | Y2: GASTOS EN DESTINO | Z2: CUOTA | AB2: SERVICIO LOGISTICO | AC2: REVALIDACION GUIA | AD2: LIBERACION DE DOCUMENTOS | AE2: HONORARIOS | AF2: GASTOS EN DESTINO | AG2: CUOTA
B3: 1-002398 | C3: CGL25012513 | D3: 45694 | E3: C0004 | F3: NAPS-GUANAJUATO AMERICAN BOA | G3: 0 | H3: 295 | I3: 47.2 | J3: =SUM(G3:I3) -> 342.2 | K3: 342.2 | L3: =J3-K3 -> 0 | M3: 20.6363 | N3: =H3*M3 -> 6087.7085 | O3: =I3*M3 -> 974.03336 | P3: =J3*M3 -> 7061.7419 | Q3: =M3*K3 -> 7061.7419 | R3: =L3*M3 -> 0 | V3: 295 | AB3: =U3*M3 -> 0 | AC3: =+V3*M3 -> 6087.7085 | AD3: =+M3*W3 -> 0 | AE3: =+X3*M3 -> 0 | AF3: =+Y3*M3 -> 0 | AG3: =+Z3*M3 -> 0
B4: 1-002400 | C4: CGL24122386 | D4: 45694 | E4: C0085 | F4: HM ULUSLARARASI PROJE TASIMACILIGI A.S | G4: 0 | H4: 75 | I4: 0 | J4: =SUM(G4:I4) -> 75 | K4: 0 | L4: =J4-K4 -> 75 | M4: 20.6363 | N4: =H4*M4 -> 1547.7225 | O4: =I4*M4 -> 0 | P4: =J4*M4 -> 1547.7225 | Q4: =M4*K4 -> 0 | R4: =L4*M4 -> 1547.7225 | V4: 75 | AB4: =U4*M4 -> 0 | AC4: =+V4*M4 -> 1547.7225 | AD4: =+M4*W4 -> 0 | AE4: =+X4*M4 -> 0 | AF4: =+Y4*M4 -> 0 | AG4: =+Z4*M4 -> 0
B5: 1-002421 | C5: CGL24122386 | D5: 45701 | E5: C0086 | F5: GOMSA INTEGRADORA | G5: 0 | H5: 245 | I5: 39.2 | J5: =SUM(G5:I5) -> 284.2 | K5: 284.2 | L5: =J5-K5 -> 0 | M5: 20.4917 | N5: =H5*M5 -> 5020.4665 | O5: =I5*M5 -> 803.27464 | P5: =J5*M5 -> 5823.7411 | Q5: =M5*K5 -> 5823.7411 | R5: =L5*M5 -> 0 | Y5: 245 | AB5: =U5*M5 -> 0 | AC5: =+V5*M5 -> 0 | AD5: =+M5*W5 -> 0 | AE5: =+X5*M5 -> 0 | AF5: =+Y5*M5 -> 5020.4665 | AG5: =+Z5*M5 -> 0
B6: 1-002422 | C6: CGL24122386 | D6: 45701 | E6: C0086 | F6: GOMSA INTEGRADORA | G6: 0 | H6: 145 | I6: 0 | J6: =SUM(G6:I6) -> 145 | K6: 145 | L6: =J6-K6 -> 0 | M6: 20.4917 | N6: =H6*M6 -> 2971.2965 | O6: =I6*M6 -> 0 | P6: =J6*M6 -> 2971.2965 | Q6: =M6*K6 -> 2971.2965 | R6: =L6*M6 -> 0 | Y6: 70 | Z6: 75 | AB6: =U6*M6 -> 0 | AC6: =+V6*M6 -> 0 | AD6: =+M6*W6 -> 0 | AE6: =+X6*M6 -> 0 | AF6: =+Y6*M6 -> 1434.419 | AG6: =+Z6*M6 -> 1536.8775
B7: 1-002426 | C7: CGL25012490 | D7: 45701 | E7: C0091 | F7: INNOVATIVE PORTING SL | G7: 0 | H7: 235 | I7: 0 | J7: =SUM(G7:I7) -> 235 | K7: 235 | L7: =J7-K7 -> 0 | M7: 20.4917 | N7: =H7*M7 -> 4815.5495 | O7: =I7*M7 -> 0 | P7: =J7*M7 -> 4815.5495 | Q7: =M7*K7 -> 4815.5495 | R7: =L7*M7 -> 0 | W7: 235 | AB7: =U7*M7 -> 0 | AC7: =+V7*M7 -> 0 | AD7: =+M7*W7 -> 4815.5495 | AE7: =+X7*M7 -> 0 | AF7: =+Y7*M7 -> 0 | AG7: =+Z7*M7 -> 0
B8: 1-002436 | C8: CGL25012490 | D8: 45707 | E8: C0093 | F8: DESCAFEINADORES MEXICANOS | G8: 0 | H8: 105 | I8: 0 | J8: =SUM(G8:I8) -> 105 | K8: 105 | L8: =J8-K8 -> 0 | M8: 20.2617 | N8: =H8*M8 -> 2127.4785 | O8: =I8*M8 -> 0 | P8: =J8*M8 -> 2127.4785 | Q8: =M8*K8 -> 2127.4785 | R8: =L8*M8 -> 0 | Y8: 105 | AB8: =U8*M8 -> 0 | AC8: =+V8*M8 -> 0 | AD8: =+M8*W8 -> 0 | AE8: =+X8*M8 -> 0 | AF8: =+Y8*M8 -> 2127.4785 | AG8: =+Z8*M8 -> 0
B9: 1-002437 | C9: CGL25012490 | D9: 45707 | E9: C0093 | F9: DESCAFEINADORES MEXICANOS | G9: 0 | H9: 50 | I9: 8 | J9: =SUM(G9:I9) -> 58 | K9: 58 | L9: =J9-K9 -> 0 | M9: 20.2617 | N9: =H9*M9 -> 1013.085 | O9: =I9*M9 -> 162.0936 | P9: =J9*M9 -> 1175.1786 | Q9: =M9*K9 -> 1175.1786 | R9: =L9*M9 -> 0 | Y9: 50 | AB9: =U9*M9 -> 0 | AC9: =+V9*M9 -> 0 | AD9: =+M9*W9 -> 0 | AE9: =+X9*M9 -> 0 | AF9: =+Y9*M9 -> 1013.085 | AG9: =+Z9*M9 -> 0
B10: 1-002454 | C10: CGL25012438 | D10: 45712 | E10: C0079 | F10: CORE GLOBAL TRANSPORT | G10: 0 | H10: 1725 | I10: 0 | J10: =SUM(G10:I10) -> 1725 | K10: 0 | L10: =J10-K10 -> 1725 | M10: 20.3448 | N10: =H10*M10 -> 35094.78 | O10: =I10*M10 -> 0 | P10: =J10*M10 -> 35094.78 | Q10: =M10*K10 -> 0 | R10: =L10*M10 -> 35094.78 | U10: 1725 | AB10: =U10*M10 -> 35094.78 | AC10: =+V10*M10 -> 0 | AD10: =+M10*W10 -> 0 | AE10: =+X10*M10 -> 0 | AF10: =+Y10*M10 -> 0 | AG10: =+Z10*M10 -> 0
B11: 2-002463 | C11: CGL25012519 | D11: 45714 | E11: C0084 | F11: JOINT PRODUCTION TECTRAN | G11: 0 | H11: 6125 | I11: 0 | J11: =SUM(G11:I11) -> 6125 | K11: 0 | L11: =J11-K11 -> 6125 | M11: 20.4683 | N11: =H11*M11 -> 125368.34 | O11: =I11*M11 -> 0 | P11: =J11*M11 -> 125368.34 | Q11: =M11*K11 -> 0 | R11: =L11*M11 -> 125368.34 | U11: 6125 | AB11: =U11*M11 -> 125368.34 | AC11: =+V11*M11 -> 0 | AD11: =+M11*W11 -> 0 | AE11: =+X11*M11 -> 0 | AF11: =+Y11*M11 -> 0 | AG11: =+Z11*M11 -> 0
B12: 1-002472 | C12: CGL25012499 | D12: 45715 | E12: C0086 | F12: GOMSA INTEGRADORA | G12: 0 | H12: 245 | I12: 39.2 | J12: =SUM(G12:I12) -> 284.2 | K12: 284.2 | L12: =J12-K12 -> 0 | M12: 20.4277 | N12: =H12*M12 -> 5004.7865 | O12: =I12*M12 -> 800.76584 | P12: =J12*M12 -> 5805.5523 | Q12: =M12*K12 -> 5805.5523 | R12: =L12*M12 -> 0 | Y12: 245 | AB12: =U12*M12 -> 0 | AC12: =+V12*M12 -> 0 | AD12: =+M12*W12 -> 0 | AE12: =+X12*M12 -> 0 | AF12: =+Y12*M12 -> 5004.7865 | AG12: =+Z12*M12 -> 0
B13: 1-002473 | C13: CGL25012499 | D13: 45715 | E13: C0086 | F13: GOMSA INTEGRADORA | G13: 0 | H13: 125 | I13: 0 | J13: =SUM(G13:I13) -> 125 | K13: 125 | L13: =J13-K13 -> 0 | M13: 20.4277 | N13: =H13*M13 -> 2553.4625 | O13: =I13*M13 -> 0 | P13: =J13*M13 -> 2553.4625 | Q13: =M13*K13 -> 2553.4625 | R13: =L13*M13 -> 0 | V13: 125 | AB13: =U13*M13 -> 0 | AC13: =+V13*M13 -> 2553.4625 | AD13: =+M13*W13 -> 0 | AE13: =+X13*M13 -> 0 | AF13: =+Y13*M13 -> 0 | AG13: =+Z13*M13 -> 0
J14: =SUM(G14:I14) -> 0 | L14: =J14-K14 -> 0 | N14: =H14*M14 -> 0 | O14: =I14*M14 -> 0 | P14: =J14*M14 -> 0 | Q14: =M14*K14 -> 0 | R14: =L14*M14 -> 0 | AB14: =U14*M14 -> 0 | AC14: =+V14*M14 -> 0 | AD14: =+M14*W14 -> 0 | AE14: =+X14*M14 -> 0 | AF14: =+Y14*M14 -> 0 | AG14: =+Z14*M14 -> 0
J15: =SUM(G15:I15) -> 0 | L15: =J15-K15 -> 0 | N15: =H15*M15 -> 0 | O15: =I15*M15 -> 0 | P15: =J15*M15 -> 0 | Q15: =M15*K15 -> 0 | R15: =L15*M15 -> 0 | AB15: =U15*M15 -> 0 | AC15: =+V15*M15 -> 0 | AD15: =+M15*W15 -> 0 | AE15: =+X15*M15 -> 0 | AF15: =+Y15*M15 -> 0 | AG15: =+Z15*M15 -> 0
J16: =SUM(G16:I16) -> 0 | L16: =J16-K16 -> 0 | N16: =H16*M16 -> 0 | O16: =I16*M16 -> 0 | P16: =J16*M16 -> 0 | Q16: =M16*K16 -> 0 | R16: =L16*M16 -> 0 | AB16: =U16*M16 -> 0 | AC16: =+V16*M16 -> 0 | AD16: =+M16*W16 -> 0 | AE16: =+X16*M16 -> 0 | AF16: =+Y16*M16 -> 0 | AG16: =+Z16*M16 -> 0
J17: =SUM(G17:I17) -> 0 | L17: =J17-K17 -> 0 | N17: =H17*M17 -> 0 | O17: =I17*M17 -> 0 | P17: =J17*M17 -> 0 | Q17: =M17*K17 -> 0 | R17: =L17*M17 -> 0 | AB17: =U17*M17 -> 0 | AC17: =+V17*M17 -> 0 | AD17: =+M17*W17 -> 0 | AE17: =+X17*M17 -> 0 | AF17: =+Y17*M17 -> 0 | AG17: =+Z17*M17 -> 0
J18: =SUM(G18:I18) -> 0 | L18: =J18-K18 -> 0 | N18: =H18*M18 -> 0 | O18: =I18*M18 -> 0 | P18: =J18*M18 -> 0 | Q18: =M18*K18 -> 0 | R18: =L18*M18 -> 0 | AB18: =U18*M18 -> 0 | AC18: =+V18*M18 -> 0 | AD18: =+M18*W18 -> 0 | AE18: =+X18*M18 -> 0 | AF18: =+Y18*M18 -> 0 | AG18: =+Z18*M18 -> 0
G19: =+SUM(G3:G18) -> 0 | H19: =+SUM(H3:H18) -> 9370 | I19: =+SUM(I3:I18) -> 133.6 | J19: =+SUM(J3:J18) -> 9503.6 | K19: =+SUM(K3:K18) -> 1578.6 | L19: =+SUM(L3:L18) -> 7925 | N19: =+SUM(N3:N18) -> 191604.67 | O19: =+SUM(O3:O18) -> 2740.1674 | P19: =+SUM(P3:P18) -> 194344.84 | Q19: =+SUM(Q3:Q18) -> 32334.001 | R19: =+SUM(R3:R18) -> 162010.84 | U19: =+SUM(U3:U18) -> 7850 | V19: =+SUM(V3:V18) -> 495 | W19: =+SUM(W3:W18) -> 235 | X19: =+SUM(X3:X18) -> 0 | Y19: =+SUM(Y3:Y18) -> 715 | Z19: =+SUM(Z3:Z18) -> 75 | AB19: =+SUM(AB3:AB18) -> 160463.12 | AC19: =+SUM(AC3:AC18) -> 10188.894 | AD19: =+SUM(AD3:AD18) -> 4815.5495 | AE19: =+SUM(AE3:AE18) -> 0 | AF19: =+SUM(AF3:AF18) -> 14600.236 | AG19: =+SUM(AG3:AG18) -> 1536.8775
Z20: =+SUM(T19:Z19) -> 9370 | AG20: =+SUM(AB19:AG19) -> 191604.67
Z21: =+Z20-H19 -> 0 | AG21: =+AG20-N19 -> 0
N22: =+N3+N5+N9+N12 -> 17126.046 | O22: 0.16
N23: =+N4+N6+N7+N8+N10+N11+N13 -> 174478.63 | O23: 0

Sheet MAR MXN
A1: SERIE | B1: FACTURA | C1: TRAFICO | D1: FECHA | E1: CLIENTE | F1: CLIENTE NOMBRE | G1: COMPROBADOS | H1: COMPLEMENTARIOS | I1: IVA | J1: SUBTOTAL | K1: ANTICIPO | L1: TOTAL | M1: MONEDA | P1: DOCUMENTACION, ALMACENAJES Y MANIOBRAS ( TER) | Q1: IMPUESTOS ADUANALES (TER) | S1: HONORARIOS | T1: REVALIDACION GUIA / BOL | U1: MANIOBRAS | V1: ALMACENAJES | W1: SERVICIOS LOGISTICOS | X1: CONSOLIDACION DE ENTRADAS | Y1: RECONOCIMIENTO ADUANERO | Z1: GASTOS EN ORIGEN | AA1: CERTIFICADO DE ORIGEN | AB1: SERVICIOS EXTRAORDINARIO | AC1: SERVICIOS COMPLEMENTARIOS | AD1: SERVICIO DE MENSAJERIA | AE1: LIBRACION DE DOCUMENTOS | AF1: GASTOS EN DESTINO | AJ1: MXN | AK1: USD | AL1: TOTAL | AM1: PORCENTAJE
A2: 1000 | B2: 1-002480 | C2: CGL25022585 | D2: 45720 | E2: C0004 | F2: NAPS-GUANAJUATO AMERICAN BOA | G2: 781 | H2: 27923.01 | I2: 4467.68 | J2: =SUM(G2:I2) -> 33171.69 | K2: 33455.25 | L2: =+J2-K2 -> -283.56 | M2: MXN | P2: 0 | Q2: 781 | S2: 6128.31 | T2: 5197.2 | U2: 15000 | V2: 0 | W2: 0 | X2: 0 | Y2: 0 | Z2: 0 | AA2: 0 | AB2: 0 | AC2: 0 | AD2: 0 | AE2: 0 | AF2: 1597.5 | AG2: =+SUM(S2:AF2)-H2 -> 0 | AI2: HONORARIOS | AJ2: =+S100 -> 396873.24 | AL2: =SUM(AJ2:AK2) -> 396873.24 | AM2: =+AL2/AL17 -> 0.13022685
A3: 2000 | B3: 2-002483 | C3: CGL25022594 | D3: 45721 | E3: C0002 | F3: NAPS-GUANAJUATO CAM | G3: 336 | H3: 14040.49 | I3: 2246.48 | J3: =SUM(G3:I3) -> 16622.97 | K3: 16622.97 | L3: =+J3-K3 -> 0 | M3: MXN | P3: 0 | Q3: 336 | S3: 6140.49 | T3: 0 | U3: 0 | V3: 0 | W3: 7900 | X3: 0 | Y3: 0 | Z3: 0 | AA3: 0 | AB3: 0 | AC3: 0 | AD3: 0 | AE3: 0 | AF3: 0 | AG3: =+SUM(S3:AF3)-H3 -> 0 | AI3: REVALIDACION GUIA / BOL | AJ3: =+T100 -> 17053.96 | AK3: =+'MAR USD '!AC19 -> 5045.5992 | AL3: =SUM(AJ3:AK3) -> 22099.559 | AM3: =+AL3/AL17 -> 0.0072515747
A4: 2000 | B4: 2-002484 | C4: CGL25022593 | D4: 45721 | E4: C0002 | F4: NAPS-GUANAJUATO CAM | G4: 336 | H4: 14040.49 | I4: 2246.48 | J4: =SUM(G4:I4) -> 16622.97 | K4: 16622.97 | L4: =+J4-K4 -> 0 | M4: MXN | P4: 0 | Q4: 336 | S4: 6140.49 | T4: 0 | U4: 0 | V4: 0 | W4: 7900 | X4: 0 | Y4: 0 | Z4: 0 | AA4: 0 | AB4: 0 | AC4: 0 | AD4: 0 | AE4: 0 | AF4: 0 | AG4: =+SUM(S4:AF4)-H4 -> 0 | AI4: MANIOBRAS | AJ4: =+U100 -> 558468.45 | AK4: =+'MAR USD '!AD19 -> 14280.21 | AL4: =SUM(AJ4:AK4) -> 572748.66 | AM4: =+AL4/AL17 -> 0.18793722
A5: 1000 | B5: 1-002485 | C5: CGL25022566 | D5: 45722 | E5: C0001 | F5: ARMOR MEXICO IMAGING SUPPLIES | G5: 0 | H5: 73861.99 | I5: 11817.92 | J5: =SUM(G5:I5) -> 85679.91 | K5: 0 | L5: =+J5-K5 -> 85679.91 | M5: MXN | P5: 0 | Q5: 0 | S5: 6111.99 | T5: 0 | U5: 25750 | V5: 0 | W5: 42000 | X5: 0 | Y5: 0 | Z5: 0 | AA5: 0 | AB5: 0 | AC5: 0 | AD5: 0 | AE5: 0 | AF5: 0 | AG5: =+SUM(S5:AF5)-H5 -> 0 | AI5: ALMACENAJES | AJ5: =+V100 -> 16647.13 | AK5: =+'MAR USD '!AE19 -> 157626.59 | AL5: =SUM(AJ5:AK5) -> 174273.72 | AM5: =+AL5/AL17 -> 0.057184801
A6: 2000 | B6: 2-002486 | C6: CGL25022577 | D6: 45722 | E6: C0002 | F6: NAPS-GUANAJUATO CAM | G6: 30731 | H6: 14163.85 | I6: 2266.22 | J6: =SUM(G6:I6) -> 47161.07 | K6: 47094.07 | L6: =+J6-K6 -> 67 | M6: MXN | P6: 0 | Q6: 30731 | S6: 4085.54 | T6: 0 | U6: 0 | V6: 0 | W6: 3950 | X6: 6128.31 | Y6: 0 | Z6: 0 | AA6: 0 | AB6: 0 | AC6: 0 | AD6: 0 | AE6: 0 | AF6: 0 | AG6: =+SUM(S6:AF6)-H6 -> 0 | AI6: SERVICIOS LOGISTICOS | AJ6: =+W100 -> 1298164 | AK6: =+'MAR USD '!AB19 -> 402610.74 | AL6: =SUM(AJ6:AK6) -> 1700774.7 | AM6: =+AL6/AL17 -> 0.55807878
A7: 2000 | B7: 2-002487 | C7: CGL25022599 | D7: 45722 | E7: C0024 | F7: SELLOS Y RETENES DE SAN LUIS | G7: 40553 | H7: 7700.77 | I7: 1232.13 | J7: =SUM(G7:I7) -> 49485.9 | K7: 49485.9 | L7: =+J7-K7 -> 0 | M7: MXN | P7: 0 | Q7: 40553 | S7: =6165.35+1535.42 -> 7700.77 | T7: 0 | U7: 0 | V7: 0 | W7: 0 | X7: 0 | Y7: 0 | Z7: 0 | AA7: 0 | AB7: 0 | AC7: 0 | AD7: 0 | AE7: 0 | AF7: 0 | AG7: =+SUM(S7:AF7)-H7 -> 0 | AI7: CONSOLIDACION DE ENTRADAS | AJ7: =+X100 -> 38443.89 | AL7: =SUM(AJ7:AK7) -> 38443.89 | AM7: =+AL7/AL17 -> 0.012614674
A8: 1000 | B8: 1-002488 | C8: CGL25022628 | D8: 45722 | E8: C0006 | F8: CLEVELAND DIE QUERETARO | G8: 14746 | H8: 34700 | I8: 5552 | J8: =SUM(G8:I8) -> 54998 | K8: 54998 | L8: =+J8-K8 -> 0 | M8: MXN | P8: 0 | Q8: 14746 | S8: 6500 | T8: 0 | U8: 24000 | V8: 0 | W8: 4200 | X8: 0 | Y8: 0 | Z8: 0 | AA8: 0 | AB8: 0 | AC8: 0 | AD8: 0 | AE8: 0 | AF8: 0 | AG8: =+SUM(S8:AF8)-H8 -> 0 | AI8: RECONOCIMIENTO ADUANERO | AJ8: =+Y100 -> 12000 | AL8: =SUM(AJ8:AK8) -> 12000 | AM8: =+AL8/AL17 -> 0.0039375852
A9: 1000 | B9: 1-002490 | C9: CGL25032636 | D9: 45726 | E9: C0001 | F9: ARMOR MEXICO IMAGING SUPPLIES | G9: 0 | H9: 11340.08 | I9: 1814.42 | J9: =SUM(G9:I9) -> 13154.5 | K9: 0 | L9: =+J9-K9 -> 13154.5 | M9: MXN | P9: 0 | Q9: 0 | S9: 4092.8 | T9: 0 | U9: 3569.8 | V9: 1177.48 | W9: 2500 | X9: 0 | Y9: 0 | Z9: 0 | AA9: 0 | AB9: 0 | AC9: 0 | AD9: 0 | AE9: 0 | AF9: 0 | AG9: =+SUM(S9:AF9)-H9 -> 0 | AI9: GASTOS EN ORIGEN | AJ9: =+Z100 -> 7200 | AL9: =SUM(AJ9:AK9) -> 7200 | AM9: =+AL9/AL17 -> 0.0023625511
A10: 1000 | B10: 1-002491 | C10: CGL25032675 | D10: 45728 | E10: C0001 | F10: ARMOR MEXICO IMAGING SUPPLIES | G10: 0 | H10: 3540 | I10: 566.4 | J10: =SUM(G10:I10) -> 4106.4 | K10: 0 | L10: =+J10-K10 -> 4106.4 | M10: MXN | P10: 0 | Q10: 0 | S10: 0 | T10: 0 | U10: 0 | V10: 0 | W10: 0 | X10: 0 | Y10: 0 | Z10: 0 | AA10: 3540 | AB10: 0 | AC10: 0 | AD10: 0 | AE10: 0 | AF10: 0 | AG10: =+SUM(S10:AF10)-H10 -> 0 | AI10: CERTIFICADO DE ORIGEN | AJ10: =+AA100 -> 10620 | AL10: =SUM(AJ10:AK10) -> 10620 | AM10: =+AL10/AL17 -> 0.0034847629
A11: 2000 | B11: 2-002492 | C11: CGL25012529 | D11: 45729 | E11: C0002 | F11: NAPS-GUANAJUATO CAM | G11: 6808 | H11: 4101.6 | I11: 656.26 | J11: =SUM(G11:I11) -> 11565.86 | K11: 11565.86 | L11: =+J11-K11 -> 0 | M11: MXN | P11: 0 | Q11: 6808 | S11: 4101.6 | T11: 0 | U11: 0 | V11: 0 | W11: 0 | X11: 0 | Y11: 0 | Z11: 0 | AA11: 0 | AB11: 0 | AC11: 0 | AD11: 0 | AE11: 0 | AF11: 0 | AG11: =+SUM(S11:AF11)-H11 -> 0 | AI11: SERVICIOS EXTRAORDINARIO | AJ11: =+AB100 -> 8440 | AL11: =SUM(AJ11:AK11) -> 8440 | AM11: =+AL11/AL17 -> 0.0027694349
A12: 2000 | B12: 2-002493 | C12: CGL25022626 | D12: 45729 | E12: C0002 | F12: NAPS-GUANAJUATO CAM | G12: 336 | H12: 14155.54 | I12: 2264.89 | J12: =SUM(G12:I12) -> 16756.43 | K12: 16756.43 | L12: =+J12-K12 -> 0 | M12: MXN | P12: 0 | Q12: 336 | S12: 6255.54 | T12: 0 | U12: 0 | V12: 0 | W12: 7900 | X12: 0 | Y12: 0 | Z12: 0 | AA12: 0 | AB12: 0 | AC12: 0 | AD12: 0 | AE12: 0 | AF12: 0 | AG12: =+SUM(S12:AF12)-H12 -> 0 | AI12: SERVICIOS COMPLEMENTARIOS | AJ12: =+AC100 -> 6500 | AL12: =SUM(AJ12:AK12) -> 6500 | AM12: =+AL12/AL17 -> 0.0021328586
A13: 2000 | B13: 2-002494 | C13: CGL25032639 | D13: 45729 | E13: C0002 | F13: NAPS-GUANAJUATO CAM | G13: 781 | H13: 8120.36 | I13: 1299.26 | J13: =SUM(G13:I13) -> 10200.62 | K13: 10200.62 | L13: =+J13-K13 -> 0 | M13: MXN | P13: 0 | Q13: 781 | S13: 4170.36 | T13: 0 | U13: 0 | V13: 0 | W13: 3950 | X13: 0 | Y13: 0 | Z13: 0 | AA13: 0 | AB13: 0 | AC13: 0 | AD13: 0 | AE13: 0 | AF13: 0 | AG13: =+SUM(S13:AF13)-H13 -> 0 | AI13: SERVICIO DE MENSAJERIA | AJ13: =+AD100 -> 1000 | AL13: =SUM(AJ13:AK13) -> 1000 | AM13: =+AL13/AL17 -> 0.0003281321
A14: 2000 | B14: 2-002495 | C14: CGL25032640 | D14: 45729 | E14: C0002 | F14: NAPS-GUANAJUATO CAM | G14: 781 | H14: 8120.36 | I14: 1299.26 | J14: =SUM(G14:I14) -> 10200.62 | K14: 10200.62 | L14: =+J14-K14 -> 0 | M14: MXN | P14: 0 | Q14: 781 | S14: 4170.36 | T14: 0 | U14: 0 | V14: 0 | W14: 3950 | X14: 0 | Y14: 0 | Z14: 0 | AA14: 0 | AB14: 0 | AC14: 0 | AD14: 0 | AE14: 0 | AF14: 0 | AG14: =+SUM(S14:AF14)-H14 -> 0 | AI14: LIBRACION DE DOCUMENTOS | AJ14: =+AE100 -> 3195 | AL14: =SUM(AJ14:AK14) -> 3195 | AM14: =+AL14/AL17 -> 0.0010483821
A15: 2000 | B15: 2-002496 | C15: CGL25032641 | D15: 45729 | E15: C0002 | F15: NAPS-GUANAJUATO CAM | G15: 781 | H15: 8120.36 | I15: 1299.26 | J15: =SUM(G15:I15) -> 10200.62 | K15: 10200.62 | L15: =+J15-K15 -> 0 | M15: MXN | P15: 0 | Q15: 781 | S15: 4170.36 | T15: 0 | U15: 0 | V15: 0 | W15: 3950 | X15: 0 | Y15: 0 | Z15: 0 | AA15: 0 | AB15: 0 | AC15: 0 | AD15: 0 | AE15: 0 | AF15: 0 | AG15: =+SUM(S15:AF15)-H15 -> 0 | AI15: GASTOS EN DESTINO | AJ15: =+AF100 -> 43554.1 | AK15: =+'MAR USD '!AF19 -> 49830.213 | AL15: =SUM(AJ15:AK15) -> 93384.313 | AM15: =+AL15/AL17 -> 0.03064239
A16: 2000 | B16: 2-002497 | C16: CGL25022627 | D16: 45729 | E16: C0002 | F16: NAPS-GUANAJUATO CAM | G16: 336 | H16: 14155.54 | I16: 2264.89 | J16: =SUM(G16:I16) -> 16756.43 | K16: 16756.43 | L16: =+J16-K16 -> 0 | M16: MXN | P16: 0 | Q16: 336 | S16: 6255.54 | T16: 0 | U16: 0 | V16: 0 | W16: 7900 | X16: 0 | Y16: 0 | Z16: 0 | AA16: 0 | AB16: 0 | AC16: 0 | AD16: 0 | AE16: 0 | AF16: 0 | AG16: =+SUM(S16:AF16)-H16 -> 0
A17: 1000 | B17: 1-002498 | C17: CGL25032671 | D17: 45730 | E17: C0001 | F17: ARMOR MEXICO IMAGING SUPPLIES | G17: 0 | H17: 9517.8 | I17: 1522.85 | J17: =SUM(G17:I17) -> 11040.65 | K17: 0 | L17: =+J17-K17 -> 11040.65 | M17: MXN | P17: 0 | Q17: 0 | S17: 4055.54 | T17: 1500 | U17: 1462.26 | V17: 0 | W17: 2500 | X17: 0 | Y17: 0 | Z17: 0 | AA17: 0 | AB17: 0 | AC17: 0 | AD17: 0 | AE17: 0 | AF17: 0 | AG17: =+SUM(S17:AF17)-H17 -> 0 | AJ17: =+SUM(AJ2:AJ16) -> 2418159.8 | AK17: =+SUM(AK2:AK16) -> 629393.35 | AL17: =+SUM(AL2:AL16) -> 3047553.1 | AM17: =+SUM(AM2:AM16) -> 1
A18: 2000 | B18: 2-002500 | C18: CGL25022612 | D18: 45730 | E18: C0069 | F18: JOINT PRODUCTION HONOR | G18: 336 | H18: 15356 | I18: 2456.96 | J18: =SUM(G18:I18) -> 18148.96 | K18: 18593.96 | L18: =+J18-K18 -> -445 | M18: MXN | P18: 0 | Q18: 336 | S18: =7678+7678 -> 15356 | T18: 0 | U18: 0 | V18: 0 | W18: 0 | X18: 0 | Y18: 0 | Z18: 0 | AA18: 0 | AB18: 0 | AC18: 0 | AD18: 0 | AE18: 0 | AF18: 0 | AG18: =+SUM(S18:AF18)-H18 -> 0
A19: 1000 | B19: 1-002501 | C19: CGL25022591 | D19: 45730 | E19: C0004 | F19: NAPS-GUANAJUATO AMERICAN BOA | G19: 1019 | H19: 16078.51 | I19: 2572.56 | J19: =SUM(G19:I19) -> 19670.07 | K19: 19670.07 | L19: =+J19-K19 -> 0 | M19: MXN | P19: 0 | Q19: 1019 | S19: 6078.51 | T19: 0 | U19: 10000 | V19: 0 | W19: 0 | X19: 0 | Y19: 0 | Z19: 0 | AA19: 0 | AB19: 0 | AC19: 0 | AD19: 0 | AE19: 0 | AF19: 0 | AG19: =+SUM(S19:AF19)-H19 -> 0
A20: 2000 | B20: 2-002502 | C20: CGL25032674 | D20: 45735 | E20: C0081 | F20: JOINT PRODUCTION BLACK SMITH | G20: 0 | H20: 22000 | I20: 3520 | J20: =SUM(G20:I20) -> 25520 | K20: 25520 | L20: =+J20-K20 -> 0 | M20: MXN | P20: 0 | Q20: 0 | S20: 0 | T20: 0 | U20: 0 | V20: 0 | W20: 22000 | X20: 0 | Y20: 0 | Z20: 0 | AA20: 0 | AB20: 0 | AC20: 0 | AD20: 0 | AE20: 0 | AF20: 0 | AG20: =+SUM(S20:AF20)-H20 -> 0
A21: 2000 | B21: 2-002503 | C21: CGL25032652 | D21: 45735 | E21: C0081 | F21: JOINT PRODUCTION BLACK SMITH | G21: 0 | H21: 22000 | I21: 3520 | J21: =SUM(G21:I21) -> 25520 | K21: 25520 | L21: =+J21-K21 -> 0 | M21: MXN | P21: 0 | Q21: 0 | S21: 0 | T21: 0 | U21: 0 | V21: 0 | W21: 22000 | X21: 0 | Y21: 0 | Z21: 0 | AA21: 0 | AB21: 0 | AC21: 0 | AD21: 0 | AE21: 0 | AF21: 0 | AG21: =+SUM(S21:AF21)-H21 -> 0
A22: 2000 | B22: 2-002504 | C22: CGL25032648 | D22: 45735 | E22: C0081 | F22: JOINT PRODUCTION BLACK SMITH | G22: 0 | H22: 22000 | I22: 3520 | J22: =SUM(G22:I22) -> 25520 | K22: 25520 | L22: =+J22-K22 -> 0 | M22: MXN | P22: 0 | Q22: 0 | S22: 0 | T22: 0 | U22: 0 | V22: 0 | W22: 22000 | X22: 0 | Y22: 0 | Z22: 0 | AA22: 0 | AB22: 0 | AC22: 0 | AD22: 0 | AE22: 0 | AF22: 0 | AG22: =+SUM(S22:AF22)-H22 -> 0
A23: 2000 | B23: 2-002505 | C23: CGL25032653 | D23: 45735 | E23: C0081 | F23: JOINT PRODUCTION BLACK SMITH | G23: 0 | H23: 22000 | I23: 3520 | J23: =SUM(G23:I23) -> 25520 | K23: 25520 | L23: =+J23-K23 -> 0 | M23: MXN | P23: 0 | Q23: 0 | S23: 0 | T23: 0 | U23: 0 | V23: 0 | W23: 22000 | X23: 0 | Y23: 0 | Z23: 0 | AA23: 0 | AB23: 0 | AC23: 0 | AD23: 0 | AE23: 0 | AF23: 0 | AG23: =+SUM(S23:AF23)-H23 -> 0
A24: 1000 | B24: 1-002507 | C24: CGL25022604 | D24: 45735 | E24: C0005 | F24: HAHN AUTOMATION | G24: 5563 | H24: 19998 | I24: 3199.68 | J24: =SUM(G24:I24) -> 28760.68 | K24: 28670.68 | L24: =+J24-K24 -> 90 | M24: MXN | P24: 0 | Q24: 5563 | S24: 4450 | T24: 0 | U24: 6500 | V24: 0 | W24: 9048 | X24: 0 | Y24: 0 | Z24: 0 | AA24: 0 | AB24: 0 | AC24: 0 | AD24: 0 | AE24: 0 | AF24: 0 | AG24: =+SUM(S24:AF24)-H24 -> 0
A25: 2000 | B25: 2-002508 | C25: CGL25022588 | D25: 45735 | E25: C0002 | F25: NAPS-GUANAJUATO CAM | G25: 3550 | H25: 8005.74 | I25: 1280.92 | J25: =SUM(G25:I25) -> 12836.66 | K25: 12836.66 | L25: =+J25-K25 -> 0 | M25: MXN | P25: 0 | Q25: 3550 | S25: 4055.74 | T25: 0 | U25: 0 | V25: 0 | W25: 3950 | X25: 0 | Y25: 0 | Z25: 0 | AA25: 0 | AB25: 0 | AC25: 0 | AD25: 0 | AE25: 0 | AF25: 0 | AG25: =+SUM(S25:AF25)-H25 -> 0
A26: 2000 | B26: 2-002509 | C26: CGL25032632 | D26: 45735 | E26: C0002 | F26: NAPS-GUANAJUATO CAM | G26: 781 | H26: 8036.66 | I26: 1285.87 | J26: =SUM(G26:I26) -> 10103.53 | K26: 10068.66 | L26: =+J26-K26 -> 34.87 | M26: MXN | P26: 0 | Q26: 781 | S26: 4086.66 | T26: 0 | U26: 0 | V26: 0 | W26: 3950 | X26: 0 | Y26: 0 | Z26: 0 | AA26: 0 | AB26: 0 | AC26: 0 | AD26: 0 | AE26: 0 | AF26: 0 | AG26: =+SUM(S26:AF26)-H26 -> 0
A27: 2000 | B27: 2-002510 | C27: CGL25032660 | D27: 45735 | E27: C0002 | F27: NAPS-GUANAJUATO CAM | G27: 781 | H27: 8008.44 | I27: 1281.35 | J27: =SUM(G27:I27) -> 10070.79 | K27: 10070.79 | L27: =+J27-K27 -> 0 | M27: MXN | P27: 0 | Q27: 781 | S27: 4058.44 | T27: 0 | U27: 0 | V27: 0 | W27: 3950 | X27: 0 | Y27: 0 | Z27: 0 | AA27: 0 | AB27: 0 | AC27: 0 | AD27: 0 | AE27: 0 | AF27: 0 | AG27: =+SUM(S27:AF27)-H27 -> 0
A28: 2000 | B28: 2-002511 | C28: CGL25032662 | D28: 45735 | E28: C0002 | F28: NAPS-GUANAJUATO CAM | G28: 781 | H28: 8008.44 | I28: 1281.35 | J28: =SUM(G28:I28) -> 10070.79 | K28: 10070.79 | L28: =+J28-K28 -> 0 | M28: MXN | P28: 0 | Q28: 781 | S28: 4058.44 | T28: 0 | U28: 0 | V28: 0 | W28: 3950 | X28: 0 | Y28: 0 | Z28: 0 | AA28: 0 | AB28: 0 | AC28: 0 | AD28: 0 | AE28: 0 | AF28: 0 | AG28: =+SUM(S28:AF28)-H28 -> 0
A29: 2000 | B29: 2-002512 | C29: CGL25032656 | D29: 45735 | E29: C0002 | F29: NAPS-GUANAJUATO CAM | G29: 2920 | H29: 8008.44 | I29: 1281.35 | J29: =SUM(G29:I29) -> 12209.79 | K29: 12209.79 | L29: =+J29-K29 -> 0 | M29: MXN | P29: 0 | Q29: 2920 | S29: 4058.44 | T29: 0 | U29: 0 | V29: 0 | W29: 3950 | X29: 0 | Y29: 0 | Z29: 0 | AA29: 0 | AB29: 0 | AC29: 0 | AD29: 0 | AE29: 0 | AF29: 0 | AG29: =+SUM(S29:AF29)-H29 -> 0
A30: 2000 | B30: 2-002513 | C30: CGL25032661 | D30: 45735 | E30: C0002 | F30: NAPS-GUANAJUATO CAM | G30: 781 | H30: 8017.76 | I30: 1282.84 | J30: =SUM(G30:I30) -> 10081.6 | K30: 10081.6 | L30: =+J30-K30 -> 0 | M30: MXN | P30: 0 | Q30: 781 | S30: 4067.76 | T30: 0 | U30: 0 | V30: 0 | W30: 3950 | X30: 0 | Y30: 0 | Z30: 0 | AA30: 0 | AB30: 0 | AC30: 0 | AD30: 0 | AE30: 0 | AF30: 0 | AG30: =+SUM(S30:AF30)-H30 -> 0
A31: 2000 | B31: 2-002514 | C31: CGL25022625 | D31: 45735 | E31: C0002 | F31: NAPS-GUANAJUATO CAM | G31: 3149 | H31: 8017.76 | I31: 1282.84 | J31: =SUM(G31:I31) -> 12449.6 | K31: 12449.6 | L31: =+J31-K31 -> 0 | M31: MXN | P31: 0 | Q31: 3149 | S31: 4067.76 | T31: 0 | U31: 0 | V31: 0 | W31: 3950 | X31: 0 | Y31: 0 | Z31: 0 | AA31: 0 | AB31: 0 | AC31: 0 | AD31: 0 | AE31: 0 | AF31: 0 | AG31: =+SUM(S31:AF31)-H31 -> 0
A32: 1000 | B32: 1-002515 | C32: CGL25022578 | D32: 45736 | E32: C0069 | F32: JOINT PRODUCTION HONOR | G32: 13625 | H32: 30790.96 | I32: 4926.55 | J32: =SUM(G32:I32) -> 49342.51 | K32: 63168.6 | L32: =+J32-K32 -> -13826.09 | M32: MXN | P32: 0 | Q32: 13625 | S32: =1500+7379.21 -> 8879.21 | T32: 1150 | U32: 17761.75 | V32: 0 | W32: 0 | X32: 0 | Y32: 3000 | Z32: 0 | AA32: 0 | AB32: 0 | AC32: 0 | AD32: 0 | AE32: 0 | AF32: 0 | AG32: =+SUM(S32:AF32)-H32 -> 0
A33: 2000 | B33: 2-002517 | C33: CGL25022543 | D33: 45736 | E33: C0002 | F33: NAPS-GUANAJUATO CAM | G33: 36840 | H33: 20221.04 | I33: 3235.36 | J33: =SUM(G33:I33) -> 60296.4 | K33: 60296.41 | L33: =+J33-K33 -> -0.01 | M33: MXN | P33: 0 | Q33: 36840 | S33: 4067.76 | T33: 0 | U33: 0 | V33: 0 | W33: 3950 | X33: 12203.28 | Y33: 0 | Z33: 0 | AA33: 0 | AB33: 0 | AC33: 0 | AD33: 0 | AE33: 0 | AF33: 0 | AG33: =+SUM(S33:AF33)-H33 -> 0
A34: 2000 | B34: 2-002518 | C34: CGL25032650 | D34: 45736 | E34: C0002 | F34: NAPS-GUANAJUATO CAM | G34: 336 | H34: 14001.64 | I34: 2240.26 | J34: =SUM(G34:I34) -> 16577.9 | K34: 16577.9 | L34: =+J34-K34 -> 0 | M34: MXN | P34: 0 | Q34: 336 | S34: 6101.64 | T34: 0 | U34: 0 | V34: 0 | W34: 7900 | X34: 0 | Y34: 0 | Z34: 0 | AA34: 0 | AB34: 0 | AC34: 0 | AD34: 0 | AE34: 0 | AF34: 0 | AG34: =+SUM(S34:AF34)-H34 -> 0
A35: 1000 | B35: 1-002519 | C35: CGL25022585 | D35: 45736 | E35: C0004 | F35: NAPS-GUANAJUATO AMERICAN BOA | G35: 0 | H35: 11000 | I35: 1760 | J35: =SUM(G35:I35) -> 12760 | K35: 12760 | L35: =+J35-K35 -> 0 | M35: MXN | P35: 0 | Q35: 0 | S35: 0 | T35: 0 | U35: 0 | V35: 0 | W35: 11000 | X35: 0 | Y35: 0 | Z35: 0 | AA35: 0 | AB35: 0 | AC35: 0 | AD35: 0 | AE35: 0 | AF35: 0 | AG35: =+SUM(S35:AF35)-H35 -> 0
A36: 1000 | B36: 1-002520 | C36: CGL25032637 | D36: 45736 | E36: C0084 | F36: JOINT PRODUCTION TECTRAN | G36: 0 | H36: 15556 | I36: 2488.96 | J36: =SUM(G36:I36) -> 18044.96 | K36: 18044.96 | L36: =+J36-K36 -> 0 | M36: MXN | P36: 0 | Q36: 0 | S36: 0 | T36: 0 | U36: 0 | V36: 0 | W36: 15556 | X36: 0 | Y36: 0 | Z36: 0 | AA36: 0 | AB36: 0 | AC36: 0 | AD36: 0 | AE36: 0 | AF36: 0 | AG36: =+SUM(S36:AF36)-H36 -> 0
A37: 1000 | B37: 1-002521 | C37: CGL25032633 | D37: 45736 | E37: C0069 | F37: JOINT PRODUCTION HONOR | G37: 915 | H37: 13943.68 | I37: 2230.99 | J37: =SUM(G37:I37) -> 17089.67 | K37: 16763.77 | L37: =+J37-K37 -> 325.9 | M37: MXN | P37: 0 | Q37: 915 | S37: 7369.99 | T37: 608.92 | U37: 2049.77 | V37: 0 | W37: 3915 | X37: 0 | Y37: 0 | Z37: 0 | AA37: 0 | AB37: 0 | AC37: 0 | AD37: 0 | AE37: 0 | AF37: 0 | AG37: =+SUM(S37:AF37)-H37 -> 0
A38: 2000 | B38: 2-002523 | C38: CGL25022613 | D38: 45737 | E38: C0001 | F38: ARMOR MEXICO IMAGING SUPPLIES | G38: 0 | H38: 3041.66 | I38: 486.67 | J38: =SUM(G38:I38) -> 3528.33 | K38: 0 | L38: =+J38-K38 -> 3528.33 | M38: MXN | P38: 0 | Q38: 0 | S38: 3041.66 | T38: 0 | U38: 0 | V38: 0 | W38: 0 | X38: 0 | Y38: 0 | Z38: 0 | AA38: 0 | AB38: 0 | AC38: 0 | AD38: 0 | AE38: 0 | AF38: 0 | AG38: =+SUM(S38:AF38)-H38 -> 0
A39: 2000 | B39: 2-002524 | C39: CGL25032649 | D39: 45737 | E39: C0002 | F39: NAPS-GUANAJUATO CAM | G39: 336 | H39: 14001.64 | I39: 2240.26 | J39: =SUM(G39:I39) -> 16577.9 | K39: 16577.9 | L39: =+J39-K39 -> 0 | M39: MXN | P39: 0 | Q39: 336 | S39: 6101.64 | T39: 0 | U39: 0 | V39: 0 | W39: 7900 | X39: 0 | Y39: 0 | Z39: 0 | AA39: 0 | AB39: 0 | AC39: 0 | AD39: 0 | AE39: 0 | AF39: 0 | AG39: =+SUM(S39:AF39)-H39 -> 0
A40: 2000 | B40: 2-002525 | C40: CGL25032683 | D40: 45737 | E40: C0084 | F40: JOINT PRODUCTION TECTRAN | G40: 0 | H40: 15525 | I40: 2484 | J40: =SUM(G40:I40) -> 18009 | K40: 18009 | L40: =+J40-K40 -> 0 | M40: MXN | P40: 0 | Q40: 0 | S40: 0 | T40: 0 | U40: 0 | V40: 0 | W40: 15525 | X40: 0 | Y40: 0 | Z40: 0 | AA40: 0 | AB40: 0 | AC40: 0 | AD40: 0 | AE40: 0 | AF40: 0 | AG40: =+SUM(S40:AF40)-H40 -> 0
A41: 1000 | B41: 1-002526 | C41: CGL25032667 | D41: 45737 | E41: C0069 | F41: JOINT PRODUCTION HONOR | G41: 1379 | H41: 13193.61 | I41: 2110.98 | J41: =SUM(G41:I41) -> 16683.59 | K41: 20443.44 | L41: =+J41-K41 -> -3759.85 | M41: MXN | P41: 0 | Q41: 1379 | S41: 7305.19 | T41: 608.92 | U41: 1364.5 | V41: 0 | W41: 3915 | X41: 0 | Y41: 0 | Z41: 0 | AA41: 0 | AB41: 0 | AC41: 0 | AD41: 0 | AE41: 0 | AF41: 0 | AG41: =+SUM(S41:AF41)-H41 -> 0
A42: 2000 | B42: 2-002527 | C42: CGL25022622 | D42: 45737 | E42: C0081 | F42: JOINT PRODUCTION BLACK SMITH | G42: 0 | H42: 22000 | I42: 3520 | J42: =SUM(G42:I42) -> 25520 | K42: 25520 | L42: =+J42-K42 -> 0 | M42: MXN | P42: 0 | Q42: 0 | S42: 0 | T42: 0 | U42: 0 | V42: 0 | W42: 22000 | X42: 0 | Y42: 0 | Z42: 0 | AA42: 0 | AB42: 0 | AC42: 0 | AD42: 0 | AE42: 0 | AF42: 0 | AG42: =+SUM(S42:AF42)-H42 -> 0
A43: 2000 | B43: 2-002528 | C43: CGL25032634 | D43: 45737 | E43: C0081 | F43: JOINT PRODUCTION BLACK SMITH | G43: 0 | H43: 22000 | I43: 3520 | J43: =SUM(G43:I43) -> 25520 | K43: 25520 | L43: =+J43-K43 -> 0 | M43: MXN | P43: 0 | Q43: 0 | S43: 0 | T43: 0 | U43: 0 | V43: 0 | W43: 22000 | X43: 0 | Y43: 0 | Z43: 0 | AA43: 0 | AB43: 0 | AC43: 0 | AD43: 0 | AE43: 0 | AF43: 0 | AG43: =+SUM(S43:AF43)-H43 -> 0
A44: 2000 | B44: 2-002529 | C44: CGL25032642 | D44: 45737 | E44: C0081 | F44: JOINT PRODUCTION BLACK SMITH | G44: 0 | H44: 22000 | I44: 3520 | J44: =SUM(G44:I44) -> 25520 | K44: 25520 | L44: =+J44-K44 -> 0 | M44: MXN | P44: 0 | Q44: 0 | S44: 0 | T44: 0 | U44: 0 | V44: 0 | W44: 22000 | X44: 0 | Y44: 0 | Z44: 0 | AA44: 0 | AB44: 0 | AC44: 0 | AD44: 0 | AE44: 0 | AF44: 0 | AG44: =+SUM(S44:AF44)-H44 -> 0
... A52: 1000 | B52: 1-002537 | C52: CGL24092105 | D52: 45740 | E52: C0002 | F52: NAPS-GUANAJUATO CAM | G52: 0 | H52: 49156.6 | I52: 0 | J52: =SUM(G52:I52) -> 49156.6 | K52: 49156.6 | L52: =+J52-K52 -> 0 | M52: MXN | P52: 0 | Q52: 0 | S52: 0 | T52: 0 | U52: 0 | V52: 0 | W52: 0 | X52: 0 | Y52: 0 | Z52: 7200 | AA52: 0 | AB52: 0 | AC52: 0 | AD52: 0 | AE52: 0 | AF52: 41956.6 | AG52: =+SUM(S52:AF52)-H52 -> 0
A53: 1000 | B53: 1-002538 | C53: CGL24092105 | D53: 45740 | E53: C0002 | F53: NAPS-GUANAJUATO CAM | G53: 107788 | H53: 80600.87 | I53: 12896.14 | J53: =SUM(G53:I53) -> 201285.01 | K53: 201285.01 | L53: =+J53-K53 -> 0 | M53: MXN | P53: 0 | Q53: 107788 | S53: =6103.44+1500 -> 7603.44 | T53: 1380 | U53: 14369.23 | V53: 2948.2 | W53: 51300 | X53: 0 | Y53: 3000 | Z53: 0 | AA53: 0 | AB53: 0 | AC53: 0 | AD53: 0 | AE53: 0 | AF53: 0 | AG53: =+SUM(S53:AF53)-H53 -> 0
A54: 1000 | B54: 1-002539 | C54: CGL25022606 | D54: 45741 | E54: C0067 | F54: ND AUTOMOTIVE SYSTEMS MEXICO | G54: 5269 | H54: 25217.02 | I54: 4034.72 | J54: =SUM(G54:I54) -> 34520.74 | K54: 0 | L54: =+J54-K54 -> 34520.74 | M54: MXN | P54: 0 | Q54: 5269 | S54: 6990.28 | T54: 0 | U54: =4861.38+335.36 -> 5196.74 | V54: 0 | W54: 10530 | X54: 0 | Y54: 0 | Z54: 0 | AA54: 0 | AB54: 2500 | AC54: 0 | AD54: 0 | AE54: 0 | AF54: 0 | AG54: =+SUM(S54:AF54)-H54 -> 0
A55: 2000 | B55: 2-002540 | C55: CGL25032678 | D55: 45741 | E55: C0002 | F55: NAPS-GUANAJUATO CAM | G55: 781 | H55: 7961.06 | I55: 1273.77 | J55: =SUM(G55:I55) -> 10015.83 | K55: 10015.83 | L55: =+J55-K55 -> 0 | M55: MXN | P55: 0 | Q55: 781 | S55: 4011.06 | T55: 0 | U55: 0 | V55: 0 | W55: 3950 | X55: 0 | Y55: 0 | Z55: 0 | AA55: 0 | AB55: 0 | AC55: 0 | AD55: 0 | AE55: 0 | AF55: 0 | AG55: =+SUM(S55:AF55)-H55 -> 0
A56: 2000 | B56: 2-002541 | C56: CGL25032703 | D56: 45741 | E56: C0002 | F56: NAPS-GUANAJUATO CAM | G56: 781 | H56: 7961.06 | I56: 1273.77 | J56: =SUM(G56:I56) -> 10015.83 | K56: 10015.83 | L56: =+J56-K56 -> 0 | M56: MXN | P56: 0 | Q56: 781 | S56: 4011.06 | T56: 0 | U56: 0 | V56: 0 | W56: 3950 | X56: 0 | Y56: 0 | Z56: 0 | AA56: 0 | AB56: 0 | AC56: 0 | AD56: 0 | AE56: 0 | AF56: 0 | AG56: =+SUM(S56:AF56)-H56 -> 0
A57: 2000 | B57: 2-002542 | C57: CGL25032704 | D57: 45741 | E57: C0002 | F57: NAPS-GUANAJUATO CAM | G57: 781 | H57: 7961.06 | I57: 1273.77 | J57: =SUM(G57:I57) -> 10015.83 | K57: 10015.83 | L57: =+J57-K57 -> 0 | M57: MXN | P57: 0 | Q57: 781 | S57: 4011.06 | T57: 0 | U57: 0 | V57: 0 | W57: 3950 | X57: 0 | Y57: 0 | Z57: 0 | AA57: 0 | AB57: 0 | AC57: 0 | AD57: 0 | AE57: 0 | AF57: 0 | AG57: =+SUM(S57:AF57)-H57 -> 0
A58: 2000 | B58: 2-002543 | C58: CGL25032680 | D58: 45741 | E58: C0002 | F58: NAPS-GUANAJUATO CAM | G58: 336 | H58: 6947.67 | I58: 1111.63 | J58: =SUM(G58:I58) -> 8395.3 | K58: 8395.3 | L58: =+J58-K58 -> 0 | M58: MXN | P58: 0 | Q58: 336 | S58: 2997.67 | T58: 0 | U58: 0 | V58: 0 | W58: 3950 | X58: 0 | Y58: 0 | Z58: 0 | AA58: 0 | AB58: 0 | AC58: 0 | AD58: 0 | AE58: 0 | AF58: 0 | AG58: =+SUM(S58:AF58)-H58 -> 0
A59: 2000 | B59: 2-002544 | C59: CGL25032681 | D59: 45741 | E59: C0002 | F59: NAPS-GUANAJUATO CAM | G59: 336 | H59: 6947.67 | I59: 1111.63 | J59: =SUM(G59:I59) -> 8395.3 | K59: 8395.3 | L59: =+J59-K59 -> 0 | M59: MXN | P59: 0 | Q59: 336 | S59: 2997.67 | T59: 0 | U59: 0 | V59: 0 | W59: 3950 | X59: 0 | Y59: 0 | Z59: 0 | AA59: 0 | AB59: 0 | AC59: 0 | AD59: 0 | AE59: 0 | AF59: 0 | AG59: =+SUM(S59:AF59)-H59 -> 0
A60: 2000 | B60: 2-002545 | C60: CGL25032699 | D60: 45741 | E60: C0002 | F60: NAPS-GUANAJUATO CAM | G60: 3717 | H60: 3996.9 | I60: 639.5 | J60: =SUM(G60:I60) -> 8353.4 | K60: 8353.4 | L60: =+J60-K60 -> 0 | M60: MXN | P60: 0 | Q60: 3717 | S60: 3996.9 | T60: 0 | U60: 0 | V60: 0 | W60: 0 | X60: 0 | Y60: 0 | Z60: 0 | AA60: 0 | AB60: 0 | AC60: 0 | AD60: 0 | AE60: 0 | AF60: 0 | AG60: =+SUM(S60:AF60)-H60 -> 0
A61: 1000 | B61: 1-002546 | C61: CGL25012517 | D61: 45741 | E61: C0002 | F61: NAPS-GUANAJUATO CAM | G61: 35100 | H61: 47558.44 | I61: 7609.35 | J61: =SUM(G61:I61) -> 90267.79 | K61: 88527.79 | L61: =+J61-K61 -> 1740 | M61: MXN | P61: 0 | Q61: 35100 | S61: 4058.44 | T61: 1500 | U61: 16000 | V61: 0 | W61: 26000 | X61: 0 | Y61: 0 | Z61: 0 | AA61: 0 | AB61: 0 | AC61: 0 | AD61: 0 | AE61: 0 | AF61: 0 | AG61: =+SUM(S61:AF61)-H61 -> 0
A62: 2000 | B62: 2-002549 | C62: CGL25022621 | D62: 45741 | E62: C0081 | F62: JOINT PRODUCTION BLACK SMITH | G62: 0 | H62: 22000 | I62: 3520 | J62: =SUM(G62:I62) -> 25520 | K62: 25520 | L62: =+J62-K62 -> 0 | M62: MXN | P62: 0 | Q62: 0 | S62: 0 | T62: 0 | U62: 0 | V62: 0 | W62: 22000 | X62: 0 | Y62: 0 | Z62: 0 | AA62: 0 | AB62: 0 | AC62: 0 | AD62: 0 | AE62: 0 | AF62: 0 | AG62: =+SUM(S62:AF62)-H62 -> 0
A63: 2000 | B63: 2-002550 | C63: CGL25032646 | D63: 45741 | E63: C0081 | F63: JOINT PRODUCTION BLACK SMITH | G63: 0 | H63: 25200 | I63: 4032 | J63: =SUM(G63:I63) -> 29232 | K63: 29232 | L63: =+J63-K63 -> 0 | M63: MXN | P63: 0 | Q63: 0 | S63: 0 | T63: 0 | U63: 0 | V63: 0 | W63: 25200 | X63: 0 | Y63: 0 | Z63: 0 | AA63: 0 | AB63: 0 | AC63: 0 | AD63: 0 | AE63: 0 | AF63: 0 | AG63: =+SUM(S63:AF63)-H63 -> 0
A64: 1000 | B64: 1-002551 | C64: CGL25032676 | D64: 45741 | E64: C0005 | F64: HAHN AUTOMATION GROUP MEXICO | G64: 8451 | H64: 18450 | I64: 2952 | J64: =SUM(G64:I64) -> 29853 | K64: 29853 | L64: =+J64-K64 -> 0 | M64: MXN | P64: 0 | Q64: 8451 | S64: 4450 | T64: 608.92 | U64: 5891.08 | V64: 0 | W64: 7500 | X64: 0 | Y64: 0 | Z64: 0 | AA64: 0 | AB64: 0 | AC64: 0 | AD64: 0 | AE64: 0 | AF64: 0 | AG64: =+SUM(S64:AF64)-H64 -> 0
A65: 1000 | B65: 1-002552 | C65: CGL25022579 | D65: 45741 | E65: C0001 | F65: ARMOR MEXICO IMAGING SUPPLIES | G65: 0 | H65: 97364.79 | I65: 15578.37 | J65: =SUM(G65:I65) -> 112943.16 | K65: 0 | L65: =+J65-K65 -> 112943.16 | M65: MXN | P65: 0 | Q65: 0 | S65: =6111.99+3000 -> 9111.99 | T65: 0 | U65: 25750 | V65: 6127.8 | W65: 46875 | X65: 0 | Y65: 3000 | Z65: 0 | AA65: 0 | AB65: 0 | AC65: 6500 | AD65: 0 | AE65: 0 | AF65: 0 | AG65: =+SUM(S65:AF65)-H65 -> 0
A66: 1000 | B66: 1-002553 | C66: CGL25032710 | D66: 45742 | E66: C0001 | F66: ARMOR MEXICO IMAGING SUPPLIES | G66: 0 | H66: 10967.64 | I66: 1754.83 | J66: =SUM(G66:I66) -> 12722.47 | K66: 0 | L66: =+J66-K66 -> 12722.47 | M66: MXN | P66: 0 | Q66: 0 | S66: 3973.86 | T66: 1500 | U66: 1990.74 | V66: 1003.04 | W66: 2500 | X66: 0 | Y66: 0 | Z66: 0 | AA66: 0 | AB66: 0 | AC66: 0 | AD66: 0 | AE66: 0 | AF66: 0 | AG66: =+SUM(S66:AF66)-H66 -> 0
A67: 2000 | B67: 2-002554 | C67: CGL25022618 | D67: 45742 | E67: C0002 | F67: NAPS-GUANAJUATO CAM | G67: 782 | H67: 4070.24 | I67: 651.24 | J67: =SUM(G67:I67) -> 5503.48 | K67: 5503.48 | L67: =+J67-K67 -> 0 | M67: MXN | P67: 0 | Q67: 782 | S67: 3070.24 | T67: 0 | U67: 0 | V67: 0 | W67: 0 | X67: 0 | Y67: 0 | Z67: 0 | AA67: 0 | AB67: 0 | AC67: 0 | AD67: 1000 | AE67: 0 | AF67: 0 | AG67: =+SUM(S67:AF67)-H67 -> 0
A68: 1000 | B68: 1-002555 | C68: CGL25032654 | D68: 45743 | E68: C0001 | F68: ARMOR MEXICO IMAGING SUPPLIES | G68: 0 | H68: 107388.35 | I68: 17182.14 | J68: =SUM(G68:I68) -> 124570.49 | K68: 0 | L68: =+J68-K68 -> 124570.49 | M68: MXN | P68: 0 | Q68: 0 | S68: 6083.31 | T68: 0 | U68: 29072.04 | V68: 2898 | W68: 69335 | X68: 0 | Y68: 0 | Z68: 0 | AA68: 0 | AB68: 0 | AC68: 0 | AD68: 0 | AE68: 0 | AF68: 0 | AG68: =+SUM(S68:AF68)-H68 -> 0
A69: 1000 | B69: 1-002556 | C69: CGL25032732 | D69: 45743 | E69: C0001 | F69: ARMOR MEXICO IMAGING SUPPLIES | G69: 0 | H69: 3540 | I69: 566.4 | J69: =SUM(G69:I69) -> 4106.4 | K69: 0 | L69: =+J69-K69 -> 4106.4 | M69: MXN | P69: 0 | Q69: 0 | S69: 0 | T69: 0 | U69: 0 | V69: 0 | W69: 0 | X69: 0 | Y69: 0 | Z69: 0 | AA69: 3540 | AB69: 0 | AC69: 0 | AD69: 0 | AE69: 0 | AF69: 0 | AG69: =+SUM(S69:AF69)-H69 -> 0
A70: 1000 | B70: 1-002557 | C70: CGL25032733 | D70: 45743 | E70: C0001 | F70: ARMOR MEXICO IMAGING SUPPLIES | G70: 0 | H70: 3540 | I70: 566.4 | J70: =SUM(G70:I70) -> 4106.4 | K70: 0 | L70: =+J70-K70 -> 4106.4 | M70: MXN | P70: 0 | Q70: 0 | S70: 0 | T70: 0 | U70: 0 | V70: 0 | W70: 0 | X70: 0 | Y70: 0 | Z70: 0 | AA70: 3540 | AB70: 0 | AC70: 0 | AD70: 0 | AE70: 0 | AF70: 0 | AG70: =+SUM(S70:AF70)-H70 -> 0
A71: 2000 | B71: 2-002558 | C71: CGL25032657 | D71: 45743 | E71: C0002 | F71: NAPS-GUANAJUATO CAM | G71: 8283 | H71: 11976.9 | I71: 1916.3 | J71: =SUM(G71:I71) -> 22176.2 | K71: 17507.2 | L71: =+J71-K71 -> 4669 | M71: MXN | P71: 0 | Q71: 8283 | S71: 4026.9 | T71: 0 | U71: 2500 | V71: 0 | W71: 3950 | X71: 0 | Y71: 1500 | Z71: 0 | AA71: 0 | AB71: 0 | AC71: 0 | AD71: 0 | AE71: 0 | AF71: 0 | AG71: =+SUM(S71:AF71)-H71 -> 0
A72: 2000 | B72: 2-002559 | C72: CGL25032698 | D72: 45743 | E72: C0002 | F72: NAPS-GUANAJUATO CAM | G72: 781 | H72: 7961.06 | I72: 1273.77 | J72: =SUM(G72:I72) -> 10015.83 | K72: 10015.83 | L72: =+J72-K72 -> 0 | M72: MXN | P72: 0 | Q72: 781 | S72: 4011.06 | T72: 0 | U72: 0 | V72: 0 | W72: 3950 | X72: 0 | Y72: 0 | Z72: 0 | AA72: 0 | AB72: 0 | AC72: 0 | AD72: 0 | AE72: 0 | AF72: 0 | AG72: =+SUM(S72:AF72)-H72 -> 0
A73: 2000 | B73: 2-002560 | C73: CGL25032700 | D73: 45743 | E73: C0002 | F73: NAPS-GUANAJUATO CAM | G73: 14988 | H73: 11976.9 | I73: 1916.3 | J73: =SUM(G73:I73) -> 28881.2 | K73: 24241.2 | L73: =+J73-K73 -> 4640 | M73: MXN | P73: 0 | Q73: 14988 | S73: 4026.9 | T73: 0 | U73: 2500 | V73: 0 | W73: 3950 | X73: 0 | Y73: 1500 | Z73: 0 | AA73: 0 | AB73: 0 | AC73: 0 | AD73: 0 | AE73: 0 | AF73: 0 | AG73: =+SUM(S73:AF73)-H73 -> 0
A74: 1000 | B74: 1-002561 | C74: CGL25032673 | D74: 45743 | E74: C0075 | F74: JOINT PRODUCTION (HCMF) | G74: 5434 | H74: 13718.71 | I74: 2195 | J74: =SUM(G74:I74) -> 21347.71 | K74: 21185.28 | L74: =+J74-K74 -> 162.43 | M74: MXN | P74: 0 | Q74: 5434 | S74: 7369.99 | T74: 0 | U74: 4008.72 | V74: 0 | W74: 2340 | X74: 0 | Y74: 0 | Z74: 0 | AA74: 0 | AB74: 0 | AC74: 0 | AD74: 0 | AE74: 0 | AF74: 0 | AG74: =+SUM(S74:AF74)-H74 -> 0
A75: 2000 | B75: 2-002562 | C75: CGL25032691 | D75: 45743 | E75: C0081 | F75: JOINT PRODUCTION BLACK SMITH | G75: 0 | H75: 22000 | I75: 3520 | J75: =SUM(G75:I75) -> 25520 | K75: 25520 | L75: =+J75-K75 -> 0 | M75: MXN | P75: 0 | Q75: 0 | S75: 0 | T75: 0 | U75: 0 | V75: 0 | W75: 22000 | X75: 0 | Y75: 0 | Z75: 0 | AA75: 0 | AB75: 0 | AC75: 0 | AD75: 0 | AE75: 0 | AF75: 0 | AG75: =+SUM(S75:AF75)-H75 -> 0
A76: 2000 | B76: 2-002563 | C76: CGL25032695 | D76: 45743 | E76: C0081 | F76: JOINT PRODUCTION BLACK SMITH | G76: 0 | H76: 24940 | I76: 3990.4 | J76: =SUM(G76:I76) -> 28930.4 | K76: 28930.4 | L76: =+J76-K76 -> 0 | M76: MXN | P76: 0 | Q76: 0 | S76: 0 | T76: 0 | U76: 0 | V76: 0 | W76: 22000 | X76: 0 | Y76: 0 | Z76: 0 | AA76: 0 | AB76: 2940 | AC76: 0 | AD76: 0 | AE76: 0 | AF76: 0 | AG76: =+SUM(S76:AF76)-H76 -> 0
A77: 2000 | B77: 2-002564 | C77: CGL25022620 | D77: 45743 | E77: C0002 | F77: NAPS-GUANAJUATO CAM | G77: 3662 | H77: 49500 | I77: 7920 | J77: =SUM(G77:I77) -> 61082 | K77: 58866.33 | L77: =+J77-K77 -> 2215.67 | M77: MXN | P77: 0 | Q77: 3662 | S77: 6000 | T77: 1500 | U77: 16000 | V77: 0 | W77: 26000 | X77: 0 | Y77: 0 | Z77: 0 | AA77: 0 | AB77: 0 | AC77: 0 | AD77: 0 | AE77: 0 | AF77: 0 | AG77: =+SUM(S77:AF77)-H77 -> 0
... A80: 1000 | B80: 1-002571 | C80: CGL25032721 | D80: 45747 | E80: C0012 | F80: MEGALUMINIO SERVICIOS | G80: 5220 | H80: 19500 | I80: 3120 | J80: =SUM(G80:I80) -> 27840 | K80: 28401 | L80: =+J80-K80 -> -561 | M80: MXN | P80: 0 | Q80: 5220 | S80: 6500 | T80: 1500 | U80: 9300 | V80: 0 | W80: 2200 | X80: 0 | Y80: 0 | Z80: 0 | AA80: 0 | AB80: 0 | AC80: 0 | AD80: 0 | AE80: 0 | AF80: 0 | AG80: =+SUM(S80:AF80)-H80 -> 0
A81: 1000 | B81: 1-002573 | C81: CGL25032677 | D81: 45747 | E81: C0002 | F81: NAPS-GUANAJUATO CAM | G81: =336+295 -> 631 | H81: 11800 | I81: 1888 | J81: =SUM(G81:I81) -> 14319 | K81: 10544 | L81: =+J81-K81 -> 3775 | M81: MXN | P81: 0 | Q81: =295+336 -> 631 | S81: 6300 | T81: 0 | U81: 2500 | V81: 0 | W81: 0 | X81: 0 | Y81: 0 | Z81: 0 | AA81: 0 | AB81: 3000 | AC81: 0 | AD81: 0 | AE81: 0 | AF81: 0 | AG81: =+SUM(S81:AF81)-H81 -> 0
A82: 1000 | B82: 1-002568 | C82: CGL25022608 | D82: 45747 | E82: C0004 | F82: NAPS-GUANAJUATO AMERICAN BOA | G82: 5644.5 | H82: 1597.5 | I82: 255.6 | J82: =SUM(G82:I82) -> 7497.6 | K82: 7497.6 | L82: =+J82-K82 -> 0 | M82: MXN | P82: 0 | Q82: 5644.5 | S82: 0 | T82: 0 | U82: 0 | V82: 0 | W82: 0 | X82: 0 | Y82: 0 | Z82: 0 | AA82: 0 | AB82: 0 | AC82: 0 | AD82: 0 | AE82: 1597.5 | AF82: 0 | AG82: =+SUM(S82:AF82)-H82 -> 0
A83: 1000 | B83: 1-002569 | C83: CGL25022608 | D83: 45747 | E83: C0004 | F83: NAPS-GUANAJUATO AMERICAN BOA | G83: 781 | H83: 110783.16 | I83: 17725.31 | J83: =SUM(G83:I83) -> 129289.47 | K83: 129698.24 | L83: =+J83-K83 -> -408.77 | M83: MXN | P83: 0 | Q83: 781 | S83: 7481.16 | T83: 0 | U83: 43302 | V83: 0 | W83: 60000 | X83: 0 | Y83: 0 | Z83: 0 | AA83: 0 | AB83: 0 | AC83: 0 | AD83: 0 | AE83: 0 | AF83: 0 | AG83: =+SUM(S83:AF83)-H83 -> 0
A84: 1000 | B84: 1-002574 | C84: CGL25022629 | D84: 45747 | E84: C0004 | F84: NAPS-GUANAJUATO AMERICAN BOA | G84: 781 | H84: 29420 | I84: 4707.2 | J84: =SUM(G84:I84) -> 34908.2 | K84: 34908.2 | L84: =+J84-K84 -> 0 | M84: MXN | P84: 0 | Q84: 781 | S84: 6390 | T84: 0 | U84: 23030 | V84: 0 | W84: 0 | X84: 0 | Y84: 0 | Z84: 0 | AA84: 0 | AB84: 0 | AC84: 0 | AD84: 0 | AE84: 0 | AF84: 0 | AG84: =+SUM(S84:AF84)-H84 -> 0
A85: 1000 | B85: 1-002575 | C85: CGL25012535 | D85: 45747 | E85: C0004 | F85: NAPS-GUANAJUATO AMERICAN BOA | G85: 0 | H85: 1585.61 | I85: 253.7 | J85: =SUM(G85:I85) -> 1839.31 | K85: 1839.31 | L85: =+J85-K85 -> 0 | M85: MXN | P85: 0 | Q85: 0 | S85: 0 | T85: 0 | U85: 0 | V85: 1585.61 | W85: 0 | X85: 0 | Y85: 0 | Z85: 0 | AA85: 0 | AB85: 0 | AC85: 0 | AD85: 0 | AE85: 0 | AF85: 0 | AG85: =+SUM(S85:AF85)-H85 -> 0
A86: 1000 | B86: 1-002576 | C86: CGL25032669 | D86: 45747 | E86: C0004 | F86: NAPS-GUANAJUATO AMERICAN BOA | G86: 402830 | H86: 44681.77 | I86: 7149.09 | J86: =SUM(G86:I86) -> 454660.86 | K86: 459915.38 | L86: =+J86-K86 -> -5254.52 | M86: MXN | P86: 0 | Q86: 402830 | S86: 7035.86 | T86: 0 | U86: 37645.91 | V86: 0 | W86: 0 | X86: 0 | Y86: 0 | Z86: 0 | AA86: 0 | AB86: 0 | AC86: 0 | AD86: 0 | AE86: 0 | AF86: 0 | AG86: =+SUM(S86:AF86)-H86 -> 0
A87: 1000 | B87: 1-002577 | C87: CGL25032672 | D87: 45747 | E87: C0004 | F87: NAPS-GUANAJUATO AMERICAN BOA | G87: 436465 | H87: 45270.42 | I87: 7243.27 | J87: =SUM(G87:I87) -> 488978.69 | K87: 481064.54 | L87: =+J87-K87 -> 7914.15 | M87: MXN | P87: 0 | Q87: 436465 | S87: 7624.51 | T87: 0 | U87: 37645.91 | V87: 0 | W87: 0 | X87: 0 | Y87: 0 | Z87: 0 | AA87: 0 | AB87: 0 | AC87: 0 | AD87: 0 | AE87: 0 | AF87: 0 | AG87: =+SUM(S87:AF87)-H87 -> 0
A88: 1000 | B88: 1-002578 | C88: CGL25022607 | D88: 45747 | E88: C0004 | F88: NAPS-GUANAJUATO AMERICAN BOA | G88: 5644.5 | H88: 94014.5 | I88: 15042.32 | J88: =SUM(G88:I88) -> 114701.32 | K88: 117960.32 | L88: =+J88-K88 -> -3259 | M88: MXN | P88: 0 | Q88: 5644.5 | S88: 6810 | T88: 0 | U88: 28000 | V88: 907 | W88: 56700 | X88: 0 | Y88: 0 | Z88: 0 | AA88: 0 | AB88: 0 | AC88: 0 | AD88: 0 | AE88: 1597.5 | AF88: 0 | AG88: =+SUM(S88:AF88)-H88 -> 0
A89: 2000 | B89: 2-002579 | C89: CGL25032707 | D89: 45747 | E89: C0002 | F89: NAPS-GUANAJUATO CAM | G89: 9735 | H89: 7965.24 | I89: 1274.44 | J89: =SUM(G89:I89) -> 18974.68 | K89: 18974.68 | L89: =+J89-K89 -> 0 | M89: MXN | P89: 0 | Q89: 9735 | S89: 4015.24 | T89: 0 | U89: 0 | V89: 0 | W89: 3950 | X89: 0 | Y89: 0 | Z89: 0 | AA89: 0 | AB89: 0 | AC89: 0 | AD89: 0 | AE89: 0 | AF89: 0 | AG89: =+SUM(S89:AF89)-H89 -> 0
A90: 2000 | B90: 2-002580 | C90: CGL25032702 | D90: 45747 | E90: C0002 | F90: NAPS-GUANAJUATO CAM | G90: 336 | H90: 13928.89 | I90: 2228.62 | J90: =SUM(G90:I90) -> 16493.51 | K90: 16493.51 | L90: =+J90-K90 -> 0 | M90: MXN | P90: 0 | Q90: 336 | S90: 6028.89 | T90: 0 | U90: 0 | V90: 0 | W90: 7900 | X90: 0 | Y90: 0 | Z90: 0 | AA90: 0 | AB90: 0 | AC90: 0 | AD90: 0 | AE90: 0 | AF90: 0 | AG90: =+SUM(S90:AF90)-H90 -> 0
A91: 2000 | B91: 2-002581 | C91: CGL25032701 | D91: 45747 | E91: C0002 | F91: NAPS-GUANAJUATO CAM | G91: 336 | H91: 6964.45 | I91: 1114.31 | J91: =SUM(G91:I91) -> 8414.76 | K91: 8414.76 | L91: =+J91-K91 -> 0 | M91: MXN | P91: 0 | Q91: 336 | S91: 3014.45 | T91: 0 | U91: 0 | V91: 0 | W91: 3950 | X91: 0 | Y91: 0 | Z91: 0 | AA91: 0 | AB91: 0 | AC91: 0 | AD91: 0 | AE91: 0 | AF91: 0 | AG91: =+SUM(S91:AF91)-H91 -> 0
A92: 2000 | B92: 2-002582 | C92: CGL25012445 | D92: 45747 | E92: C0002 | F92: NAPS-GUANAJUATO CAM | G92: 291009 | H92: 28084.76 | I92: 4493.56 | J92: =SUM(G92:I92) -> 323587.32 | K92: 323587.32 | L92: =+J92-K92 -> 0 | M92: MXN | P92: 0 | Q92: 291009 | S92: 4022.46 | T92: 0 | U92: 0 | V92: 0 | W92: 3950 | X92: 20112.3 | Y92: 0 | Z92: 0 | AA92: 0 | AB92: 0 | AC92: 0 | AD92: 0 | AE92: 0 | AF92: 0 | AG92: =+SUM(S92:AF92)-H92 -> 0
A93: 1000 | B93: 1-002583 | C93: CGL25022580 | D93: 45747 | E93: C0004 | F93: NAPS-GUANAJUATO AMERICAN BOA | G93: 781 | H93: 103002.37 | I93: 16480.38 | J93: =SUM(G93:I93) -> 120263.75 | K93: 120263.75 | L93: =+J93-K93 -> 0 | M93: MXN | P93: 0 | Q93: 781 | S93: 24942.37 | T93: 0 | U93: 25000 | V93: 0 | W93: 53060 | X93: 0 | Y93: 0 | Z93: 0 | AA93: 0 | AB93: 0 | AC93: 0 | AD93: 0 | AE93: 0 | AF93: 0 | AG93: =+SUM(S93:AF93)-H93 -> 0
... A96: 2000 | B96: 2-002586 | C96: CGL25032715 | D96: 45747 | E96: C0084 | F96: JOINT PRODUCTION TECTRAN | G96: 0 | H96: 21000 | I96: 3360 | J96: =SUM(G96:I96) -> 24360 | K96: 0 | L96: =+J96-K96 -> 24360 | M96: MXN | P96: 0 | Q96: 0 | S96: 0 | T96: 0 | U96: 0 | V96: 0 | W96: 21000 | X96: 0 | Y96: 0 | Z96: 0 | AA96: 0 | AB96: 0 | AC96: 0 | AD96: 0 | AE96: 0 | AF96: 0 | AG96: =+SUM(S96:AF96)-H96 -> 0
J97: =SUM(G97:I97) -> 0 | L97: =+J97-K97 -> 0
J98: =SUM(G98:I98) -> 0 | L98: =+J98-K98 -> 0
J99: =SUM(G99:I99) -> 0 | L99: =+J99-K99 -> 0 | M99: MXN | AG99: =+SUM(S99:AF99)-H99 -> 0
G100: =+SUM(G2:G99) -> 1529424 | H100: =+SUM(H2:H99) -> 2418159.8 | I100: =+SUM(I2:I99) -> 379040.57 | J100: =+SUM(J2:J99) -> 4326624.3 | K100: =+SUM(K2:K99) -> 3752286.1 | L100: =+SUM(L2:L99) -> 574338.21 | P100: =+SUM(P2:P99) -> 0 | Q100: =+SUM(Q2:Q99) -> 1529424 | S100: =+SUM(S2:S99) -> 396873.24 | T100: =+SUM(T2:T99) -> 17053.96 | U100: =+SUM(U2:U99) -> 558468.45 | V100: =+SUM(V2:V99) -> 16647.13 | W100: =+SUM(W2:W99) -> 1298164 | X100: =+SUM(X2:X99) -> 38443.89 | Y100: =+SUM(Y2:Y99) -> 12000 | Z100: =+SUM(Z2:Z99) -> 7200 | ... AG100: =+SUM(AG2:AG99) -> 0
K102: 3752282.1
K103: =+K100-K102 -> 4
H104: BASE 16% | I104: BASE 0% | J104: IVA 16% | K104: T O T A L
B105: TOTAL FACTURACION | D105: =+H107+I107 -> 3047553.1 | G105: TOTAL MXN | H105: =+H100-I105 -> 2369003.2 | I105: =+H52 -> 49156.6 | J105: =+H105*0.16 -> 379040.51 | K105: =+SUM(H105:J105) -> 2797200.3
A106: ( vs ) | B106: TOTAL SAT | D106: =2418159.77+'MAR USD '!N19 -> 3047553.1 | G106: TOTAL USD | H106: =+'MAR USD '!N22 -> 9422.8395 | I106: =+'MAR USD '!N23 -> 619970.51 | J106: =+H106*0.16 -> 1507.6543 | K106: =+SUM(H106:J106) -> 630901.01
A107: ( = ) | B107: DIFERENCIA | D107: =+D105-D106 -> 0 | H107: =+SUM(H105:H106) -> 2378426 | I107: =+SUM(I105:I106) -> 669127.11 | J107: =+SUM(J105:J106) -> 380548.16 | K107: =+SUM(K105:K106) -> 3428101.3
G109: TOTAL FACTURADOS | H109: =+H107+I107 -> 3047553.1

Sheet MAR USD 
G1: INFORMACION EN USD | N1: INFORMACION EN MXN
A2: SERIE | B2: FACTURA | C2: TRAFICO | D2: FECHA | E2: CLIENTE | F2: CLIENTENOMBRE | G2: COMPROBADOS | H2: COMPLEMENTARIOS | I2: IVA | J2: SUBTOTAL | K2: ANTICIPO | L2: TOTAL | M2: TIPOCAMBIO | N2: COMPLEMENTARIOS | O2: IVA | P2: SUBTOTAL | Q2: ANTICIPO | R2: TOTAL | U2: SERVICIO LOGISTICO | V2: REVALIDACION GUIA | W2: MANIOBRAS | X2: ALMACENAJES | Y2: GASTOS EN DESTINO | Z2: CUOTA | AB2: SERVICIO LOGISTICO | AC2: REVALIDACION GUIA | AD2: MANIOBRAS | AE2: ALMACENAJES | AF2: GASTOS EN DESTINO | AG2: CUOTA
A3: 1000 | B3: 1-002481 | C3: CGL25012472 | D3: 45720 | E3: C0086 | F3: GOMSA INTEGRADORA | G3: 0 | H3: 99 | I3: 0 | J3: =SUM(G3:I3) -> 99 | K3: 99 | L3: =J3-K3 -> 0 | M3: 20.4333 | N3: =H3*M3 -> 2022.8967 | O3: =I3*M3 -> 0 | P3: =J3*M3 -> 2022.8967 | Q3: =M3*K3 -> 2022.8967 | R3: =L3*M3 -> 0 | U3: 0 | V3: 99 | W3: 0 | X3: 0 | Y3: 0 | Z3: 0 | AB3: =U3*M3 -> 0 | AC3: =+V3*M3 -> 2022.8967 | AD3: =+M3*W3 -> 0 | AE3: =+X3*M3 -> 0 | AF3: =+Y3*M3 -> 0 | AG3: =+Z3*M3 -> 0
A4: 1000 | B4: 1-002482 | C4: CGL25012472 | D4: 45720 | E4: C0086 | F4: GOMSA INTEGRADORA | G4: 0 | H4: 220 | I4: 35.2 | J4: =SUM(G4:I4) -> 255.2 | K4: 255.2 | L4: =J4-K4 -> 0 | M4: 20.4333 | N4: =H4*M4 -> 4495.326 | O4: =I4*M4 -> 719.25216 | P4: =J4*M4 -> 5214.5782 | Q4: =M4*K4 -> 5214.5782 | R4: =L4*M4 -> 0 | U4: 0 | V4: 0 | W4: 0 | X4: 0 | Y4: 220 | Z4: 0 | AB4: =U4*M4 -> 0 | AC4: =+V4*M4 -> 0 | AD4: =+M4*W4 -> 0 | AE4: =+X4*M4 -> 0 | AF4: =+Y4*M4 -> 4495.326 | AG4: =+Z4*M4 -> 0
A5: 1000 | B5: 1-002489 | C5: CGL25022564 | D5: 45723 | E5: C0001 | F5: ARMOR MEXICO IMAGING SUPPLIES | G5: 0 | H5: 4270.15 | I5: 0 | J5: =SUM(G5:I5) -> 4270.15 | K5: 0 | L5: =J5-K5 -> 4270.15 | M5: 20.3893 | N5: =H5*M5 -> 87065.369 | O5: =I5*M5 -> 0 | P5: =J5*M5 -> 87065.369 | Q5: =M5*K5 -> 0 | R5: =L5*M5 -> 87065.369 | U5: 2840.5 | V5: 0 | W5: 0 | X5: 0 | Y5: 1429.65 | Z5: 0 | AB5: =U5*M5 -> 57915.807 | AC5: =+V5*M5 -> 0 | AD5: =+M5*W5 -> 0 | AE5: =+X5*M5 -> 0 | AF5: =+Y5*M5 -> 29149.563 | AG5: =+Z5*M5 -> 0
A6: 2000 | B6: 2-002499 | C6: CGL25032644 | D6: 45730 | E6: C0084 | F6: JOINT PRODUCTION TECTRAN | G6: 0 | H6: 6125 | I6: 0 | J6: =SUM(G6:I6) -> 6125 | K6: 0 | L6: =J6-K6 -> 6125 | M6: 20.0848 | N6: =H6*M6 -> 123019.4 | O6: =I6*M6 -> 0 | P6: =J6*M6 -> 123019.4 | Q6: =M6*K6 -> 0 | R6: =L6*M6 -> 123019.4 | U6: 6125 | V6: 0 | W6: 0 | X6: 0 | Y6: 0 | Z6: 0 | AB6: =U6*M6 -> 123019.4 | AC6: =+V6*M6 -> 0 | AD6: =+M6*W6 -> 0 | AE6: =+X6*M6 -> 0 | AF6: =+Y6*M6 -> 0 | AG6: =+Z6*M6 -> 0
A7: 1000 | B7: 1-002506 | C7: CGL25012472 | D7: 45735 | E7: C0085 | F7: HM ULUSLARARASI PROJE TASIMACILIGI A.S | G7: 0 | H7: 75 | I7: 0 | J7: =SUM(G7:I7) -> 75 | K7: 0 | L7: =J7-K7 -> 75 | M7: 19.9845 | N7: =H7*M7 -> 1498.8375 | O7: =I7*M7 -> 0 | P7: =J7*M7 -> 1498.8375 | Q7: =M7*K7 -> 0 | R7: =L7*M7 -> 1498.8375 | U7: 0 | V7: 75 | W7: 0 | X7: 0 | Y7: 0 | Z7: 0 | AB7: =U7*M7 -> 0 | AC7: =+V7*M7 -> 1498.8375 | AD7: =+M7*W7 -> 0 | AE7: =+X7*M7 -> 0 | AF7: =+Y7*M7 -> 0 | AG7: =+Z7*M7 -> 0
A8: 1000 | B8: 1-002516 | C8: CGL25022582 | D8: 45736 | E8: C0089 | F8: CHEMICAL COLOR DE MEXICO | G8: 0 | H8: =3750+360 -> 4110 | I8: 0 | J8: =SUM(G8:I8) -> 4110 | K8: 4110 | L8: =J8-K8 -> 0 | M8: 20.0553 | N8: =H8*M8 -> 82427.283 | O8: =I8*M8 -> 0 | P8: =J8*M8 -> 82427.283 | Q8: =M8*K8 -> 82427.283 | R8: =L8*M8 -> 0 | U8: 3750 | V8: 0 | W8: 0 | X8: 0 | Y8: 360 | Z8: 0 | AB8: =U8*M8 -> 75207.375 | AC8: =+V8*M8 -> 0 | AD8: =+M8*W8 -> 0 | AE8: =+X8*M8 -> 0 | AF8: =+Y8*M8 -> 7219.908 | AG8: =+Z8*M8 -> 0
A9: 2000 | B9: 2-002522 | C9: CGL25022613 | D9: 45737 | E9: C0001 | F9: ARMOR MEXICO IMAGING SUPPLIES | G9: 0 | H9: 1200 | I9: 0 | J9: =SUM(G9:I9) -> 1200 | K9: 0 | L9: =J9-K9 -> 1200 | M9: 20.0553 | N9: =H9*M9 -> 24066.36 | O9: =I9*M9 -> 0 | P9: =J9*M9 -> 24066.36 | Q9: =M9*K9 -> 0 | R9: =L9*M9 -> 24066.36 | U9: 1200 | V9: 0 | W9: 0 | X9: 0 | Y9: 0 | Z9: 0 | AB9: =U9*M9 -> 24066.36 | AC9: =+V9*M9 -> 0 | AD9: =+M9*W9 -> 0 | AE9: =+X9*M9 -> 0 | AF9: =+Y9*M9 -> 0 | AG9: =+Z9*M9 -> 0
A10: 1000 | B10: 1-002547 | C10: CGL25022568 | D10: 45741 | E10: C0086 | F10: GOMSA INTEGRADORA | G10: 0 | H10: 125 | I10: 0 | J10: =SUM(G10:I10) -> 125 | K10: 125 | L10: =J10-K10 -> 0 | M10: 20.1123 | N10: =H10*M10 -> 2514.0375 | O10: =I10*M10 -> 0 | P10: =J10*M10 -> 2514.0375 | Q10: =M10*K10 -> 2514.0375 | R10: =L10*M10 -> 0 | U10: 0 | V10: 0 | W10: 0 | X10: 0 | Y10: 125 | Z10: 0 | AB10: =U10*M10 -> 0 | AC10: =+V10*M10 -> 0 | AD10: =+M10*W10 -> 0 | AE10: =+X10*M10 -> 0 | AF10: =+Y10*M10 -> 2514.0375 | AG10: =+Z10*M10 -> 0
A11: 1000 | B11: 1-002548 | C11: CGL25022568 | D11: 45741 | E11: C0086 | F11: GOMSA INTEGRADORA | G11: 0 | H11: 245 | I11: 39.2 | J11: =SUM(G11:I11) -> 284.2 | K11: 284.2 | L11: =J11-K11 -> 0 | M11: 20.1123 | N11: =H11*M11 -> 4927.5135 | O11: =I11*M11 -> 788.40216 | P11: =J11*M11 -> 5715.9157 | Q11: =M11*K11 -> 5715.9157 | R11: =L11*M11 -> 0 | U11: 0 | V11: 0 | W11: 0 | X11: 0 | Y11: 245 | Z11: 0 | AB11: =U11*M11 -> 0 | AC11: =+V11*M11 -> 0 | AD11: =+M11*W11 -> 0 | AE11: =+X11*M11 -> 0 | AF11: =+Y11*M11 -> 4927.5135 | AG11: =+Z11*M11 -> 0
A12: 1000 | B12: 1-002566 | C12: CGL25022568 | D12: 45744 | E12: C0085 | F12: HM ULUSLARARASI PROJE TASIMACILIGI A.S | G12: 0 | H12: 75 | I12: 0 | J12: =SUM(G12:I12) -> 75 | K12: 0 | L12: =J12-K12 -> 75 | M12: 20.3182 | N12: =H12*M12 -> 1523.865 | O12: =I12*M12 -> 0 | P12: =J12*M12 -> 1523.865 | Q12: =M12*K12 -> 0 | R12: =L12*M12 -> 1523.865 | U12: 0 | V12: 75 | W12: 0 | X12: 0 | Y12: 0 | Z12: 0 | AB12: =U12*M12 -> 0 | AC12: =+V12*M12 -> 1523.865 | AD12: =+M12*W12 -> 0 | AE12: =+X12*M12 -> 0 | AF12: =+Y12*M12 -> 0 | AG12: =+Z12*M12 -> 0
A13: 1000 | B13: 1-002565 | C13: CGL25012499 | D13: 45744 | E13: C0085 | F13: HM ULUSLARARASI PROJE TASIMACILIGI A.S | G13: 0 | H13: 75 | I13: 0 | J13: =SUM(G13:I13) -> 75 | K13: 0 | L13: =J13-K13 -> 75 | M13: 20.3182 | N13: =H13*M13 -> 1523.865 | O13: =I13*M13 -> 0 | P13: =J13*M13 -> 1523.865 | Q13: =M13*K13 -> 0 | R13: =L13*M13 -> 1523.865 | U13: 0 | V13: 0 | W13: 0 | X13: 0 | Y13: 75 | Z13: 0 | AB13: =U13*M13 -> 0 | AC13: =+V13*M13 -> 0 | AD13: =+M13*W13 -> 0 | AE13: =+X13*M13 -> 0 | AF13: =+Y13*M13 -> 1523.865 | AG13: =+Z13*M13 -> 0
A14: 2000 | B14: 2-002572 | C14: CGL25032694 | D14: 45747 | E14: C0084 | F14: JOINT PRODUCTION | G14: 0 | H14: 6000 | I14: 0 | J14: =SUM(G14:I14) -> 6000 | K14: 0 | L14: =J14-K14 -> 6000 | M14: 20.4003 | N14: =H14*M14 -> 122401.8 | O14: =I14*M14 -> 0 | P14: =J14*M14 -> 122401.8 | Q14: =M14*K14 -> 0 | R14: =L14*M14 -> 122401.8 | U14: 6000 | V14: 0 | W14: 0 | X14: 0 | Y14: 0 | Z14: 0 | AB14: =U14*M14 -> 122401.8 | AC14: =+V14*M14 -> 0 | AD14: =+M14*W14 -> 0 | AE14: =+X14*M14 -> 0 | AF14: =+Y14*M14 -> 0 | AG14: =+Z14*M14 -> 0
A15: 1000 | B15: 1-002587 | C15: CGL25012469 | D15: 45747 | E15: C0090 | F15: INVICONT OÜ | G15: 843.32 | H15: =700+7140+586.68 -> 8426.68 | I15: 0 | J15: =SUM(G15:I15) -> 9270 | K15: 9270 | L15: =J15-K15 -> 0 | M15: 20.4003 | N15: =H15*M15 -> 171906.8 | O15: =I15*M15 -> 0 | P15: =J15*M15 -> 189110.78 | Q15: =M15*K15 -> 189110.78 | R15: =L15*M15 -> 0 | U15: 0 | V15: 0 | W15: 700 | X15: =7140+586.68 -> 7726.68 | Y15: 0 | Z15: 0 | AB15: =U15*M15 -> 0 | AC15: =+V15*M15 -> 0 | AD15: =+M15*W15 -> 14280.21 | AE15: =+X15*M15 -> 157626.59 | AF15: =+Y15*M15 -> 0 | AG15: =+Z15*M15 -> 0
J16: =SUM(G16:I16) -> 0 | L16: =J16-K16 -> 0 | N16: =H16*M16 -> 0 | O16: =I16*M16 -> 0 | P16: =J16*M16 -> 0 | Q16: =M16*K16 -> 0 | R16: =L16*M16 -> 0 | U16: 0 | V16: 0 | W16: 0 | X16: 0 | Y16: 0 | Z16: 0 | AB16: =U16*M16 -> 0 | AC16: =+V16*M16 -> 0 | AD16: =+M16*W16 -> 0 | AE16: =+X16*M16 -> 0 | AF16: =+Y16*M16 -> 0 | AG16: =+Z16*M16 -> 0
J17: =SUM(G17:I17) -> 0 | L17: =J17-K17 -> 0 | N17: =H17*M17 -> 0 | O17: =I17*M17 -> 0 | P17: =J17*M17 -> 0 | Q17: =M17*K17 -> 0 | R17: =L17*M17 -> 0 | U17: 0 | V17: 0 | W17: 0 | X17: 0 | Y17: 0 | Z17: 0 | AB17: =U17*M17 -> 0 | AC17: =+V17*M17 -> 0 | AD17: =+M17*W17 -> 0 | AE17: =+X17*M17 -> 0 | AF17: =+Y17*M17 -> 0 | AG17: =+Z17*M17 -> 0
J18: =SUM(G18:I18) -> 0 | L18: =J18-K18 -> 0 | N18: =H18*M18 -> 0 | O18: =I18*M18 -> 0 | P18: =J18*M18 -> 0 | Q18: =M18*K18 -> 0 | R18: =L18*M18 -> 0 | U18: 0 | V18: 0 | W18: 0 | X18: 0 | Y18: 0 | Z18: 0 | AB18: =U18*M18 -> 0 | AC18: =+V18*M18 -> 0 | AD18: =+M18*W18 -> 0 | AE18: =+X18*M18 -> 0 | AF18: =+Y18*M18 -> 0 | AG18: =+Z18*M18 -> 0
G19: =+SUM(G3:G18) -> 843.32 | H19: =+SUM(H3:H18) -> 31045.83 | I19: =+SUM(I3:I18) -> 74.4 | J19: =+SUM(J3:J18) -> 31963.55 | K19: =+SUM(K3:K18) -> 14143.4 | L19: =+SUM(L3:L18) -> 17820.15 | N19: =+SUM(N3:N18) -> 629393.35 | O19: =+SUM(O3:O18) -> 1507.6543 | P19: =+SUM(P3:P18) -> 648104.99 | Q19: =+SUM(Q3:Q18) -> 287005.49 | R19: =+SUM(R3:R18) -> 361099.5 | U19: =+SUM(U3:U18) -> 19915.5 | V19: =+SUM(V3:V18) -> 249 | W19: =+SUM(W3:W18) -> 700 | X19: =+SUM(X3:X18) -> 7726.68 | Y19: =+SUM(Y3:Y18) -> 2454.65 | Z19: =+SUM(Z3:Z18) -> 0 | AB19: =+SUM(AB3:AB18) -> 402610.74 | AC19: =+SUM(AC3:AC18) -> 5045.5992 | AD19: =+SUM(AD3:AD18) -> 14280.21 | AE19: =+SUM(AE3:AE18) -> 157626.59 | AF19: =+SUM(AF3:AF18) -> 49830.213 | AG19: =+SUM(AG3:AG18) -> 0
Z20: =+SUM(T19:Z19) -> 31045.83 | AG20: =+SUM(AB19:AG19) -> 629393.35
H21: 31045.83 | Z21: =+Z20-H19 -> 0 | AG21: =+AG20-N19 -> 0
M22: 16 | N22: =+N4+N11 -> 9422.8395
M23: 0 | N23: =+N3+N5+N6+N7+N8+N9+N10+N12+N13+N14+N15 -> 619970.51
N25: =+N22+N23 -> 629393.35

Sheet ABR MXN 
A1: SERIE | B1: FACTURA | C1: TRAFICO | D1: FECHA | E1: CLIENTE | F1: CLIENTE NOMBRE | G1: COMPROBADOS | H1: COMPLEMENTARIOS | I1: IVA | J1: SUBTOTAL | K1: ANTICIPO | L1: TOTAL | M1: MONEDA | P1: DOCUMENTACION, ALMACENAJES Y MANIOBRAS ( TER) | Q1: IMPUESTOS ADUANALES (TER) | S1: HONORARIOS | T1: REVALIDACION GUIA / BOL | U1: MANIOBRAS | V1: ALMACENAJES | W1: SERVICIOS LOGISTICOS | X1: ACONDICIONAMIENTO DE EMBALAJE | Y1: RECONOCIMIENTO ADUANERO | Z1: CONSOLIDACION DE ETRADAS | AA1: CERTIFICADO DE ORIGEN | AB1: SERVICIOS EXTRAORDINARIO | AC1: RECTIFICACIONES | AG1: MXN | AH1: USD | AI1: TOTAL | AJ1: PORCENTAJE
A2: 1 | B2: 1-002588 | C2: CGL25022564 | D2: 45751 | E2: C0001 | F2: ARMOR MEXICO IMAGING SUPPLIES | G2: 0 | H2: 97127.13 | I2: 15540.34 | J2: =SUM(G2:I2) -> 112667.47 | K2: 0 | L2: =+J2-K2 -> 112667.47 | M2: MXN | P2: 0 | Q2: 0 | S2: 6120.09 | T2: 0 | U2: 29072.04 | V2: 0 | W2: 61935 | X2: 0 | Y2: 0 | Z2: 0 | AA2: 0 | AB2: 0 | AC2: 0 | AD2: =+SUM(S2:AC2)-H2 -> 0 | AF2: HONORARIOS | AG2: =+S76 -> 375773.69 | AH2: =+'ABR USD '!AE19 -> 7442.984 | AI2: =SUM(AG2:AH2) -> 383216.67 | AJ2: =+AI2/AI17 -> 0.18710574
A3: 2 | B3: 2-002589 | C3: CGL25022587 | D3: 45751 | E3: C0002 | F3: NAPS-GUANAJUATO CAM | G3: 8736 | H3: 8013.64 | I3: 1282.18 | J3: =SUM(G3:I3) -> 18031.82 | K3: 18031.82 | L3: =+J3-K3 -> 0 | M3: MXN | P3: 0 | Q3: 8736 | S3: 4063.64 | T3: 0 | U3: 0 | V3: 0 | W3: 3950 | X3: 0 | Y3: 0 | Z3: 0 | AA3: 0 | AB3: 0 | AC3: 0 | AD3: =+SUM(S3:AC3)-H3 -> 0 | AF3: REVALIDACION GUIA / BOL | AG3: =+T76 -> 12696.88 | AH3: =+'ABR USD '!AC19 -> 4308.15 | AI3: =SUM(AG3:AH3) -> 17005.03 | AJ3: =+AI3/AI17 -> 0.0083027146
A4: 2 | B4: 2-002590 | C4: CGL25032724 | D4: 45751 | E4: C0002 | F4: NAPS-GUANAJUATO CAM | G4: 8412 | H4: 7986.91 | I4: 1277.91 | J4: =SUM(G4:I4) -> 17676.82 | K4: 17676.82 | L4: =+J4-K4 -> 0 | M4: MXN | P4: 0 | Q4: 8412 | S4: 4036.91 | T4: 0 | U4: 0 | V4: 0 | W4: 3950 | X4: 0 | Y4: 0 | Z4: 0 | AA4: 0 | AB4: 0 | AC4: 0 | AD4: =+SUM(S4:AC4)-H4 -> 0 | AF4: MANIOBRAS | AG4: =+U76 -> 453529 | AH4: =+'ABR USD '!AD19 -> 19586.8 | AI4: =SUM(AG4:AH4) -> 473115.8 | AJ4: =+AI4/AI17 -> 0.23099903
A5: 1 | B5: 1-002591 | C5: CGL25032731 | D5: 45751 | E5: C0002 | F5: NAPS-GUANAJUATO CAM | G5: 336 | H5: 11500 | I5: 1840 | J5: =SUM(G5:I5) -> 13676 | K5: 13676 | L5: =+J5-K5 -> 0 | M5: MXN | P5: 0 | Q5: 336 | S5: 6000 | T5: 0 | U5: 2500 | V5: 0 | W5: 0 | X5: 0 | Y5: 0 | Z5: 0 | AA5: 0 | AB5: 3000 | AC5: 0 | AD5: =+SUM(S5:AC5)-H5 -> 0 | AF5: ALMACENAJES | AG5: =+V76 -> 24105.19 | AH5: 0 | AI5: =SUM(AG5:AH5) -> 24105.19 | AJ5: =+AI5/AI17 -> 0.011769371
A6: 2 | B6: 2-002592 | C6: CGL25032655 | D6: 45754 | E6: C0002 | F6: NAPS-GUANAJUATO CAM | G6: 92698 | H6: 4087.6 | I6: 654.02 | J6: =SUM(G6:I6) -> 97439.62 | K6: 97800.62 | L6: =+J6-K6 -> -361 | M6: MXN | P6: 0 | Q6: 92698 | S6: 4087.6 | T6: 0 | U6: 0 | V6: 0 | W6: 0 | X6: 0 | Y6: 0 | Z6: 0 | AA6: 0 | AB6: 0 | AC6: 0 | AD6: =+SUM(S6:AC6)-H6 -> 0 | AF6: SERVICIOS LOGISTICOS | AG6: =+W76 -> 729288.79 | AH6: =+'ABR USD '!AB19 -> 342354.39 | AI6: =SUM(AG6:AH6) -> 1071643.2 | AJ6: =+AI6/AI17 -> 0.52323033
A7: 1 | B7: 1-002593 | C7: CGL25032717 | D7: 45754 | E7: C0002 | F7: NAPS-GUANAJUATO CAM | G7: 336 | H7: 17500 | I7: 2800 | J7: =SUM(G7:I7) -> 20636 | K7: 20636 | L7: =+J7-K7 -> 0 | M7: MXN | P7: 0 | Q7: 336 | S7: 12000 | T7: 0 | U7: 2500 | V7: 0 | W7: 0 | X7: 0 | Y7: 0 | Z7: 0 | AA7: 0 | AB7: 3000 | AC7: 0 | AD7: =+SUM(S7:AC7)-H7 -> 0 | AF7: ACONDICIONAMIENTO DE EMBALAJE | AG7: =+X76 -> 1050 | AH7: 0 | AI7: =SUM(AG7:AH7) -> 1050 | AJ7: =+AI7/AI17 -> 0.00051266304
A8: 2 | B8: 2-002594 | C8: CGL25022630 | D8: 45756 | E8: C0069 | F8: JOINT PRODUCTION HONOR | G8: 428 | H8: 1200 | I8: 192 | J8: =SUM(G8:I8) -> 1820 | K8: 1820 | L8: =+J8-K8 -> 0 | M8: MXN | P8: 0 | Q8: 428 | S8: 1200 | T8: 0 | U8: 0 | V8: 0 | W8: 0 | X8: 0 | Y8: 0 | Z8: 0 | AA8: 0 | AB8: 0 | AC8: 0 | AD8: =+SUM(S8:AC8)-H8 -> 0 | AF8: RECONOCIMIENTO ADUANERO | AG8: =+Y76 -> 5110.76 | AH8: 0 | AI8: =SUM(AG8:AH8) -> 5110.76 | AJ8: =+AI8/AI17 -> 0.0024953312
A9: 2 | B9: 2-002595 | C9: CGL25022630 | D9: 45756 | E9: C0069 | F9: JOINT PRODUCTION HONOR | G9: =336+336 -> 672 | H9: 15356 | I9: 2456.96 | J9: =SUM(G9:I9) -> 18484.96 | K9: 19265.96 | L9: =+J9-K9 -> -781 | M9: MXN | P9: 0 | Q9: =336+336 -> 672 | S9: =7678+7678 -> 15356 | T9: 0 | U9: 0 | V9: 0 | W9: 0 | X9: 0 | Y9: 0 | Z9: 0 | AA9: 0 | AB9: 0 | AC9: 0 | AD9: =+SUM(S9:AC9)-H9 -> 0 | AF9: CONSOLIDACION DE ETRADAS | AG9: =+Z76 -> 21916.49 | AH9: 0 | AI9: =SUM(AG9:AH9) -> 21916.49 | AJ9: =+AI9/AI17 -> 0.010700737
A10: 2 | B10: 2-002596 | C10: CGL25032738 | D10: 45756 | E10: C0001 | F10: ARMOR MEXICO IMAGING SUPPLIES | G10: 0 | H10: 12779.53 | I10: 2044.73 | J10: =SUM(G10:I10) -> 14824.26 | K10: 0 | L10: =+J10-K10 -> 14824.26 | M10: MXN | P10: 0 | Q10: 0 | S10: 4700.74 | T10: 0 | U10: 0 | V10: 0 | W10: 8078.79 | X10: 0 | Y10: 0 | Z10: 0 | AA10: 0 | AB10: 0 | AC10: 0 | AD10: =+SUM(S10:AC10)-H10 -> 0 | AF10: CERTIFICADO DE ORIGEN | AG10: =+AA76 -> 7080 | AH10: 0 | AI10: =SUM(AG10:AH10) -> 7080 | AJ10: =+AI10/AI17 -> 0.0034568136
A11: 1 | B11: 1-002597 | C11: CGL25032713 | D11: 45756 | E11: C0006 | F11: CLEVELAND DIE QUERETARO | G11: 2757 | H11: 22200.24 | I11: 3552.04 | J11: =SUM(G11:I11) -> 28509.28 | K11: 33102.6 | L11: =+J11-K11 -> -4593.32 | M11: MXN | P11: 0 | Q11: 2757 | S11: 6500 | T11: 554.67 | U11: 4513.21 | V11: 8132.36 | W11: 2500 | X11: 0 | Y11: 0 | Z11: 0 | AA11: 0 | AB11: 0 | AC11: 0 | AD11: =+SUM(S11:AC11)-H11 -> 0 | AF11: SERVICIOS EXTRAORDINARIO | AG11: =+AB76 -> 8800 | AH11: 0 | AI11: =SUM(AG11:AH11) -> 8800 | AJ11: =+AI11/AI17 -> 0.0042966045
A12: 1 | B12: 1-002598 | C12: CGL25032712 | D12: 45756 | E12: C0006 | F12: CLEVELAND DIE QUERETARO | G12: 7387 | H12: 16046.75 | I12: 2567.48 | J12: =SUM(G12:I12) -> 26001.23 | K12: 37732.6 | L12: =+J12-K12 -> -11731.37 | M12: MXN | P12: 0 | Q12: 7387 | S12: 6500 | T12: 867.62 | U12: 3778.18 | V12: 2400.95 | W12: 2500 | X12: 0 | Y12: 0 | Z12: 0 | AA12: 0 | AB12: 0 | AC12: 0 | AD12: =+SUM(S12:AC12)-H12 -> 0 | AF12: RECTIFICACIONES | AG12: =+AC76 -> 1400 | AH12: 0 | AI12: =SUM(AG12:AH12) -> 1400 | AJ12: =+AI12/AI17 -> 0.00068355072
A13: 2 | B13: 2-002599 | C13: CGL25032688 | D13: 45756 | E13: C0069 | F13: JOINT PRODUCTION HONOR | G13: =336+336 -> 672 | H13: 15247.22 | I13: 2439.56 | J13: =SUM(G13:I13) -> 18358.78 | K13: 19586.78 | L13: =+J13-K13 -> -1228 | M13: MXN | P13: 0 | Q13: =336+336 -> 672 | S13: =7685+7562.22 -> 15247.22 | T13: 0 | U13: 0 | V13: 0 | W13: 0 | X13: 0 | Y13: 0 | Z13: 0 | AA13: 0 | AB13: 0 | AC13: 0 | AD13: =+SUM(S13:AC13)-H13 -> 0 | AF13: GASTOS EN ORIGEN | AG13: 0 | AH13: =+'ABR USD '!AF19 -> 30670.101 | AI13: =SUM(AG13:AH13) -> 30670.101 | AJ13: =+AI13/AI17 -> 0.014974693
A14: 1 | B14: 1-002601 | C14: CGL25032742 | D14: 45756 | E14: C0001 | F14: ARMOR MEXICO IMAGING SUPPLIES | G14: 0 | H14: 11255.82 | I14: 1800.94 | J14: =SUM(G14:I14) -> 13056.76 | K14: 0 | L14: =+J14-K14 -> 13056.76 | M14: MXN | P14: 0 | Q14: 0 | S14: 4087.6 | T14: 1500 | U14: 1990.74 | V14: 1177.48 | W14: 2500 | X14: 0 | Y14: 0 | Z14: 0 | AA14: 0 | AB14: 0 | AC14: 0 | AD14: =+SUM(S14:AC14)-H14 -> 0 | AF14: GASTOS EN DESTINO | AG14: 0 | AH14: =+'ABR USD '!AG19 -> 3015.705 | AI14: =SUM(AG14:AH14) -> 3015.705 | AJ14: =+AI14/AI17 -> 0.0014724195
A15: 2 | B15: 2-002602 | C15: CGL25032722 | D15: 45757 | E15: C0002 | F15: NAPS-GUANAJUATO CAM | G15: 336 | H15: 18007.61 | I15: 2881.22 | J15: =SUM(G15:I15) -> 21224.83 | K15: 21224.83 | L15: =+J15-K15 -> 0 | M15: MXN | P15: 0 | Q15: 336 | S15: 6107.61 | T15: 0 | U15: 2500 | V15: 0 | W15: 7900 | X15: 0 | Y15: 1500 | Z15: 0 | AA15: 0 | AB15: 0 | AC15: 0 | AD15: =+SUM(S15:AC15)-H15 -> 0 | AI15: =SUM(AG15:AH15) -> 0 | AJ15: =+AI15/AI17 -> 0
A16: 2 | B16: 2-002603 | C16: CGL25032723 | D16: 45757 | E16: C0002 | F16: NAPS-GUANAJUATO CAM | G16: 336 | H16: 18007.61 | I16: 2881.22 | J16: =SUM(G16:I16) -> 21224.83 | K16: 21224.83 | L16: =+J16-K16 -> 0 | M16: MXN | P16: 0 | Q16: 336 | S16: 6107.61 | T16: 0 | U16: 2500 | V16: 0 | W16: 7900 | X16: 0 | Y16: 1500 | Z16: 0 | AA16: 0 | AB16: 0 | AC16: 0 | AD16: =+SUM(S16:AC16)-H16 -> 0
A17: 1 | B17: 1-002604 | C17: CGL25032714 | D17: 45757 | E17: C0001 | F17: ARMOR MEXICO IMAGING SUPPLIES | G17: 0 | H17: 74345.46 | I17: 11895.27 | J17: =SUM(G17:I17) -> 86240.73 | K17: 0 | L17: =+J17-K17 -> 86240.73 | M17: MXN | P17: 0 | Q17: 0 | S17: 6095.46 | T17: 0 | U17: 25750 | V17: 0 | W17: 42000 | X17: 500 | Y17: 0 | Z17: 0 | AA17: 0 | AB17: 0 | AC17: 0 | AD17: =+SUM(S17:AC17)-H17 -> 0 | AG17: =+SUM(AG2:AG16) -> 1640750.8 | AH17: =+SUM(AH2:AH16) -> 407378.13 | AI17: =+SUM(AI2:AI16) -> 2048128.9 | AJ17: =+SUM(AJ2:AJ16) -> 1
A18: 2 | B18: 2-002605 | C18: CGL25042748 | D18: 45757 | E18: C0081 | F18: JOINT PRODUCTION BLACK SMITH | G18: 0 | H18: 22000 | I18: 3520 | J18: =SUM(G18:I18) -> 25520 | K18: 25520 | L18: =+J18-K18 -> 0 | M18: MXN | P18: 0 | Q18: 0 | S18: 0 | T18: 0 | U18: 0 | V18: 0 | W18: 22000 | X18: 0 | Y18: 0 | Z18: 0 | AA18: 0 | AB18: 0 | AC18: 0 | AD18: =+SUM(S18:AC18)-H18 -> 0
A19: 1 | B19: 1-002606 | C19: CGL25022592 | D19: 45758 | E19: C0002 | F19: NAPS-GUANAJUATO CAM | G19: 19746 | H19: 49500 | I19: 7920 | J19: =SUM(G19:I19) -> 77166 | K19: 89834 | L19: =+J19-K19 -> -12668 | M19: MXN | P19: 0 | Q19: 19746 | S19: 6000 | T19: 1500 | U19: 16000 | V19: 0 | W19: 26000 | X19: 0 | Y19: 0 | Z19: 0 | AA19: 0 | AB19: 0 | AC19: 0 | AD19: =+SUM(S19:AC19)-H19 -> 0 | AI19: 2048128.9
A20: 2 | B20: 2-002607 | C20: CGL25022576 | D20: 45758 | E20: C0002 | F20: NAPS-GUANAJUATO CAM | G20: 31644 | H20: 15784.7 | I20: 2525.55 | J20: =SUM(G20:I20) -> 49954.25 | K20: 49954.25 | L20: =+J20-K20 -> 0 | M20: MXN | P20: 0 | Q20: 31644 | S20: 4354.4 | T20: 0 | U20: 0 | V20: 0 | W20: 0 | X20: 0 | Y20: 0 | Z20: 11430.3 | AA20: 0 | AB20: 0 | AC20: 0 | AD20: =+SUM(S20:AC20)-H20 -> 0
A21: 2 | B21: 2-002608 | C21: CGL25042771 | D21: 45758 | E21: C0002 | F21: NAPS-GUANAJUATO CAM | G21: 1081 | H21: 8304.4 | I21: 1328.7 | J21: =SUM(G21:I21) -> 10714.1 | K21: 10714.1 | L21: =+J21-K21 -> 0 | M21: MXN | P21: 0 | Q21: 1081 | S21: 4354.4 | T21: 0 | U21: 0 | V21: 0 | W21: 3950 | X21: 0 | Y21: 0 | Z21: 0 | AA21: 0 | AB21: 0 | AC21: 0 | AD21: =+SUM(S21:AC21)-H21 -> 0 | AI21: =+AI17-AI19 -> 0.0033199999
A22: 2 | B22: 2-002609 | C22: CGL25022612 | D22: 45762 | E22: C0069 | F22: JOINT PRODUCTION HONOR | G22: 428 | H22: 1200 | I22: 192 | J22: =SUM(G22:I22) -> 1820 | K22: 1820 | L22: =+J22-K22 -> 0 | M22: MXN | P22: 0 | Q22: 428 | S22: 1200 | T22: 0 | U22: 0 | V22: 0 | W22: 0 | X22: 0 | Y22: 0 | Z22: 0 | AA22: 0 | AB22: 0 | AC22: 0 | AD22: =+SUM(S22:AC22)-H22 -> 0
A23: 2 | B23: 2-002610 | C23: CGL25042769 | D23: 45762 | E23: C0081 | F23: JOINT PRODUCTION BLACK SMITH | G23: 0 | H23: 22000 | I23: 3520 | J23: =SUM(G23:I23) -> 25520 | K23: 25520 | L23: =+J23-K23 -> 0 | M23: MXN | P23: 0 | Q23: 0 | S23: 0 | T23: 0 | U23: 0 | V23: 0 | W23: 22000 | X23: 0 | Y23: 0 | Z23: 0 | AA23: 0 | AB23: 0 | AC23: 0 | AD23: =+SUM(S23:AC23)-H23 -> 0
A24: 1 | B24: 1-002611 | C24: CGL25032737 | D24: 45762 | E24: C0001 | F24: ARMOR MEXICO IMAGING SUPPLIES | G24: 0 | H24: 13800.4 | I24: 2208.07 | J24: =SUM(G24:I24) -> 16008.47 | K24: 0 | L24: =+J24-K24 -> 16008.47 | M24: MXN | P24: 0 | Q24: 0 | S24: 8274.68 | T24: 0 | U24: 2475.72 | V24: 0 | W24: 2500 | X24: 550 | Y24: 0 | Z24: 0 | AA24: 0 | AB24: 0 | AC24: 0 | AD24: =+SUM(S24:AC24)-H24 -> 0
A25: 1 | B25: 1-002612 | C25: CGL25032716 | D25: 45762 | E25: C0001 | F25: ARMOR MEXICO IMAGING SUPPLIES | G25: 0 | H25: 104527.13 | I25: 16724.34 | J25: =SUM(G25:I25) -> 121251.47 | K25: 0 | L25: =+J25-K25 -> 121251.47 | M25: MXN | P25: 0 | Q25: 0 | S25: 6120.09 | T25: 0 | U25: 29072.04 | V25: 0 | W25: 69335 | X25: 0 | Y25: 0 | Z25: 0 | AA25: 0 | AB25: 0 | AC25: 0 | AD25: =+SUM(S25:AC25)-H25 -> 0
A26: 2 | B26: 2-002613 | C26: CGL25032734 | D26: 45762 | E26: C0002 | F26: NAPS-GUANAJUATO CAM | G26: 336 | H26: 4100.2 | I26: 656.03 | J26: =SUM(G26:I26) -> 5092.23 | K26: 5092.23 | L26: =+J26-K26 -> 0 | M26: MXN | P26: 0 | Q26: 336 | S26: 4100.2 | T26: 0 | U26: 0 | V26: 0 | W26: 0 | X26: 0 | Y26: 0 | Z26: 0 | AA26: 0 | AB26: 0 | AC26: 0 | AD26: =+SUM(S26:AC26)-H26 -> 0
A27: 1 | B27: 1-002614 | C27: CGL25032740 | D27: 45762 | E27: C0002 | F27: NAPS-GUANAJUATO CAM | G27: 336 | H27: 17000 | I27: 2720 | J27: =SUM(G27:I27) -> 20056 | K27: 20056 | L27: =+J27-K27 -> 0 | M27: MXN | P27: 0 | Q27: 336 | S27: 12000 | T27: 0 | U27: 5000 | V27: 0 | W27: 0 | X27: 0 | Y27: 0 | Z27: 0 | AA27: 0 | AB27: 0 | AC27: 0 | AD27: =+SUM(S27:AC27)-H27 -> 0
A28: 2 | B28: 2-002615 | C28: CGL25042744 | D28: 45762 | E28: C0002 | F28: NAPS-GUANAJUATO CAM | G28: 336 | H28: 14106.01 | I28: 2256.96 | J28: =SUM(G28:I28) -> 16698.97 | K28: 16698.97 | L28: =+J28-K28 -> 0 | M28: MXN | P28: 0 | Q28: 336 | S28: 6206.01 | T28: 0 | U28: 0 | V28: 0 | W28: 7900 | X28: 0 | Y28: 0 | Z28: 0 | AA28: 0 | AB28: 0 | AC28: 0 | AD28: =+SUM(S28:AC28)-H28 -> 0
A29: 2 | B29: 2-002616 | C29: CGL25042745 | D29: 45762 | E29: C0002 | F29: NAPS-GUANAJUATO CAM | G29: 336 | H29: 7053.01 | I29: 1128.48 | J29: =SUM(G29:I29) -> 8517.49 | K29: 8517.49 | L29: =+J29-K29 -> 0 | M29: MXN | P29: 0 | Q29: 336 | S29: 3103.01 | T29: 0 | U29: 0 | V29: 0 | W29: 3950 | X29: 0 | Y29: 0 | Z29: 0 | AA29: 0 | AB29: 0 | AC29: 0 | AD29: =+SUM(S29:AC29)-H29 -> 0
A30: 2 | B30: 2-002617 | C30: CGL25042750 | D30: 45763 | E30: C0001 | F30: ARMOR MEXICO IMAGING SUPPLIES | G30: 0 | H30: 22950.06 | I30: 3672.01 | J30: =SUM(G30:I30) -> 26622.07 | K30: 0 | L30: =+J30-K30 -> 26622.07 | M30: MXN | P30: 0 | Q30: 0 | S30: 4200.06 | T30: 0 | U30: 0 | V30: 0 | W30: 18750 | X30: 0 | Y30: 0 | Z30: 0 | AA30: 0 | AB30: 0 | AC30: 0 | AD30: =+SUM(S30:AC30)-H30 -> 0
A31: 2 | B31: 2-002618 | C31: CGL25042751 | D31: 45763 | E31: C0001 | F31: ARMOR MEXICO IMAGING SUPPLIES | G31: 0 | H31: 22950.06 | I31: 3672.01 | J31: =SUM(G31:I31) -> 26622.07 | K31: 0 | L31: =+J31-K31 -> 26622.07 | M31: MXN | P31: 0 | Q31: 0 | S31: 4200.06 | T31: 0 | U31: 0 | V31: 0 | W31: 18750 | X31: 0 | Y31: 0 | Z31: 0 | AA31: 0 | AB31: 0 | AC31: 0 | AD31: =+SUM(S31:AC31)-H31 -> 0
A32: 1 | B32: 1-002620 | C32: CGL25032697 | D32: 45763 | E32: C0004 | F32: NAPS-GUANAJUATO AMERICAN BOA | G32: 442529 | H32: 42230.6 | I32: 6756.9 | J32: =SUM(G32:I32) -> 491516.5 | K32: 498044.34 | L32: =+J32-K32 -> -6527.84 | M32: MXN | P32: 0 | Q32: 442529 | S32: 7730.6 | T32: 0 | U32: 34500 | V32: 0 | W32: 0 | X32: 0 | Y32: 0 | Z32: 0 | AA32: 0 | AB32: 0 | AC32: 0 | AD32: =+SUM(S32:AC32)-H32 -> 0
A33: 2 | B33: 2-002621 | C33: CGL25042779 | D33: 45764 | E33: C0081 | F33: JOINT PRODUCTION BLACK SMITH | G33: 0 | H33: 24110.76 | I33: 3857.72 | J33: =SUM(G33:I33) -> 27968.48 | K33: 27968.48 | L33: =+J33-K33 -> 0 | M33: MXN | P33: 0 | Q33: 0 | S33: 0 | T33: 0 | U33: 0 | V33: 0 | W33: 22000 | X33: 0 | Y33: 2110.76 | Z33: 0 | AA33: 0 | AB33: 0 | AC33: 0 | AD33: =+SUM(S33:AC33)-H33 -> 0
... A74: 1 | B74: 1-002665 | C74: CGL25032705 | D74: 45777 | E74: C0004 | F74: NAPS-GUANAJUATO AMERICAN BOA | G74: 781 | H74: 34491.24 | I74: 5518.6 | J74: =SUM(G74:I74) -> 40790.84 | K74: 41253.4 | L74: =+J74-K74 -> -462.56 | M74: MXN | P74: 0 | Q74: 781 | S74: 5991.24 | T74: 0 | U74: 20000 | V74: 0 | W74: 8500 | X74: 0 | Y74: 0 | Z74: 0 | AA74: 0 | AB74: 0 | AC74: 0 | AD74: =+SUM(S74:AC74)-H74 -> 0
J75: =SUM(G75:I75) -> 0 | L75: =+J75-K75 -> 0 | M75: MXN | AD75: =+SUM(S75:AC75)-H75 -> 0
G76: =+SUM(G2:G75) -> 2633921 | H76: =+SUM(H2:H75) -> 1640750.8 | I76: =+SUM(I2:I75) -> 262520.12 | J76: =+SUM(J2:J75) -> 4537191.9 | K76: =+SUM(K2:K75) -> 3993284.9 | L76: =+SUM(L2:L75) -> 543907.04 | P76: =+SUM(P2:P75) -> 295 | Q76: =+SUM(Q2:Q75) -> 2633626 | S76: =+SUM(S2:S75) -> 375773.69 | T76: =+SUM(T2:T75) -> 12696.88 | U76: =+SUM(U2:U75) -> 453529 | V76: =+SUM(V2:V75) -> 24105.19 | W76: =+SUM(W2:W75) -> 729288.79 | X76: =+SUM(X2:X75) -> 1050 | Y76: =+SUM(Y2:Y75) -> 5110.76 | Z76: =+SUM(Z2:Z75) -> 21916.49 | ... AD76: =+SUM(AD2:AD75) -> 0
Q78: =+G76-P76-Q76 -> 0
H80: BASE 16% | I80: BASE 0% | J80: IVA 16% | K80: T O T A L
B81: TOTAL FACTURACION | D81: =+H76+'ABR USD '!N19 -> 2048128.9 | G81: TOTAL MXN | H81: =+H76-I81 -> 1640750.8 | I81: 0 | J81: =+H81*0.16 -> 262520.13 | K81: =+SUM(H81:J81) -> 1903270.9
A82: ( vs ) | B82: TOTAL SAT | D82: =+H85 -> 2048128.9 | G82: TOTAL USD | H82: =+'ABR USD '!N22 -> 93702.305 | I82: =+'ABR USD '!N23 -> 313675.83 | J82: =+H82*0.16 -> 14992.369 | K82: =+SUM(H82:J82) -> 422370.5
A83: ( = ) | B83: DIFERENCIA | D83: =+D81-D82 -> 0 | H83: =+SUM(H81:H82) -> 1734453.1 | I83: =+SUM(I81:I82) -> 313675.83 | J83: =+SUM(J81:J82) -> 277512.5 | K83: =+SUM(K81:K82) -> 2325641.4
G85: TOTAL FACTURADOS | H85: =+H83+I83 -> 2048128.9

Sheet ABR USD 
G1: INFORMACION EN USD | N1: INFORMACION EN MXN
A2: SERIE | B2: FACTURA | C2: TRAFICO | D2: FECHA | E2: CLIENTE | F2: CLIENTENOMBRE | G2: COMPROBADOS | H2: COMPLEMENTARIOS | I2: IVA | J2: SUBTOTAL | K2: ANTICIPO | L2: TOTAL | M2: TIPOCAMBIO | N2: COMPLEMENTARIOS | O2: IVA | P2: SUBTOTAL | Q2: ANTICIPO | R2: TOTAL | U2: SERVICIO LOGISTICO | V2: REVALIDACION GUIA | W2: MANIOBRAS | X2: HONORARIOS | Y2: GASTOS EN ORIGEN | Z2: GASTOS EN DESTINO | AB2: SERVICIO LOGISTICO | AC2: REVALIDACION GUIA | AD2: MANIOBRAS | AE2: HONORARIOS | AF2: GASTOS EN ORIGEN | AG2: GASTOS EN DESTINO
A3: 1 | B3: 1-002600 | C3: CGL25032709 | D3: 45756 | E3: C0001 | F3: ARMOR MEXICO IMAGING SUPPLIES | G3: 0 | H3: =2051+1482.6 -> 3533.6 | I3: 0 | J3: =SUM(G3:I3) -> 3533.6 | K3: 0 | L3: =J3-K3 -> 3533.6 | M3: 20.6867 | N3: =H3*M3 -> 73098.523 | O3: =I3*M3 -> 0 | P3: =J3*M3 -> 73098.523 | Q3: =M3*K3 -> 0 | R3: =L3*M3 -> 73098.523 | U3: 2051 | V3: 0 | W3: 0 | X3: 0 | Y3: 1482.6 | Z3: 0 | AB3: =U3*M3 -> 42428.422 | AC3: =+V3*M3 -> 0 | AD3: =+M3*W3 -> 0 | AE3: =+X3*M3 -> 0 | AF3: =+Y3*M3 -> 30670.101 | AG3: =+Z3*M3 -> 0
A4: 1 | B4: 1-002636 | C4: CGL25032668 | D4: 45772 | E4: C0086 | F4: GOMSA INTEGRADORA | G4: 0 | H4: 220 | I4: 35.2 | J4: =SUM(G4:I4) -> 255.2 | K4: 255.2 | L4: =J4-K4 -> 0 | M4: 19.5825 | N4: =H4*M4 -> 4308.15 | O4: =I4*M4 -> 689.304 | P4: =J4*M4 -> 4997.454 | Q4: =M4*K4 -> 4997.454 | R4: =L4*M4 -> 0 | U4: 0 | V4: 220 | W4: 0 | X4: 0 | Y4: 0 | Z4: 0 | AB4: =U4*M4 -> 0 | AC4: =+V4*M4 -> 4308.15 | AD4: =+M4*W4 -> 0 | AE4: =+X4*M4 -> 0 | AF4: =+Y4*M4 -> 0 | AG4: =+Z4*M4 -> 0
A5: 1 | B5: 1-002637 | C5: CGL25032668 | D5: 45772 | E5: C0086 | F5: GOMSA INTEGRADORA | G5: 0 | H5: 154 | I5: 0 | J5: =SUM(G5:I5) -> 154 | K5: 154 | L5: =J5-K5 -> 0 | M5: 19.5825 | N5: =H5*M5 -> 3015.705 | O5: =I5*M5 -> 0 | P5: =J5*M5 -> 3015.705 | Q5: =M5*K5 -> 3015.705 | R5: =L5*M5 -> 0 | U5: 0 | V5: 0 | W5: 0 | X5: 0 | Y5: 0 | Z5: 154 | AB5: =U5*M5 -> 0 | AC5: =+V5*M5 -> 0 | AD5: =+M5*W5 -> 0 | AE5: =+X5*M5 -> 0 | AF5: =+Y5*M5 -> 0 | AG5: =+Z5*M5 -> 3015.705
A6: 2 | B6: 2-002619 | C6: CGL25042789 | D6: 45763 | E6: C0084 | F6: JOINT PRODUCTION | G6: 0 | H6: 6000 | I6: 0 | J6: =SUM(G6:I6) -> 6000 | K6: 0 | L6: =J6-K6 -> 6000 | M6: 20.0213 | N6: =H6*M6 -> 120127.8 | O6: =I6*M6 -> 0 | P6: =J6*M6 -> 120127.8 | Q6: =M6*K6 -> 0 | R6: =L6*M6 -> 120127.8 | U6: 6000 | V6: 0 | W6: 0 | X6: 0 | Y6: 0 | Z6: 0 | AB6: =U6*M6 -> 120127.8 | AC6: =+V6*M6 -> 0 | AD6: =+M6*W6 -> 0 | AE6: =+X6*M6 -> 0 | AF6: =+Y6*M6 -> 0 | AG6: =+Z6*M6 -> 0
A7: 2 | B7: 2-002653 | C7: CGL25042860 | D7: 45777 | E7: C0084 | F7: JOINT PRODUCTION | G7: 0 | H7: 6000 | I7: 0 | J7: =SUM(G7:I7) -> 6000 | K7: 0 | L7: =J7-K7 -> 6000 | M7: 19.5723 | N7: =H7*M7 -> 117433.8 | O7: =I7*M7 -> 0 | P7: =J7*M7 -> 117433.8 | Q7: =M7*K7 -> 0 | R7: =L7*M7 -> 117433.8 | U7: 6000 | V7: 0 | W7: 0 | X7: 0 | Y7: 0 | Z7: 0 | AB7: =U7*M7 -> 117433.8 | AC7: =+V7*M7 -> 0 | AD7: =+M7*W7 -> 0 | AE7: =+X7*M7 -> 0 | AF7: =+Y7*M7 -> 0 | AG7: =+Z7*M7 -> 0
A8: 1 | B8: 1-002666 | C8: CGL25022582 | D8: 45777 | E8: C0089 | F8: CHEMICAL COLOR DE MEXICO | G8: 0 | H8: =380+1000+3184 -> 4564 | I8: 730.24 | J8: =SUM(G8:I8) -> 5294.24 | K8: 4564 | L8: =J8-K8 -> 730.24 | M8: 19.5868 | N8: =H8*M8 -> 89394.155 | O8: =I8*M8 -> 14303.065 | P8: =J8*M8 -> 103697.22 | Q8: =M8*K8 -> 89394.155 | R8: =L8*M8 -> 14303.065 | U8: 3184 | V8: 0 | W8: 1000 | X8: 380 | Y8: 0 | Z8: 0 | AB8: =U8*M8 -> 62364.371 | AC8: =+V8*M8 -> 0 | AD8: =+M8*W8 -> 19586.8 | AE8: =+X8*M8 -> 7442.984 | AF8: =+Y8*M8 -> 0 | AG8: =+Z8*M8 -> 0
J9: =SUM(G9:I9) -> 0 | L9: =J9-K9 -> 0 | N9: =H9*M9 -> 0 | O9: =I9*M9 -> 0 | P9: =J9*M9 -> 0 | Q9: =M9*K9 -> 0 | R9: =L9*M9 -> 0 | U9: 0 | V9: 0 | W9: 0 | X9: 0 | Y9: 0 | Z9: 0 | AB9: =U9*M9 -> 0 | AC9: =+V9*M9 -> 0 | AD9: =+M9*W9 -> 0 | AE9: =+X9*M9 -> 0 | AF9: =+Y9*M9 -> 0 | AG9: =+Z9*M9 -> 0
J10: =SUM(G10:I10) -> 0 | L10: =J10-K10 -> 0 | N10: =H10*M10 -> 0 | O10: =I10*M10 -> 0 | P10: =J10*M10 -> 0 | Q10: =M10*K10 -> 0 | R10: =L10*M10 -> 0 | U10: 0 | V10: 0 | W10: 0 | X10: 0 | Y10: 0 | Z10: 0 | AB10: =U10*M10 -> 0 | AC10: =+V10*M10 -> 0 | AD10: =+M10*W10 -> 0 | AE10: =+X10*M10 -> 0 | AF10: =+Y10*M10 -> 0 | AG10: =+Z10*M10 -> 0
J11: =SUM(G11:I11) -> 0 | L11: =J11-K11 -> 0 | N11: =H11*M11 -> 0 | O11: =I11*M11 -> 0 | P11: =J11*M11 -> 0 | Q11: =M11*K11 -> 0 | R11: =L11*M11 -> 0 | U11: 0 | V11: 0 | W11: 0 | X11: 0 | Y11: 0 | Z11: 0 | AB11: =U11*M11 -> 0 | AC11: =+V11*M11 -> 0 | AD11: =+M11*W11 -> 0 | AE11: =+X11*M11 -> 0 | AF11: =+Y11*M11 -> 0 | AG11: =+Z11*M11 -> 0
J12: =SUM(G12:I12) -> 0 | L12: =J12-K12 -> 0 | N12: =H12*M12 -> 0 | O12: =I12*M12 -> 0 | P12: =J12*M12 -> 0 | Q12: =M12*K12 -> 0 | R12: =L12*M12 -> 0 | U12: 0 | V12: 0 | W12: 0 | X12: 0 | Y12: 0 | Z12: 0 | AB12: =U12*M12 -> 0 | AC12: =+V12*M12 -> 0 | AD12: =+M12*W12 -> 0 | AE12: =+X12*M12 -> 0 | AF12: =+Y12*M12 -> 0 | AG12: =+Z12*M12 -> 0
J13: =SUM(G13:I13) -> 0 | L13: =J13-K13 -> 0 | N13: =H13*M13 -> 0 | O13: =I13*M13 -> 0 | P13: =J13*M13 -> 0 | Q13: =M13*K13 -> 0 | R13: =L13*M13 -> 0 | U13: 0 | V13: 0 | W13: 0 | X13: 0 | Y13: 0 | Z13: 0 | AB13: =U13*M13 -> 0 | AC13: =+V13*M13 -> 0 | AD13: =+M13*W13 -> 0 | AE13: =+X13*M13 -> 0 | AF13: =+Y13*M13 -> 0 | AG13: =+Z13*M13 -> 0
J14: =SUM(G14:I14) -> 0 | L14: =J14-K14 -> 0 | N14: =H14*M14 -> 0 | O14: =I14*M14 -> 0 | P14: =J14*M14 -> 0 | Q14: =M14*K14 -> 0 | R14: =L14*M14 -> 0 | U14: 0 | V14: 0 | W14: 0 | X14: 0 | Y14: 0 | Z14: 0 | AB14: =U14*M14 -> 0 | AC14: =+V14*M14 -> 0 | AD14: =+M14*W14 -> 0 | AE14: =+X14*M14 -> 0 | AF14: =+Y14*M14 -> 0 | AG14: =+Z14*M14 -> 0
J15: =SUM(G15:I15) -> 0 | L15: =J15-K15 -> 0 | N15: =H15*M15 -> 0 | O15: =I15*M15 -> 0 | P15: =J15*M15 -> 0 | Q15: =M15*K15 -> 0 | R15: =L15*M15 -> 0 | U15: 0 | V15: 0 | W15: 0 | X15: 0 | Y15: 0 | Z15: 0 | AB15: =U15*M15 -> 0 | AC15: =+V15*M15 -> 0 | AD15: =+M15*W15 -> 0 | AE15: =+X15*M15 -> 0 | AF15: =+Y15*M15 -> 0 | AG15: =+Z15*M15 -> 0
J16: =SUM(G16:I16) -> 0 | L16: =J16-K16 -> 0 | N16: =H16*M16 -> 0 | O16: =I16*M16 -> 0 | P16: =J16*M16 -> 0 | Q16: =M16*K16 -> 0 | R16: =L16*M16 -> 0 | U16: 0 | V16: 0 | W16: 0 | X16: 0 | Y16: 0 | Z16: 0 | AB16: =U16*M16 -> 0 | AC16: =+V16*M16 -> 0 | AD16: =+M16*W16 -> 0 | AE16: =+X16*M16 -> 0 | AF16: =+Y16*M16 -> 0 | AG16: =+Z16*M16 -> 0
J17: =SUM(G17:I17) -> 0 | L17: =J17-K17 -> 0 | N17: =H17*M17 -> 0 | O17: =I17*M17 -> 0 | P17: =J17*M17 -> 0 | Q17: =M17*K17 -> 0 | R17: =L17*M17 -> 0 | U17: 0 | V17: 0 | W17: 0 | X17: 0 | Y17: 0 | Z17: 0 | AB17: =U17*M17 -> 0 | AC17: =+V17*M17 -> 0 | AD17: =+M17*W17 -> 0 | AE17: =+X17*M17 -> 0 | AF17: =+Y17*M17 -> 0 | AG17: =+Z17*M17 -> 0
J18: =SUM(G18:I18) -> 0 | L18: =J18-K18 -> 0 | N18: =H18*M18 -> 0 | O18: =I18*M18 -> 0 | P18: =J18*M18 -> 0 | Q18: =M18*K18 -> 0 | R18: =L18*M18 -> 0 | U18: 0 | V18: 0 | W18: 0 | X18: 0 | Y18: 0 | Z18: 0 | AB18: =U18*M18 -> 0 | AC18: =+V18*M18 -> 0 | AD18: =+M18*W18 -> 0 | AE18: =+X18*M18 -> 0 | AF18: =+Y18*M18 -> 0 | AG18: =+Z18*M18 -> 0
G19: =+SUM(G3:G18) -> 0 | H19: =+SUM(H3:H18) -> 20471.6 | I19: =+SUM(I3:I18) -> 765.44 | J19: =+SUM(J3:J18) -> 21237.04 | K19: =+SUM(K3:K18) -> 4973.2 | L19: =+SUM(L3:L18) -> 16263.84 | N19: =+SUM(N3:N18) -> 407378.13 | O19: =+SUM(O3:O18) -> 14992.369 | P19: =+SUM(P3:P18) -> 422370.5 | Q19: =+SUM(Q3:Q18) -> 97407.314 | R19: =+SUM(R3:R18) -> 324963.19 | U19: =+SUM(U3:U18) -> 17235 | V19: =+SUM(V3:V18) -> 220 | W19: =+SUM(W3:W18) -> 1000 | X19: =+SUM(X3:X18) -> 380 | Y19: =+SUM(Y3:Y18) -> 1482.6 | Z19: =+SUM(Z3:Z18) -> 154 | AB19: =+SUM(AB3:AB18) -> 342354.39 | AC19: =+SUM(AC3:AC18) -> 4308.15 | AD19: =+SUM(AD3:AD18) -> 19586.8 | AE19: =+SUM(AE3:AE18) -> 7442.984 | AF19: =+SUM(AF3:AF18) -> 30670.101 | AG19: =+SUM(AG3:AG18) -> 3015.705
Z20: =+SUM(T19:Z19) -> 20471.6 | AG20: =+SUM(AB19:AG19) -> 407378.13
H21: 20471.6 | Z21: =+Z20-H19 -> 0 | AG21: =+AG20-N19 -> 0
M22: 16 | N22: =+N4+N8 -> 93702.305
M23: 0 | N23: =+N3+N5+N6+N7 -> 313675.83
N25: =+N22+N23 -> 407378.13

Sheet MAY MXN
A1: SERIE | B1: FACTURA | C1: REFERENCIA | D1: FECHA | E1: CLIENTE | F1: CLIENTE NOMBRE | G1: COMPROBADOS | H1: COMPLEMENTARIOS | I1: IVA | J1: SUBTOTAL | K1: ANTICIPO | L1: TOTAL | M1: MONEDA | P1: DOCUMENTACION, ALMACENAJES Y MANIOBRAS ( TER) | Q1: IMPUESTOS ADUANALES (TER) | S1: HONORARIOS | T1: REVALIDACION GUIA / BOL | U1: MANIOBRAS | V1: ALMACENAJES | W1: SERVICIOS LOGISTICOS | X1: ACONDICIONAMIENTO DE EMBALAJE | Y1: RECONOCIMIENTO ADUANERO | Z1: CONSOLIDACION DE ETRADAS | AA1: SERVICIOS COMPLEMENTARIOS | AB1: SERVICIOS EXTRAORDINARIO | AC1: DEMORAS | AD1: GASTOS EN DESTINO | AE1: CUOTA | AF1: RECTIFICACIONES | AJ1: MXN | AK1: USD | AL1: TOTAL | AM1: PORCENTAJE
A2: 2 | B2: 2-002667 | C2: CGL25042849 | D2: 45784 | E2: C0002 | F2: NAPS-GUANAJUATO CAM | G2: 336 | H2: 6894.17 | I2: 1103.07 | J2: =SUM(G2:I2) -> 8333.24 | K2: 8333.24 | L2: =+J2-K2 -> 0 | M2: MXN | O2: =+H2*0.16-I2 -> -0.0028 | P2: 0 | Q2: 336 | S2: 2944.17 | T2: 0 | U2: 0 | V2: 0 | W2: 3950 | X2: 0 | Y2: 0 | Z2: 0 | AA2: 0 | AB2: 0 | AC2: 0 | AD2: 0 | AE2: 0 | AF2: 0 | AG2: =+SUM(S2:AF2)-H2 -> 0 | AI2: HONORARIOS | AJ2: =+S146 -> 878883.88 | AK2: 0 | AL2: =SUM(AJ2:AK2) -> 878883.88 | AM2: =+AL2/AL17 -> 0.16811244
A3: 2 | B3: 2-002668 | C3: CGL25042850 | D3: 45784 | E3: C0002 | F3: NAPS-GUANAJUATO CAM | G3: 336 | H3: 6894.17 | I3: 1103.07 | J3: =SUM(G3:I3) -> 8333.24 | K3: 8333.24 | L3: =+J3-K3 -> 0 | M3: MXN | P3: 0 | Q3: 336 | S3: 2944.17 | T3: 0 | U3: 0 | V3: 0 | W3: 3950 | X3: 0 | Y3: 0 | Z3: 0 | AA3: 0 | AB3: 0 | AC3: 0 | AD3: 0 | AE3: 0 | AF3: 0 | AG3: =+SUM(S3:AF3)-H3 -> 0 | AI3: REVALIDACION GUIA / BOL | AJ3: =+T146 -> 11678.2 | AK3: =+'MAY USD '!AC19 -> 8582.12 | AL3: =SUM(AJ3:AK3) -> 20260.32 | AM3: =+AL3/AL17 -> 0.0038753831
A4: 2 | B4: 2-002669 | C4: CGL25042793 | D4: 45784 | E4: C0002 | F4: NAPS-GUANAJUATO CAM | G4: 336 | H4: 8856.95 | I4: 1417.11 | J4: =SUM(G4:I4) -> 10610.06 | K4: 10610.06 | L4: =+J4-K4 -> 0 | M4: MXN | P4: 0 | Q4: 336 | S4: 4906.95 | T4: 0 | U4: 0 | V4: 0 | W4: 3950 | X4: 0 | Y4: 0 | Z4: 0 | AA4: 0 | AB4: 0 | AC4: 0 | AD4: 0 | AE4: 0 | AF4: 0 | AG4: =+SUM(S4:AF4)-H4 -> 0 | AI4: MANIOBRAS | AJ4: =+U146 -> 2196733.4 | AK4: 0 | AL4: =SUM(AJ4:AK4) -> 2196733.4 | AM4: =+AL4/AL17 -> 0.42018999
A5: 2 | B5: 2-002670 | C5: CGL25042762 | D5: 45784 | E5: C0069 | F5: JOINT PRODUCTION HONOR | G5: 782 | H5: 7781.2 | I5: 1244.99 | J5: =SUM(G5:I5) -> 9808.19 | K5: 9808.19 | L5: =+J5-K5 -> 0 | M5: MXN | P5: 0 | Q5: 782 | S5: 7781.2 | T5: 0 | U5: 0 | V5: 0 | W5: 0 | X5: 0 | Y5: 0 | Z5: 0 | AA5: 0 | AB5: 0 | AC5: 0 | AD5: 0 | AE5: 0 | AF5: 0 | AG5: =+SUM(S5:AF5)-H5 -> 0 | AI5: ALMACENAJES | AJ5: =+V146 -> 596041.34 | AK5: 0 | AL5: =SUM(AJ5:AK5) -> 596041.34 | AM5: =+AL5/AL17 -> 0.11401047
A6: 1 | B6: 1-002671 | C6: CGL25042875 | D6: 45784 | E6: C0001 | F6: ARMOR MEXICO IMAGING SUPPLIES | G6: 0 | H6: 9074.25 | I6: 1451.88 | J6: =SUM(G6:I6) -> 10526.13 | K6: 0 | L6: =+J6-K6 -> 10526.13 | M6: MXN | P6: 0 | Q6: 0 | S6: 3909.56 | T6: 1500 | U6: 1164.69 | V6: 0 | W6: 2500 | X6: 0 | Y6: 0 | Z6: 0 | AA6: 0 | AB6: 0 | AC6: 0 | AD6: 0 | AE6: 0 | AF6: 0 | AG6: =+SUM(S6:AF6)-H6 -> 0 | AI6: SERVICIOS LOGISTICOS | AJ6: =+W146 -> 968259.44 | AK6: =+'MAY USD '!AB19 -> 294647.59 | AL6: =SUM(AJ6:AK6) -> 1262907 | AM6: =+AL6/AL17 -> 0.24156818
A7: 1 | B7: 1-002672 | C7: CGL25042784 | D7: 45784 | E7: C0001 | F7: ARMOR MEXICO IMAGING SUPPLIES | G7: 0 | H7: 73533.76 | I7: 11765.41 | J7: =SUM(G7:I7) -> 85299.17 | K7: 0 | L7: =+J7-K7 -> 85299.17 | M7: MXN | P7: 0 | Q7: 0 | S7: 6087.66 | T7: 0 | U7: 25750 | V7: 0 | W7: 40837.5 | X7: 858.6 | Y7: 0 | Z7: 0 | AA7: 0 | AB7: 0 | AC7: 0 | AD7: 0 | AE7: 0 | AF7: 0 | AG7: =+SUM(S7:AF7)-H7 -> 0 | AI7: ACONDICIONAMIENTO DE EMBALAJE | AJ7: =+X146 -> 1550.25 | AK7: 0 | AL7: =SUM(AJ7:AK7) -> 1550.25 | AM7: =+AL7/AL17 -> 0.00029653099
A8: 1 | B8: 1-002673 | C8: CGL25042788 | D8: 45784 | E8: C0001 | F8: ARMOR MEXICO IMAGING SUPPLIES | G8: 0 | H8: 73285.54 | I8: 11725.68 | J8: =SUM(G8:I8) -> 85011.22 | K8: 0 | L8: =+J8-K8 -> 85011.22 | M8: MXN | P8: 0 | Q8: 0 | S8: 6006.39 | T8: 0 | U8: 25750 | V8: 0 | W8: 40837.5 | X8: 691.65 | Y8: 0 | Z8: 0 | AA8: 0 | AB8: 0 | AC8: 0 | AD8: 0 | AE8: 0 | AF8: 0 | AG8: =+SUM(S8:AF8)-H8 -> 0 | AI8: RECONOCIMIENTO ADUANERO | AJ8: =+Y146 -> 6000 | AK8: 0 | AL8: =SUM(AJ8:AK8) -> 6000 | AM8: =+AL8/AL17 -> 0.0011476768
A9: 2 | B9: 2-002674 | C9: CGL25032689 | D9: 45784 | E9: C0069 | F9: JOINT PRODUCTION HONOR | G9: 1118 | H9: 15685 | I9: 2509.6 | J9: =SUM(G9:I9) -> 19312.6 | K9: 19312.6 | L9: =+J9-K9 -> 0 | M9: MXN | P9: 0 | Q9: =782+336 -> 1118 | S9: =7789+7896 -> 15685 | T9: 0 | U9: 0 | V9: 0 | W9: 0 | X9: 0 | Y9: 0 | Z9: 0 | AA9: 0 | AB9: 0 | AC9: 0 | AD9: 0 | AE9: 0 | AF9: 0 | AG9: =+SUM(S9:AF9)-H9 -> 0 | AI9: CONSOLIDACION DE ETRADAS | AJ9: =+Z146 -> 15750 | AK9: 0 | AL9: =SUM(AJ9:AK9) -> 15750 | AM9: =+AL9/AL17 -> 0.0030126515
A10: 2 | B10: 2-002675 | C10: CGL23030260 | D10: 45785 | E10: C0079 | F10: CORE GLOBAL TRANSPORT | G10: 0 | H10: 57070.28 | I10: 9131.24 | J10: =SUM(G10:I10) -> 66201.52 | K10: 66201.52 | L10: =+J10-K10 -> 0 | M10: MXN | P10: 0 | Q10: 0 | S10: 0 | T10: 0 | U10: 0 | V10: 0 | W10: 57070.28 | X10: 0 | Y10: 0 | Z10: 0 | AA10: 0 | AB10: 0 | AC10: 0 | AD10: 0 | AE10: 0 | AF10: 0 | AG10: =+SUM(S10:AF10)-H10 -> 0 | AI10: SERVICIOS COMPLEMENTARIOS | AJ10: =+AA146 -> 110000 | AK10: 0 | AL10: =SUM(AJ10:AK10) -> 110000 | AM10: =+AL10/AL17 -> 0.021040741
A11: 2 | B11: 2-002677 | C11: CGL25042885 | D11: 45785 | E11: C0002 | F11: NAPS-GUANAJUATO CAM | G11: 781 | H11: 8150 | I11: 1304 | J11: =SUM(G11:I11) -> 10235 | K11: 10235 | L11: =+J11-K11 -> 0 | M11: MXN | P11: 0 | Q11: 781 | S11: 4200 | T11: 0 | U11: 0 | V11: 0 | W11: 3950 | X11: 0 | Y11: 0 | Z11: 0 | AA11: 0 | AB11: 0 | AC11: 0 | AD11: 0 | AE11: 0 | AF11: 0 | AG11: =+SUM(S11:AF11)-H11 -> 0 | AI11: SERVICIOS EXTRAORDINARIO | AJ11: =+AB146 -> 45715 | AK11: 0 | AL11: =SUM(AJ11:AK11) -> 45715 | AM11: =+AL11/AL17 -> 0.0087443406
A12: 1 | B12: 1-002678 | C12: CGL25042851 | D12: 45785 | E12: C0002 | F12: NAPS-GUANAJUATO CAM | G12: 336 | H12: 9300 | I12: 1488 | J12: =SUM(G12:I12) -> 11124 | K12: 11124 | L12: =+J12-K12 -> 0 | M12: MXN | P12: 0 | Q12: 336 | S12: 6000 | T12: 0 | U12: 3300 | V12: 0 | W12: 0 | X12: 0 | Y12: 0 | Z12: 0 | AA12: 0 | AB12: 0 | AC12: 0 | AD12: 0 | AE12: 0 | AF12: 0 | AG12: =+SUM(S12:AF12)-H12 -> 0 | AI12: DEMORAS | AJ12: =+AC146 -> 25285.31 | AK12: 0 | AL12: =SUM(AJ12:AK12) -> 25285.31 | AM12: =+AL12/AL17 -> 0.0048365605
A13: 1 | B13: 1-002680 | C13: CGL25042884 | D13: 45790 | E13: C0002 | F13: NAPS-GUANAJUATO CAM | G13: 2413 | H13: 16050 | I13: 2568 | J13: =SUM(G13:I13) -> 21031 | K13: 20335 | L13: =+J13-K13 -> 696 | M13: MXN | P13: 0 | Q13: 2413 | S13: 6000 | T13: 0 | U13: 5500 | V13: 0 | W13: 3950 | X13: 0 | Y13: 0 | Z13: 0 | AA13: 0 | AB13: 600 | AC13: 0 | AD13: 0 | AE13: 0 | AF13: 0 | AG13: =+SUM(S13:AF13)-H13 -> 0 | AI13: GASTOS EN DESTINO | AJ13: =+AD146 -> 13055.65 | AK13: =+'MAY USD '!AG19 -> 3885.1 | AL13: =SUM(AJ13:AK13) -> 16940.75 | AM13: =+AL13/AL17 -> 0.0032404176
A14: 2 | B14: 2-002681 | C14: CGL25042877 | D14: 45790 | E14: C0002 | F14: NAPS-GUANAJUATO CAM | G14: 336 | H14: 13803.55 | I14: 2208.57 | J14: =SUM(G14:I14) -> 16348.12 | K14: 16348.12 | L14: =+J14-K14 -> 0 | M14: MXN | P14: 0 | Q14: 336 | S14: 5903.55 | T14: 0 | U14: 0 | V14: 0 | W14: 7900 | X14: 0 | Y14: 0 | Z14: 0 | AA14: 0 | AB14: 0 | AC14: 0 | AD14: 0 | AE14: 0 | AF14: 0 | AG14: =+SUM(S14:AF14)-H14 -> 0 | AI14: CUOTA | AJ14: =+AE146 -> 1425 | AK14: 0 | AL14: =SUM(AJ14:AK14) -> 1425 | AM14: =+AL14/AL17 -> 0.00027257323
A15: 2 | B15: 2-002682 | C15: CGL25052886 | D15: 45790 | E15: C0002 | F15: NAPS-GUANAJUATO CAM | G15: 781 | H15: 8150 | I15: 1304 | J15: =SUM(G15:I15) -> 10235 | K15: 10235 | L15: =+J15-K15 -> 0 | M15: MXN | P15: 0 | Q15: 781 | S15: 4200 | T15: 0 | U15: 0 | V15: 0 | W15: 3950 | X15: 0 | Y15: 0 | Z15: 0 | AA15: 0 | AB15: 0 | AC15: 0 | AD15: 0 | AE15: 0 | AF15: 0 | AG15: =+SUM(S15:AF15)-H15 -> 0 | AI15: RECTIFICACIONES | AJ15: =+AF146 -> 1800 | AK15: 0 | AL15: =SUM(AJ15:AK15) -> 1800 | AM15: =+AL15/AL17 -> 0.00034430303
A16: 2 | B16: 2-002683 | C16: CGL25042743 | D16: 45790 | E16: C0002 | F16: NAPS-GUANAJUATO CAM | G16: 16790 | H16: 11268.96 | I16: 1803.03 | J16: =SUM(G16:I16) -> 29861.99 | K16: 29862 | L16: =+J16-K16 -> -0.01 | M16: MXN | P16: 0 | Q16: 16790 | S16: 4168.96 | T16: 0 | U16: 0 | V16: 0 | W16: 3950 | X16: 0 | Y16: 0 | Z16: 3150 | AA16: 0 | AB16: 0 | AC16: 0 | AD16: 0 | AE16: 0 | AF16: 0 | AG16: =+SUM(S16:AF16)-H16 -> 0 | AI16: GASTOS EN ORIGEN | AJ16: 0 | AK16: =+'MAY USD '!AF19 -> 48660.499 | AL16: =SUM(AJ16:AK16) -> 48660.499 | AM16: =+AL16/AL17 -> 0.0093077541
A17: 2 | B17: 2-002684 | C17: CGL25052893 | D17: 45790 | E17: C0002 | F17: NAPS-GUANAJUATO CAM | G17: 781 | H17: 8150 | I17: 1304 | J17: =SUM(G17:I17) -> 10235 | K17: 10235 | L17: =+J17-K17 -> 0 | M17: MXN | P17: 0 | Q17: 781 | S17: 4200 | T17: 0 | U17: 0 | V17: 0 | W17: 3950 | X17: 0 | Y17: 0 | Z17: 0 | AA17: 0 | AB17: 0 | AC17: 0 | AD17: 0 | AE17: 0 | AF17: 0 | AG17: =+SUM(S17:AF17)-H17 -> 0 | AJ17: =+SUM(AJ2:AJ16) -> 4872177.5 | AK17: =+SUM(AK2:AK16) -> 355775.31 | AL17: =+SUM(AL2:AL16) -> 5227952.8 | AM17: =+SUM(AM2:AM16) -> 1
A18: 2 | B18: 2-002685 | C18: CGL25042881 | D18: 45790 | E18: C0002 | F18: NAPS-GUANAJUATO CAM | G18: 781 | H18: 8150 | I18: 1304 | J18: =SUM(G18:I18) -> 10235 | K18: 10235 | L18: =+J18-K18 -> 0 | M18: MXN | P18: 0 | Q18: 781 | S18: 4200 | T18: 0 | U18: 0 | V18: 0 | W18: 3950 | X18: 0 | Y18: 0 | Z18: 0 | AA18: 0 | AB18: 0 | AC18: 0 | AD18: 0 | AE18: 0 | AF18: 0 | AG18: =+SUM(S18:AF18)-H18 -> 0
A19: 1 | B19: 1-002686 | C19: CGL25042857 | D19: 45790 | E19: C0001 | F19: ARMOR MEXICO IMAGING SUPPLIES | G19: 0 | H19: 38270.11 | I19: 6123.21 | J19: =SUM(G19:I19) -> 44393.32 | K19: 0 | L19: =+J19-K19 -> 44393.32 | M19: MXN | P19: 0 | Q19: 0 | S19: 3925.56 | T19: 3880.02 | U19: 8284.03 | V19: 2065.5 | W19: 20115 | X19: 0 | Y19: 0 | Z19: 0 | AA19: 0 | AB19: 0 | AC19: 0 | AD19: 0 | AE19: 0 | AF19: 0 | AG19: =+SUM(S19:AF19)-H19 -> 0
A20: 2 | B20: 2-002687 | C20: CGL25042858 | D20: 45790 | E20: C0001 | F20: ARMOR MEXICO IMAGING SUPPLIES | G20: 0 | H20: 35000 | I20: 5600 | J20: =SUM(G20:I20) -> 40600 | K20: 0 | L20: =+J20-K20 -> 40600 | M20: MXN | P20: 0 | Q20: 0 | S20: 4000 | T20: 0 | U20: 0 | V20: 0 | W20: 31000 | X20: 0 | Y20: 0 | Z20: 0 | AA20: 0 | AB20: 0 | AC20: 0 | AD20: 0 | AE20: 0 | AF20: 0 | AG20: =+SUM(S20:AF20)-H20 -> 0
A21: 1 | B21: 1-002688 | C21: CGL25042855 | D21: 45790 | E21: C0069 | F21: JOINT PRODUCTION HONOR | G21: 6674 | H21: 41643.42 | I21: 6662.95 | J21: =SUM(G21:I21) -> 54980.37 | K21: 118287.12 | L21: =+J21-K21 -> -63306.75 | M21: MXN | P21: 0 | Q21: 6674 | S21: 14132.01 | T21: 0 | U21: 23011.41 | V21: 0 | W21: 0 | X21: 0 | Y21: 0 | Z21: 0 | AA21: 4500 | AB21: 0 | AC21: 0 | AD21: 0 | AE21: 0 | AF21: 0 | AG21: =+SUM(S21:AF21)-H21 -> 0
A22: 1 | B22: 1-002689 | C22: CGL25052901 | D22: 45790 | E22: C0069 | F22: JOINT PRODUCTION HONOR | G22: 781 | H22: 24730.23 | I22: 3956.83 | J22: =SUM(G22:I22) -> 29468.06 | K22: 102438.65 | L22: =+J22-K22 -> -72970.59 | M22: MXN | P22: 0 | Q22: 781 | S22: 7076.52 | T22: 0 | U22: 14653.71 | V22: 0 | W22: 0 | X22: 0 | Y22: 0 | Z22: 0 | AA22: 3000 | AB22: 0 | AC22: 0 | AD22: 0 | AE22: 0 | AF22: 0 | AG22: =+SUM(S22:AF22)-H22 -> 0
A23: 1 | B23: 1-002690 | C23: CGL25042859 | D23: 45790 | E23: C0069 | F23: JOINT PRODUCTION HONOR | G23: 781 | H23: 42302.16 | I23: 6768.34 | J23: =SUM(G23:I23) -> 49851.5 | K23: 132438.65 | L23: =+J23-K23 -> -82587.15 | M23: MXN | P23: 0 | Q23: 781 | S23: 7049.7 | T23: 0 | U23: 32252.46 | V23: 0 | W23: 0 | X23: 0 | Y23: 0 | Z23: 0 | AA23: 3000 | AB23: 0 | AC23: 0 | AD23: 0 | AE23: 0 | AF23: 0 | AG23: =+SUM(S23:AF23)-H23 -> 0
A24: 1 | B24: 1-002691 | C24: CGL25052887 | D24: 45790 | E24: C0069 | F24: JOINT PRODUCTION HONOR | G24: 781 | H24: 32050.72 | I24: 5128.12 | J24: =SUM(G24:I24) -> 37959.84 | K24: 90000 | L24: =+J24-K24 -> -52040.16 | M24: MXN | P24: 0 | Q24: 781 | S24: 7059.42 | T24: 0 | U24: 21491.3 | V24: 0 | W24: 0 | X24: 0 | Y24: 0 | Z24: 0 | AA24: 3500 | AB24: 0 | AC24: 0 | AD24: 0 | AE24: 0 | AF24: 0 | AG24: =+SUM(S24:AF24)-H24 -> 0
A25: 2 | B25: 2-002694 | C25: CGL25042761 | D25: 45791 | E25: C0069 | F25: JOINT PRODUCTION HONOR | G25: 336 | H25: 7500 | I25: 1200 | J25: =SUM(G25:I25) -> 9036 | K25: 9036 | L25: =+J25-K25 -> 0 | M25: MXN | P25: 0 | Q25: 336 | S25: 7500 | T25: 0 | U25: 0 | V25: 0 | W25: 0 | X25: 0 | Y25: 0 | Z25: 0 | AA25: 0 | AB25: 0 | AC25: 0 | AD25: 0 | AE25: 0 | AF25: 0 | AG25: =+SUM(S25:AF25)-H25 -> 0
A26: 2 | B26: 2-002695 | C26: CGL25042754 | D26: 45791 | E26: C0002 | F26: NAPS-GUANAJUATO CAM | G26: 53317 | H26: 20750 | I26: 3320 | J26: =SUM(G26:I26) -> 77387 | K26: 77630 | L26: =+J26-K26 -> -243 | M26: MXN | P26: 0 | Q26: 53317 | S26: 4200 | T26: 0 | U26: 0 | V26: 0 | W26: 3950 | X26: 0 | Y26: 0 | Z26: 12600 | AA26: 0 | AB26: 0 | AC26: 0 | AD26: 0 | AE26: 0 | AF26: 0 | AG26: =+SUM(S26:AF26)-H26 -> 0
A27: 1 | B27: 1-002692 | C27: CGL25012469 | D27: 45791 | E27: C0097 | F27: CORPORATIVO ADUANAL ROBLES | G27: 0 | H27: 583471.45 | I27: 0 | J27: =SUM(G27:I27) -> 583471.45 | K27: 0 | L27: =+J27-K27 -> 583471.45 | M27: MXN | P27: 0 | Q27: 0 | S27: 0 | T27: 0 | U27: 0 | V27: 583471.45 | W27: 0 | X27: 0 | Y27: 0 | Z27: 0 | AA27: 0 | AB27: 0 | AC27: 0 | AD27: 0 | AE27: 0 | AF27: 0 | AG27: =+SUM(S27:AF27)-H27 -> 0
A28: 1 | B28: 1-002696 | C28: CGL25042775 | D28: 45792 | E28: C0004 | F28: NAPS-GUANAJUATO AMERICAN BOA | G28: 781 | H28: 125996 | I28: 20159.36 | J28: =SUM(G28:I28) -> 146936.36 | K28: 146936.36 | L28: =+J28-K28 -> 0 | M28: MXN | P28: 0 | Q28: 781 | S28: 32796 | T28: 0 | U28: 34500 | V28: 2000 | W28: 56700 | X28: 0 | Y28: 0 | Z28: 0 | AA28: 0 | AB28: 0 | AC28: 0 | AD28: 0 | AE28: 0 | AF28: 0 | AG28: =+SUM(S28:AF28)-H28 -> 0
A29: 2 | B29: 2-002697 | C29: CGL25052907 | D29: 45792 | E29: C0001 | F29: ARMOR MEXICO IMAGING SUPPLIES | G29: 0 | H29: 42040 | I29: 6726.4 | J29: =SUM(G29:I29) -> 48766.4 | K29: 0 | L29: =+J29-K29 -> 48766.4 | M29: MXN | P29: 0 | Q29: 0 | S29: 4040 | T29: 0 | U29: 0 | V29: 0 | W29: 38000 | X29: 0 | Y29: 0 | Z29: 0 | AA29: 0 | AB29: 0 | AC29: 0 | AD29: 0 | AE29: 0 | AF29: 0 | AG29: =+SUM(S29:AF29)-H29 -> 0
... A85: 1 | B85: 1-002753 0 % | C85: CGL25042854 | D85: 45798 | E85: C0069 | F85: JOINT PRODUCTION HONOR | G85: 0 | H85: 1800 | I85: 0 | J85: =SUM(G85:I85) -> 1800 | K85: 1800 | L85: =+J85-K85 -> 0 | M85: MXN | P85: 0 | Q85: 0 | S85: 0 | T85: 0 | U85: 0 | V85: 0 | W85: 0 | X85: 0 | Y85: 0 | Z85: 0 | AA85: 0 | AB85: 0 | AC85: 0 | AD85: 0 | AE85: 0 | AF85: 1800 | AG85: =+SUM(S85:AF85)-H85 -> 0
A86: 1 | B86: 1-002753 | C86: CGL25042854 | D86: 45798 | E86: C0069 | F86: JOINT PRODUCTION HONOR | G86: 781 | H86: =7049.7+3865.1+3915+608.92 -> 15438.72 | I86: 2470.2 | J86: =SUM(G86:I86) -> 18689.92 | K86: 19232.77 | L86: =+J86-K86 -> -542.85 | M86: MXN | P86: 0 | Q86: 781 | S86: 7049.7 | T86: 608.92 | U86: 3865.1 | V86: 0 | W86: 3915 | X86: 0 | Y86: 0 | Z86: 0 | AA86: 0 | AB86: 0 | AC86: 0 | AD86: 0 | AE86: 0 | AF86: 0 | AG86: =+SUM(S86:AF86)-H86 -> 0
A87: 1 | B87: 1-002754 | C87: CGL25042749 | D87: 45798 | E87: C0084 | F87: JOINT PRODUCTION TECTRAN | G87: 0 | H87: 23706.75 | I87: 3793.08 | J87: =SUM(G87:I87) -> 27499.83 | K87: 27499.83 | L87: =+J87-K87 -> 0 | M87: MXN | P87: 0 | Q87: 0 | S87: 0 | T87: 0 | U87: 0 | V87: 0 | W87: 23706.75 | X87: 0 | Y87: 0 | Z87: 0 | AA87: 0 | AB87: 0 | AC87: 0 | AD87: 0 | AE87: 0 | AF87: 0 | AG87: =+SUM(S87:AF87)-H87 -> 0
A88: 1 | B88: 1-002755 | C88: CGL25032643 | D88: 45798 | E88: C0004 | F88: NAPS-GUANAJUATO AMERICAN BOA | G88: 0 | H88: 18159.1 | I88: 2905.46 | J88: =SUM(G88:I88) -> 21064.56 | K88: 21064.56 | L88: =+J88-K88 -> 0 | M88: MXN | P88: 0 | Q88: 0 | S88: 18159.1 | T88: 0 | U88: 0 | V88: 0 | W88: 0 | X88: 0 | Y88: 0 | Z88: 0 | AA88: 0 | AB88: 0 | AC88: 0 | AD88: 0 | AE88: 0 | AF88: 0 | AG88: =+SUM(S88:AF88)-H88 -> 0
A89: 2 | B89: 2-002756 | C89: CGL25052931 | D89: 45798 | E89: C0002 | F89: NAPS-GUANAJUATO CAM | G89: 336 | H89: 12500 | I89: 2000 | J89: =SUM(G89:I89) -> 14836 | K89: 14836 | L89: =+J89-K89 -> 0 | M89: MXN | P89: 0 | Q89: 336 | S89: 6000 | T89: 0 | U89: 2500 | V89: 0 | W89: 0 | X89: 0 | Y89: 0 | Z89: 0 | AA89: 0 | AB89: 4000 | AC89: 0 | AD89: 0 | AE89: 0 | AF89: 0 | AG89: =+SUM(S89:AF89)-H89 -> 0
A90: 1 | B90: 1-002757 | C90: CGL25052929 | D90: 45798 | E90: C0069 | F90: JOINT PRODUCTION HONOR | G90: 781 | H90: 55004.42 | I90: 8800.71 | J90: =SUM(G90:I90) -> 64586.13 | K90: 98951.01 | L90: =+J90-K90 -> -34364.88 | M90: MXN | P90: 0 | Q90: 781 | S90: 7043.11 | T90: 0 | U90: 47961.31 | V90: 0 | W90: 0 | X90: 0 | Y90: 0 | Z90: 0 | AA90: 0 | AB90: 0 | AC90: 0 | AD90: 0 | AE90: 0 | AF90: 0 | AG90: =+SUM(S90:AF90)-H90 -> 0
A91: 1 | B91: 1-002758 | C91: CGL25052928 | D91: 45798 | E91: C0069 | F91: JOINT PRODUCTION HONOR | G91: 781 | H91: 11554.79 | I91: 1848.77 | J91: =SUM(G91:I91) -> 14184.56 | K91: 98951.01 | L91: =+J91-K91 -> -84766.45 | M91: MXN | P91: 0 | Q91: 781 | S91: 7043.11 | T91: 0 | U91: 4511.68 | V91: 0 | W91: 0 | X91: 0 | Y91: 0 | Z91: 0 | AA91: 0 | AB91: 0 | AC91: 0 | AD91: 0 | AE91: 0 | AF91: 0 | AG91: =+SUM(S91:AF91)-H91 -> 0
A92: 1 | B92: 1-002759 | C92: CGL25052888 | D92: 45798 | E92: C0069 | F92: JOINT PRODUCTION HONOR | G92: 781 | H92: 75383.78 | I92: 12061.41 | J92: =SUM(G92:I92) -> 88226.19 | K92: 98969.93 | L92: =+J92-K92 -> -10743.74 | M92: MXN | P92: 0 | Q92: 781 | S92: 7059.42 | T92: 0 | U92: 68324.36 | V92: 0 | W92: 0 | X92: 0 | Y92: 0 | Z92: 0 | AA92: 0 | AB92: 0 | AC92: 0 | AD92: 0 | AE92: 0 | AF92: 0 | AG92: =+SUM(S92:AF92)-H92 -> 0
A93: 1 | B93: 1-002760 | C93: CGL25052930 | D93: 45798 | E93: C0069 | F93: JOINT PRODUCTION HONOR | G93: 781 | H93: 13209.08 | I93: 2113.46 | J93: =SUM(G93:I93) -> 16103.54 | K93: 98951.01 | L93: =+J93-K93 -> -82847.47 | M93: MXN | P93: 0 | Q93: 781 | S93: 7043.11 | T93: 0 | U93: 6165.97 | V93: 0 | W93: 0 | X93: 0 | Y93: 0 | Z93: 0 | AA93: 0 | AB93: 0 | AC93: 0 | AD93: 0 | AE93: 0 | AF93: 0 | AG93: =+SUM(S93:AF93)-H93 -> 0
A94: 1 | B94: 1-002761 | C94: CGL25042874 | D94: 45798 | E94: C0069 | F94: JOINT PRODUCTION HONOR | G94: 781 | H94: 17453.33 | I94: 2792.53 | J94: =SUM(G94:I94) -> 21026.86 | K94: 23200.55 | L94: =+J94-K94 -> -2173.69 | M94: MXN | P94: 0 | Q94: 781 | S94: 7049.7 | T94: 862.5 | U94: 5626.13 | V94: 0 | W94: 3915 | X94: 0 | Y94: 0 | Z94: 0 | AA94: 0 | AB94: 0 | AC94: 0 | AD94: 0 | AE94: 0 | AF94: 0 | AG94: =+SUM(S94:AF94)-H94 -> 0
A95: 2 | B95: 2-002762 | C95: CGL25052899 | D95: 45799 | E95: C0002 | F95: NAPS-GUANAJUATO CAM | G95: 6941 | H95: 12150 | I95: 1944 | J95: =SUM(G95:I95) -> 21035 | K95: 21035 | L95: =+J95-K95 -> 0 | M95: MXN | P95: 0 | Q95: 6941 | S95: 4200 | T95: 0 | U95: 2500 | V95: 0 | W95: 3950 | X95: 0 | Y95: 1500 | Z95: 0 | AA95: 0 | AB95: 0 | AC95: 0 | AD95: 0 | AE95: 0 | AF95: 0 | AG95: =+SUM(S95:AF95)-H95 -> 0
A96: 2 | B96: 2-002763 | C96: CGL25052913 | D96: 45799 | E96: C0002 | F96: NAPS-GUANAJUATO CAM | G96: 336 | H96: 10300 | I96: 1648 | J96: =SUM(G96:I96) -> 12284 | K96: 12284 | L96: =+J96-K96 -> 0 | M96: MXN | P96: 0 | Q96: 336 | S96: 3150 | T96: 0 | U96: 0 | V96: 0 | W96: 3950 | X96: 0 | Y96: 0 | Z96: 0 | AA96: 0 | AB96: 3200 | AC96: 0 | AD96: 0 | AE96: 0 | AF96: 0 | AG96: =+SUM(S96:AF96)-H96 -> 0
A97: 2 | B97: 2-002764 | C97: CGL25052914 | D97: 45799 | E97: C0002 | F97: NAPS-GUANAJUATO CAM | G97: 336 | H97: 10300 | I97: 1648 | J97: =SUM(G97:I97) -> 12284 | K97: 12284 | L97: =+J97-K97 -> 0 | M97: MXN | P97: 0 | Q97: 336 | S97: 3150 | T97: 0 | U97: 0 | V97: 0 | W97: 3950 | X97: 0 | Y97: 0 | Z97: 0 | AA97: 0 | AB97: 3200 | AC97: 0 | AD97: 0 | AE97: 0 | AF97: 0 | AG97: =+SUM(S97:AF97)-H97 -> 0
A98: 2 | B98: 2-002765 | C98: CGL25042845 | D98: 45799 | E98: C0002 | F98: NAPS-GUANAJUATO CAM | G98: 1948 | H98: 4200 | I98: 672 | J98: =SUM(G98:I98) -> 6820 | K98: 6820 | L98: =+J98-K98 -> 0 | M98: MXN | P98: 0 | Q98: 1948 | S98: 4200 | T98: 0 | U98: 0 | V98: 0 | W98: 0 | X98: 0 | Y98: 0 | Z98: 0 | AA98: 0 | AB98: 0 | AC98: 0 | AD98: 0 | AE98: 0 | AF98: 0 | AG98: =+SUM(S98:AF98)-H98 -> 0
... A102: 2 | B102: 2-002769 | C102: CGL25052922 | D102: 45799 | E102: C0069 | F102: JOINT PRODUCTION HONOR | G102: 782 | H102: 7520 | I102: 1203.2 | J102: =SUM(G102:I102) -> 9505.2 | K102: 9505.2 | L102: =+J102-K102 -> 0 | M102: MXN | P102: 0 | Q102: 782 | S102: 7520 | T102: 0 | U102: 0 | V102: 0 | W102: 0 | X102: 0 | Y102: 0 | Z102: 0 | AA102: 0 | AB102: 0 | AC102: 0 | AD102: 0 | AE102: 0 | AF102: 0 | AG102: =+SUM(S102:AF102)-H102 -> 0
A103: 2 | B103: 2-002772 | C103: CGL25042763 | D103: 45800 | E103: C0069 | F103: JOINT PRODUCTION HONOR | G103: =782+336 -> 1118 | H103: 28005.52 | I103: 4480.88 | J103: =SUM(G103:I103) -> 33604.4 | K103: 33604.4 | L103: =+J103-K103 -> 0 | M103: MXN | P103: 0 | Q103: =782+336 -> 1118 | S103: =7521.12+5444.4+7520+7520 -> 28005.52 | T103: 0 | U103: 0 | V103: 0 | W103: 0 | X103: 0 | Y103: 0 | Z103: 0 | AA103: 0 | AB103: 0 | AC103: 0 | AD103: 0 | AE103: 0 | AF103: 0 | AG103: =+SUM(S103:AF103)-H103 -> 0
A104: 2 | B104: 2-002773 | C104: CGL25042832 | D104: 45800 | E104: C0024 | F104: SELLOS Y RETENES DE SAN LUIS | G104: 230212 | H104: 8400 | I104: 1344 | J104: =SUM(G104:I104) -> 239956 | K104: 240839 | L104: =+J104-K104 -> -883 | M104: MXN | P104: 0 | Q104: 230212 | S104: =4200+4200 -> 8400 | T104: 0 | U104: 0 | V104: 0 | W104: 0 | X104: 0 | Y104: 0 | Z104: 0 | AA104: 0 | AB104: 0 | AC104: 0 | AD104: 0 | AE104: 0 | AF104: 0 | AG104: =+SUM(S104:AF104)-H104 -> 0
A105: 2 | B105: 2-002774 | C105: CGL25052953 | D105: 45803 | E105: C0081 | F105: JOINT PRODUCTION BLACK SMITH | G105: 0 | H105: 22680.31 | I105: 3628.85 | J105: =SUM(G105:I105) -> 26309.16 | K105: 26309.16 | L105: =+J105-K105 -> 0 | M105: MXN | P105: 0 | Q105: 0 | S105: 0 | T105: 0 | U105: 0 | V105: 0 | W105: 22000 | X105: 0 | Y105: 0 | Z105: 0 | AA105: 0 | AB105: 0 | AC105: 680.31 | AD105: 0 | AE105: 0 | AF105: 0 | AG105: =+SUM(S105:AF105)-H105 -> 0
A106: 1 | B106: 1-002775 | C106: CGL25052926 | D106: 45803 | E106: C0069 | F106: JOINT PRODUCTION HONOR | G106: 781 | H106: 20911.1 | I106: 3345.78 | J106: =SUM(G106:I106) -> 25037.88 | K106: 102613 | L106: =+J106-K106 -> -77575.12 | M106: MXN | P106: 0 | Q106: 781 | S106: 7200 | T106: 0 | U106: 10711.1 | V106: 0 | W106: 0 | X106: 0 | Y106: 0 | Z106: 0 | AA106: 3000 | AB106: 0 | AC106: 0 | AD106: 0 | AE106: 0 | AF106: 0 | AG106: =+SUM(S106:AF106)-H106 -> 0
A107: 1 | B107: 1-002776 | C107: CGL25052932 | D107: 45803 | E107: C0069 | F107: JOINT PRODUCTION HONOR | G107: 0 | H107: 26986.73 | I107: 4317.88 | J107: =SUM(G107:I107) -> 31304.61 | K107: 90000 | L107: =+J107-K107 -> -58695.39 | M107: MXN | P107: 0 | Q107: 0 | S107: 7200 | T107: 0 | U107: 16786.73 | V107: 0 | W107: 0 | X107: 0 | Y107: 0 | Z107: 0 | AA107: 3000 | AB107: 0 | AC107: 0 | AD107: 0 | AE107: 0 | AF107: 0 | AG107: =+SUM(S107:AF107)-H107 -> 0
A108: 1 | B108: 1-002777 | C108: CGL25052933 | D108: 45803 | E108: C0069 | F108: JOINT PRODUCTION HONOR | G108: 0 | H108: 26986.73 | I108: 4317.88 | J108: =SUM(G108:I108) -> 31304.61 | K108: 101832 | L108: =+J108-K108 -> -70527.39 | M108: MXN | P108: 0 | Q108: 0 | S108: 7200 | T108: 0 | U108: 16786.73 | V108: 0 | W108: 0 | X108: 0 | Y108: 0 | Z108: 0 | AA108: 3000 | AB108: 0 | AC108: 0 | AD108: 0 | AE108: 0 | AF108: 0 | AG108: =+SUM(S108:AF108)-H108 -> 0
A109: 2 | B109: 2-002778 | C109: CGL25052961 | D109: 45803 | E109: C0084 | F109: JOINT PRODUCTION TECTRAN | G109: 0 | H109: 22772.41 | I109: 3643.59 | J109: =SUM(G109:I109) -> 26416 | K109: 26416 | L109: =+J109-K109 -> 0 | M109: MXN | P109: 0 | Q109: 0 | S109: 0 | T109: 0 | U109: 0 | V109: 0 | W109: 22772.41 | X109: 0 | Y109: 0 | Z109: 0 | AA109: 0 | AB109: 0 | AC109: 0 | AD109: 0 | AE109: 0 | AF109: 0 | AG109: =+SUM(S109:AF109)-H109 -> 0
A110: 1 | B110: 1-002779 | C110: CGL25032709 | D110: 45803 | E110: C0001 | F110: ARMOR MEXICO IMAGING SUPPLIES | G110: 0 | H110: 111078.38 | I110: 17772.54 | J110: =SUM(G110:I110) -> 128850.92 | K110: 0 | L110: =+J110-K110 -> 128850.92 | M110: MXN | P110: 0 | Q110: 0 | S110: 5882.85 | T110: 0 | U110: 29072.04 | V110: 5669.59 | W110: 69335 | X110: 0 | Y110: 0 | Z110: 0 | AA110: 0 | AB110: 0 | AC110: 0 | AD110: 1118.9 | AE110: 0 | AF110: 0 | AG110: =+SUM(S110:AF110)-H110 -> 0
A111: 2 | B111: 2-002780 | C111: CGL25052960 | D111: 45804 | E111: C0001 | F111: ARMOR MEXICO IMAGING SUPPLIES | G111: 0 | H111: 16542 | I111: 2646.72 | J111: =SUM(G111:I111) -> 19188.72 | K111: 0 | L111: =+J111-K111 -> 19188.72 | M111: MXN | P111: 0 | Q111: 0 | S111: 4042 | T111: 0 | U111: 0 | V111: 0 | W111: 12500 | X111: 0 | Y111: 0 | Z111: 0 | AA111: 0 | AB111: 0 | AC111: 0 | AD111: 0 | AE111: 0 | AF111: 0 | AG111: =+SUM(S111:AF111)-H111 -> 0
A112: 1 | B112: 1-002781 | C112: CGL25052943 | D112: 45804 | E112: C0069 | F112: JOINT PRODUCTION HONOR | G112: 0 | H112: 90045.75 | I112: 14407.32 | J112: =SUM(G112:I112) -> 104453.07 | K112: 112710.94 | L112: =+J112-K112 -> -8257.87 | M112: MXN | P112: 0 | Q112: 0 | S112: 7200 | T112: 0 | U112: 79845.75 | V112: 0 | W112: 0 | X112: 0 | Y112: 0 | Z112: 0 | AA112: 3000 | AB112: 0 | AC112: 0 | AD112: 0 | AE112: 0 | AF112: 0 | AG112: =+SUM(S112:AF112)-H112 -> 0
A113: 2 | B113: 2-002782 | C113: CGL25052951 | D113: 45804 | E113: C0002 | F113: NAPS-GUANAJUATO CAM | G113: 336 | H113: 10300 | I113: 1648 | J113: =SUM(G113:I113) -> 12284 | K113: 12284 | L113: =+J113-K113 -> 0 | M113: MXN | P113: 0 | Q113: 336 | S113: 3150 | T113: 0 | U113: 0 | V113: 0 | W113: 3950 | X113: 0 | Y113: 0 | Z113: 0 | AA113: 0 | AB113: 3200 | AC113: 0 | AD113: 0 | AE113: 0 | AF113: 0 | AG113: =+SUM(S113:AF113)-H113 -> 0
A114: 2 | B114: 2-002783 | C114: CGL25052952 | D114: 45804 | E114: C0002 | F114: NAPS-GUANAJUATO CAM | G114: 336 | H114: 10300 | I114: 1648 | J114: =SUM(G114:I114) -> 12284 | K114: 12284 | L114: =+J114-K114 -> 0 | M114: MXN | P114: 0 | Q114: 336 | S114: 3150 | T114: 0 | U114: 0 | V114: 0 | W114: 3950 | X114: 0 | Y114: 0 | Z114: 0 | AA114: 0 | AB114: 3200 | AC114: 0 | AD114: 0 | AE114: 0 | AF114: 0 | AG114: =+SUM(S114:AF114)-H114 -> 0
A115: 2 | B115: 2-002784 | C115: CGL25052889 | D115: 45804 | E115: C0002 | F115: NAPS-GUANAJUATO CAM | G115: 6303 | H115: 8150 | I115: 1304 | J115: =SUM(G115:I115) -> 15757 | K115: 15757 | L115: =+J115-K115 -> 0 | M115: MXN | P115: 0 | Q115: 6303 | S115: 4200 | T115: 0 | U115: 0 | V115: 0 | W115: 3950 | X115: 0 | Y115: 0 | Z115: 0 | AA115: 0 | AB115: 0 | AC115: 0 | AD115: 0 | AE115: 0 | AF115: 0 | AG115: =+SUM(S115:AF115)-H115 -> 0
A116: 2 | B116: 2-002785 | C116: CGL25052950 | D116: 45804 | E116: C0002 | F116: NAPS-GUANAJUATO CAM | G116: 781 | H116: 15350 | I116: 2456 | J116: =SUM(G116:I116) -> 18587 | K116: 18587 | L116: =+J116-K116 -> 0 | M116: MXN | P116: 0 | Q116: 781 | S116: 4200 | T116: 0 | U116: 2500 | V116: 0 | W116: 3950 | X116: 0 | Y116: 1500 | Z116: 0 | AA116: 0 | AB116: 3200 | AC116: 0 | AD116: 0 | AE116: 0 | AF116: 0 | AG116: =+SUM(S116:AF116)-H116 -> 0
... A142: 1 | B142: 1-002816 | C142: CGL25052973 | D142: 45808 | E142: C0012 | F142: MEGALUMINIO SERVICIOS | G142: 7941 | H142: 19500 | I142: 3120 | J142: =SUM(G142:I142) -> 30561 | K142: 31174.23 | L142: =+J142-K142 -> -613.23 | M142: MXN | P142: 0 | Q142: 7941 | S142: 6500 | T142: 1500 | U142: 9300 | V142: 0 | W142: 2200 | X142: 0 | Y142: 0 | Z142: 0 | AA142: 0 | AB142: 0 | AC142: 0 | AD142: 0 | AE142: 0 | AF142: 0 | AG142: =+SUM(S142:AF142)-H142 -> 0
J143: =SUM(G143:I143) -> 0 | L143: =+J143-K143 -> 0 | M143: MXN | P143: 0 | Q143: 0 | S143: 0 | T143: 0 | U143: 0 | V143: 0 | W143: 0 | X143: 0 | Y143: 0 | Z143: 0 | AA143: 0 | AB143: 0 | AC143: 0 | AD143: 0 | AE143: 0 | AF143: 0 | AG143: =+SUM(S143:AF143)-H143 -> 0
J144: =SUM(G144:I144) -> 0 | L144: =+J144-K144 -> 0 | M144: MXN | P144: 0 | Q144: 0 | S144: 0 | T144: 0 | U144: 0 | V144: 0 | W144: 0 | X144: 0 | Y144: 0 | Z144: 0 | AA144: 0 | AB144: 0 | AC144: 0 | AD144: 0 | AE144: 0 | AF144: 0 | AG144: =+SUM(S144:AF144)-H144 -> 0
J145: =SUM(G145:I145) -> 0 | L145: =+J145-K145 -> 0 | M145: MXN | P145: 0 | Q145: 0 | S145: 0 | T145: 0 | U145: 0 | V145: 0 | W145: 0 | X145: 0 | Y145: 0 | Z145: 0 | AA145: 0 | AB145: 0 | AC145: 0 | AD145: 0 | AE145: 0 | AF145: 0 | AG145: =+SUM(S145:AF145)-H145 -> 0
G146: =+SUM(G2:G145) -> 531303 | H146: =+SUM(H2:H145) -> 4872177.5 | I146: =+SUM(I2:I145) -> 683767.12 | J146: =+SUM(J2:J145) -> 6087247.6 | K146: =+SUM(K2:K145) -> 7093715.6 | L146: =+SUM(L2:L145) -> -1006468 | P146: =+SUM(P2:P145) -> 0 | Q146: =+SUM(Q2:Q145) -> 531303 | S146: =+SUM(S2:S145) -> 878883.88 | T146: =+SUM(T2:T145) -> 11678.2 | U146: =+SUM(U2:U145) -> 2196733.4 | V146: =+SUM(V2:V145) -> 596041.34 | W146: =+SUM(W2:W145) -> 968259.44 | X146: =+SUM(X2:X145) -> 1550.25 | Y146: =+SUM(Y2:Y145) -> 6000 | Z146: =+SUM(Z2:Z145) -> 15750 | ... AG146: =+SUM(AG2:AG145) -> 0
Q148: =+G146-Q146 -> 0
H150: BASE 16% | I150: BASE 0% | J150: IVA 16% | K150: T O T A L
B151: TOTAL FACTURACION | D151: =+H146+'MAY USD '!N19 -> 5227952.8 | G151: TOTAL MXN | H151: =+H146-I151 -> 4273544.3 | I151: =+H27+H79+H124+H85 -> 598633.21 | J151: =+H151*0.16 -> 683767.08 | K151: =+SUM(H151:J151) -> 5555944.6
A152: ( vs ) | B152: TOTAL SAT | D152: =+H155 -> 5227952.8 | G152: TOTAL USD | H152: =+'MAY USD '!N22 -> 8582.12 | I152: =+'MAY USD '!N23 -> 347193.19 | J152: =+H152*0.16 -> 1373.1392 | K152: =+SUM(H152:J152) -> 357148.45
A153: ( = ) | B153: DIFERENCIA | D153: =+D151-D152 -> 0 | H153: =+SUM(H151:H152) -> 4282126.4 | I153: =+SUM(I151:I152) -> 945826.4 | J153: =+SUM(J151:J152) -> 685140.22 | K153: =+SUM(K151:K152) -> 5913093
G155: TOTAL FACTURADOS | H155: =+H153+I153 -> 5227952.8

Sheet MAY USD 
G1: INFORMACION EN USD | N1: INFORMACION EN MXN
A2: SERIE | B2: FACTURA | C2: REFERENCIA | D2: FECHA | E2: CLIENTE | F2: CLIENTENOMBRE | G2: COMPROBADOS | H2: COMPLEMENTARIOS | I2: IVA | J2: SUBTOTAL | K2: ANTICIPO | L2: TOTAL | M2: TIPOCAMBIO | N2: COMPLEMENTARIOS | O2: IVA | P2: SUBTOTAL | Q2: ANTICIPO | R2: TOTAL | U2: SERVICIO LOGISTICO | V2: REVALIDACION GUIA | W2: MANIOBRAS | X2: HONORARIOS | Y2: GASTOS EN ORIGEN | Z2: GASTOS EN DESTINO | AB2: SERVICIO LOGISTICO | AC2: REVALIDACION GUIA | AD2: MANIOBRAS | AE2: HONORARIOS | AF2: GASTOS EN ORIGEN | AG2: GASTOS EN DESTINO
A3: 1 | B3: 1-002676 | C3: CGL25042814 | D3: 45785 | E3: C0001 | F3: ARMOR MEXICO IMAGING SUPPLIES | G3: 0 | H3: =2282+1587.6 -> 3869.6 | I3: 0 | J3: =SUM(G3:I3) -> 3869.6 | K3: 0 | L3: =J3-K3 -> 3869.6 | M3: 19.588 | N3: =H3*M3 -> 75797.725 | O3: =I3*M3 -> 0 | P3: =J3*M3 -> 75797.725 | Q3: =M3*K3 -> 0 | R3: =L3*M3 -> 75797.725 | U3: 2282 | V3: 0 | W3: 0 | X3: 0 | Y3: 1587.6 | Z3: 0 | AB3: =U3*M3 -> 44699.816 | AC3: =+V3*M3 -> 0 | AD3: =+M3*W3 -> 0 | AE3: =+X3*M3 -> 0 | AF3: =+Y3*M3 -> 31097.909 | AG3: =+Z3*M3 -> 0
A4: 1 | B4: 1-002679 | C4: CGL25032668 | D4: 45785 | E4: C0085 | F4: HM ULUSLARARASI PROJE TASIMACILIGI A.S | G4: 0 | H4: 75 | I4: 0 | J4: =SUM(G4:I4) -> 75 | K4: 0 | L4: =J4-K4 -> 75 | M4: 19.588 | N4: =H4*M4 -> 1469.1 | O4: =I4*M4 -> 0 | P4: =J4*M4 -> 1469.1 | Q4: =M4*K4 -> 0 | R4: =L4*M4 -> 1469.1 | U4: 0 | V4: 0 | W4: 0 | X4: 0 | Y4: 0 | Z4: 75 | AB4: =U4*M4 -> 0 | AC4: =+V4*M4 -> 0 | AD4: =+M4*W4 -> 0 | AE4: =+X4*M4 -> 0 | AF4: =+Y4*M4 -> 0 | AG4: =+Z4*M4 -> 1469.1
A5: 2 | B5: 2-002771 | C5: CGL25052942 | D5: 45800 | E5: C0084 | F5: JOIN PRODUCTIO TECTRAN | G5: 0 | H5: 6000 | I5: 0 | J5: =SUM(G5:I5) -> 6000 | K5: 0 | L5: =J5-K5 -> 6000 | M5: 19.3227 | N5: =H5*M5 -> 115936.2 | O5: =I5*M5 -> 0 | P5: =J5*M5 -> 115936.2 | Q5: =M5*K5 -> 0 | R5: =L5*M5 -> 115936.2 | U5: 6000 | V5: 0 | W5: 0 | X5: 0 | Y5: 0 | Z5: 0 | AB5: =U5*M5 -> 115936.2 | AC5: =+V5*M5 -> 0 | AD5: =+M5*W5 -> 0 | AE5: =+X5*M5 -> 0 | AF5: =+Y5*M5 -> 0 | AG5: =+Z5*M5 -> 0
A6: 1 | B6: 1-002788 | C6: CGL25052925 | D6: 45805 | E6: C0055 | F6: INTERIORISMO CORP | G6: 0 | H6: 200 | I6: 32 | J6: =SUM(G6:I6) -> 232 | K6: 232 | L6: =J6-K6 -> 0 | M6: 19.2338 | N6: =H6*M6 -> 3846.76 | O6: =I6*M6 -> 615.4816 | P6: =J6*M6 -> 4462.2416 | Q6: =M6*K6 -> 4462.2416 | R6: =L6*M6 -> 0 | U6: 0 | V6: 200 | W6: 0 | X6: 0 | Y6: 0 | Z6: 0 | AB6: =U6*M6 -> 0 | AC6: =+V6*M6 -> 3846.76 | AD6: =+M6*W6 -> 0 | AE6: =+X6*M6 -> 0 | AF6: =+Y6*M6 -> 0 | AG6: =+Z6*M6 -> 0
A7: 1 | B7: 1-002789 | C7: CGL25052925 | D7: 45805 | E7: C0055 | F7: INTERIORISMO CORP | G7: 0 | H7: =3185.1+550 -> 3735.1 | I7: 0 | J7: =SUM(G7:I7) -> 3735.1 | K7: 3735.1 | L7: =J7-K7 -> 0 | M7: 19.2338 | N7: =H7*M7 -> 71840.166 | O7: =I7*M7 -> 0 | P7: =J7*M7 -> 71840.166 | Q7: =M7*K7 -> 71840.166 | R7: =L7*M7 -> 0 | U7: 3185.1 | V7: 0 | W7: 0 | X7: 0 | Y7: 550 | Z7: 0 | AB7: =U7*M7 -> 61261.576 | AC7: =+V7*M7 -> 0 | AD7: =+M7*W7 -> 0 | AE7: =+X7*M7 -> 0 | AF7: =+Y7*M7 -> 10578.59 | AG7: =+Z7*M7 -> 0
A8: 1 | B8: 1-002805 | C8: CGL25052915 | D8: 45806 | E8: C0089 | F8: CHEMICAL COLOR DE MEXICO | G8: 0 | H8: =3750+360 -> 4110 | I8: 0 | J8: =SUM(G8:I8) -> 4110 | K8: 0 | L8: =J8-K8 -> 4110 | M8: 19.4 | N8: =H8*M8 -> 79734 | O8: =I8*M8 -> 0 | P8: =J8*M8 -> 79734 | Q8: =M8*K8 -> 0 | R8: =L8*M8 -> 79734 | U8: 3750 | V8: 0 | W8: 0 | X8: 0 | Y8: 360 | Z8: 0 | AB8: =U8*M8 -> 72750 | AC8: =+V8*M8 -> 0 | AD8: =+M8*W8 -> 0 | AE8: =+X8*M8 -> 0 | AF8: =+Y8*M8 -> 6984 | AG8: =+Z8*M8 -> 0
A9: 1 | B9: 1-002807 | C9: CGL25042746 | D9: 45807 | E9: C0086 | F9: GOMSA INTEGRADORA | G9: 0 | H9: 125 | I9: 0 | J9: =SUM(G9:I9) -> 125 | K9: 125 | L9: =J9-K9 -> 0 | M9: 19.328 | N9: =H9*M9 -> 2416 | O9: =I9*M9 -> 0 | P9: =J9*M9 -> 2416 | Q9: =M9*K9 -> 2416 | R9: =L9*M9 -> 0 | U9: 0 | V9: 0 | W9: 0 | X9: 0 | Y9: 0 | Z9: 125 | AB9: =U9*M9 -> 0 | AC9: =+V9*M9 -> 0 | AD9: =+M9*W9 -> 0 | AE9: =+X9*M9 -> 0 | AF9: =+Y9*M9 -> 0 | AG9: =+Z9*M9 -> 2416
A10: 1 | B10: 1-002808 | C10: CGL25042746 | D10: 45807 | E10: C0086 | F10: GOMSA INTEGRADORA | G10: 0 | H10: 245 | I10: =+H10*0.16 -> 39.2 | J10: =SUM(G10:I10) -> 284.2 | K10: 284.2 | L10: =J10-K10 -> 0 | M10: 19.328 | N10: =H10*M10 -> 4735.36 | O10: =I10*M10 -> 757.6576 | P10: =J10*M10 -> 5493.0176 | Q10: =M10*K10 -> 5493.0176 | R10: =L10*M10 -> 0 | U10: 0 | V10: 245 | W10: 0 | X10: 0 | Y10: 0 | Z10: 0 | AB10: =U10*M10 -> 0 | AC10: =+V10*M10 -> 4735.36 | AD10: =+M10*W10 -> 0 | AE10: =+X10*M10 -> 0 | AF10: =+Y10*M10 -> 0 | AG10: =+Z10*M10 -> 0
J11: =SUM(G11:I11) -> 0 | L11: =J11-K11 -> 0 | N11: =H11*M11 -> 0 | O11: =I11*M11 -> 0 | P11: =J11*M11 -> 0 | Q11: =M11*K11 -> 0 | R11: =L11*M11 -> 0 | U11: 0 | V11: 0 | W11: 0 | X11: 0 | Y11: 0 | Z11: 0 | AB11: =U11*M11 -> 0 | AC11: =+V11*M11 -> 0 | AD11: =+M11*W11 -> 0 | AE11: =+X11*M11 -> 0 | AF11: =+Y11*M11 -> 0 | AG11: =+Z11*M11 -> 0
J12: =SUM(G12:I12) -> 0 | L12: =J12-K12 -> 0 | N12: =H12*M12 -> 0 | O12: =I12*M12 -> 0 | P12: =J12*M12 -> 0 | Q12: =M12*K12 -> 0 | R12: =L12*M12 -> 0 | U12: 0 | V12: 0 | W12: 0 | X12: 0 | Y12: 0 | Z12: 0 | AB12: =U12*M12 -> 0 | AC12: =+V12*M12 -> 0 | AD12: =+M12*W12 -> 0 | AE12: =+X12*M12 -> 0 | AF12: =+Y12*M12 -> 0 | AG12: =+Z12*M12 -> 0
J13: =SUM(G13:I13) -> 0 | L13: =J13-K13 -> 0 | N13: =H13*M13 -> 0 | O13: =I13*M13 -> 0 | P13: =J13*M13 -> 0 | Q13: =M13*K13 -> 0 | R13: =L13*M13 -> 0 | U13: 0 | V13: 0 | W13: 0 | X13: 0 | Y13: 0 | Z13: 0 | AB13: =U13*M13 -> 0 | AC13: =+V13*M13 -> 0 | AD13: =+M13*W13 -> 0 | AE13: =+X13*M13 -> 0 | AF13: =+Y13*M13 -> 0 | AG13: =+Z13*M13 -> 0
J14: =SUM(G14:I14) -> 0 | L14: =J14-K14 -> 0 | N14: =H14*M14 -> 0 | O14: =I14*M14 -> 0 | P14: =J14*M14 -> 0 | Q14: =M14*K14 -> 0 | R14: =L14*M14 -> 0 | U14: 0 | V14: 0 | W14: 0 | X14: 0 | Y14: 0 | Z14: 0 | AB14: =U14*M14 -> 0 | AC14: =+V14*M14 -> 0 | AD14: =+M14*W14 -> 0 | AE14: =+X14*M14 -> 0 | AF14: =+Y14*M14 -> 0 | AG14: =+Z14*M14 -> 0
J15: =SUM(G15:I15) -> 0 | L15: =J15-K15 -> 0 | N15: =H15*M15 -> 0 | O15: =I15*M15 -> 0 | P15: =J15*M15 -> 0 | Q15: =M15*K15 -> 0 | R15: =L15*M15 -> 0 | U15: 0 | V15: 0 | W15: 0 | X15: 0 | Y15: 0 | Z15: 0 | AB15: =U15*M15 -> 0 | AC15: =+V15*M15 -> 0 | AD15: =+M15*W15 -> 0 | AE15: =+X15*M15 -> 0 | AF15: =+Y15*M15 -> 0 | AG15: =+Z15*M15 -> 0
J16: =SUM(G16:I16) -> 0 | L16: =J16-K16 -> 0 | N16: =H16*M16 -> 0 | O16: =I16*M16 -> 0 | P16: =J16*M16 -> 0 | Q16: =M16*K16 -> 0 | R16: =L16*M16 -> 0 | U16: 0 | V16: 0 | W16: 0 | X16: 0 | Y16: 0 | Z16: 0 | AB16: =U16*M16 -> 0 | AC16: =+V16*M16 -> 0 | AD16: =+M16*W16 -> 0 | AE16: =+X16*M16 -> 0 | AF16: =+Y16*M16 -> 0 | AG16: =+Z16*M16 -> 0
J17: =SUM(G17:I17) -> 0 | L17: =J17-K17 -> 0 | N17: =H17*M17 -> 0 | O17: =I17*M17 -> 0 | P17: =J17*M17 -> 0 | Q17: =M17*K17 -> 0 | R17: =L17*M17 -> 0 | U17: 0 | V17: 0 | W17: 0 | X17: 0 | Y17: 0 | Z17: 0 | AB17: =U17*M17 -> 0 | AC17: =+V17*M17 -> 0 | AD17: =+M17*W17 -> 0 | AE17: =+X17*M17 -> 0 | AF17: =+Y17*M17 -> 0 | AG17: =+Z17*M17 -> 0
J18: =SUM(G18:I18) -> 0 | L18: =J18-K18 -> 0 | N18: =H18*M18 -> 0 | O18: =I18*M18 -> 0 | P18: =J18*M18 -> 0 | Q18: =M18*K18 -> 0 | R18: =L18*M18 -> 0 | U18: 0 | V18: 0 | W18: 0 | X18: 0 | Y18: 0 | Z18: 0 | AB18: =U18*M18 -> 0 | AC18: =+V18*M18 -> 0 | AD18: =+M18*W18 -> 0 | AE18: =+X18*M18 -> 0 | AF18: =+Y18*M18 -> 0 | AG18: =+Z18*M18 -> 0
G19: =+SUM(G3:G18) -> 0 | H19: =+SUM(H3:H18) -> 18359.7 | I19: =+SUM(I3:I18) -> 71.2 | J19: =+SUM(J3:J18) -> 18430.9 | K19: =+SUM(K3:K18) -> 4376.3 | L19: =+SUM(L3:L18) -> 14054.6 | N19: =+SUM(N3:N18) -> 355775.31 | O19: =+SUM(O3:O18) -> 1373.1392 | P19: =+SUM(P3:P18) -> 357148.45 | Q19: =+SUM(Q3:Q18) -> 84211.426 | R19: =+SUM(R3:R18) -> 272937.02 | U19: =+SUM(U3:U18) -> 15217.1 | V19: =+SUM(V3:V18) -> 445 | W19: =+SUM(W3:W18) -> 0 | X19: =+SUM(X3:X18) -> 0 | Y19: =+SUM(Y3:Y18) -> 2497.6 | Z19: =+SUM(Z3:Z18) -> 200 | AB19: =+SUM(AB3:AB18) -> 294647.59 | AC19: =+SUM(AC3:AC18) -> 8582.12 | AD19: =+SUM(AD3:AD18) -> 0 | AE19: =+SUM(AE3:AE18) -> 0 | AF19: =+SUM(AF3:AF18) -> 48660.499 | AG19: =+SUM(AG3:AG18) -> 3885.1
Z20: =+SUM(T19:Z19) -> 18359.7 | AG20: =+SUM(AB19:AG19) -> 355775.31
Z21: =+Z20-H19 -> 0 | AG21: =+AG20-N19 -> 0
H22: 18359.7 | M22: 16 | N22: =+N6+N10 -> 8582.12
M23: 0 | N23: =+N3+N4+N5+N7+N8+N9 -> 347193.19
N25: =+N22+N23 -> 355775.31

Sheet JUL MXN
A1: SERIE | B1: FACTURA | C1: REFERENCIA | D1: FECHA | E1: CLIENTE | F1: CLIENTE NOMBRE | G1: COMPROBADOS | H1: COMPLEMENTARIOS | I1: IVA | J1: SUBTOTAL | K1: ANTICIPO | L1: TOTAL | M1: MONEDA | P1: DOCUMENTACION, ALMACENAJES Y MANIOBRAS ( TER) | Q1: IMPUESTOS ADUANALES (TER) | S1: HONORARIOS | T1: REVALIDACION GUIA / BOL | U1: MANIOBRAS | V1: ALMACENAJES | W1: SERVICIOS LOGISTICOS | X1: RECONOCIMIENTO ADUANERO | Y1: CONSOLIDACION DE ETRADAS | Z1: DEMORAS | AA1: SERVICIOS EXTRAORDINARIO | AB1: SERVICIOS COMPLEMENTARIOS | AC1: LIMPIEZA DE CONTENEDOR | AD1: CUOTA | AE1: LIBERACIONES DOCUMENTOS | AF1: CERTIFICADO DE ORIGEN | AG1: GASTOS EN DESTINO | AH1: RECTIFICACIONES | AL1: MXN | AM1: USD | AN1: TOTAL | AO1: PORCENTAJE
A2: 2 | B2: 2-002890 | C2: CGL25063092 | D2: 45842 | E2: C0002 | F2: NAPS-GUANAJUATO CAM | G2: 336 | H2: 17400 | I2: 2784 | J2: =SUM(G2:I2) -> 20520 | K2: 20520 | L2: =+J2-K2 -> 0 | M2: MXN | P2: 0 | Q2: 336 | S2: =4800+4800 -> 9600 | T2: 0 | U2: 0 | V2: 0 | W2: 7800 | X2: 0 | Y2: 0 | Z2: 0 | AA2: 0 | AB2: 0 | AC2: 0 | AD2: 0 | AE2: 0 | AF2: 0 | AH2: 0 | AI2: =+SUM(S2:AH2)-H2 -> 0 | AK2: HONORARIOS | AL2: =+S153 -> 992307.04 | AN2: =SUM(AL2:AM2) -> 992307.04 | AO2: =+AN2/AN20 -> 0.15661726
A3: 2 | B3: 2-002891 | C3: CGL25063090 | D3: 45842 | E3: C0002 | F3: NAPS-GUANAJUATO CAM | G3: 336 | H3: 9700 | I3: 1552 | J3: =SUM(G3:I3) -> 11588 | K3: 11588 | L3: =+J3-K3 -> 0 | M3: MXN | P3: 0 | Q3: 336 | S3: 4800 | T3: 0 | U3: 0 | V3: 0 | W3: 4900 | X3: 0 | Y3: 0 | Z3: 0 | AA3: 0 | AB3: 0 | AC3: 0 | AD3: 0 | AE3: 0 | AF3: 0 | AG3: 0 | AH3: 0 | AI3: =+SUM(S3:AH3)-H3 -> 0 | AK3: REVALIDACION GUIA / BOL | AL3: =+T153 -> 6585.68 | AM3: =+'JUL USD'!AD19 -> 1485.88 | AN3: =SUM(AL3:AM3) -> 8071.56 | AO3: =+AN3/AN20 -> 0.001273946
A4: 2 | B4: 2-002892 | C4: CGL25063070 | D4: 45842 | E4: C0002 | F4: NAPS-GUANAJUATO CAM | G4: 336 | H4: 4200 | I4: 672 | J4: =SUM(G4:I4) -> 5208 | K4: 5208 | L4: =+J4-K4 -> 0 | M4: MXN | P4: 0 | Q4: 336 | S4: 4200 | T4: 0 | U4: 0 | V4: 0 | W4: 0 | X4: 0 | Y4: 0 | Z4: 0 | AA4: 0 | AB4: 0 | AC4: 0 | AD4: 0 | AE4: 0 | AF4: 0 | AG4: 0 | AH4: 0 | AI4: =+SUM(S4:AH4)-H4 -> 0 | AK4: MANIOBRAS | AL4: =+U153 -> 2179527.3 | AN4: =SUM(AL4:AM4) -> 2179527.3 | AO4: =+AN4/AN20 -> 0.34399796
A5: 2 | B5: 2-002893 | C5: CGL25063170 | D5: 45842 | E5: C0002 | F5: NAPS-GUANAJUATO CAM | G5: 336 | H5: 10700 | I5: 1712 | J5: =SUM(G5:I5) -> 12748 | K5: 18316 | L5: =+J5-K5 -> -5568 | M5: MXN | P5: 0 | Q5: 336 | S5: 6000 | T5: 0 | U5: 700 | V5: 0 | W5: 0 | X5: 0 | Y5: 0 | Z5: 0 | AA5: 4000 | AB5: 0 | AC5: 0 | AD5: 0 | AE5: 0 | AF5: 0 | AG5: 0 | AH5: 0 | AI5: =+SUM(S5:AH5)-H5 -> 0 | AK5: ALMACENAJES | AL5: =+V153 -> 1219566.3 | AN5: =SUM(AL5:AM5) -> 1219566.3 | AO5: =+AN5/AN20 -> 0.19248591
A6: 2 | B6: 2-002894 | C6: CGL25063066 | D6: 45842 | E6: C0002 | F6: NAPS-GUANAJUATO CAM | G6: 64293 | H6: 41000 | I6: 6560 | J6: =SUM(G6:I6) -> 111853 | K6: 111853 | L6: =+J6-K6 -> 0 | M6: MXN | P6: 0 | Q6: 64293 | S6: 6000 | T6: 0 | U6: 20000 | V6: 0 | W6: 15000 | X6: 0 | Y6: 0 | Z6: 0 | AA6: 0 | AB6: 0 | AC6: 0 | AD6: 0 | AE6: 0 | AF6: 0 | AG6: 0 | AH6: 0 | AI6: =+SUM(S6:AH6)-H6 -> 0 | AK6: SERVICIOS LOGISTICOS | AL6: =+W153 -> 1019120.3 | AM6: =+'JUL USD'!AB19 -> 534981.39 | AN6: =SUM(AL6:AM6) -> 1554101.6 | AO6: =+AN6/AN20 -> 0.24528612
A7: 2 | B7: 2-002895 | C7: CGL25063039 | D7: 45842 | E7: C0002 | F7: NAPS-GUANAJUATO CAM | G7: 1703 | H7: 4800 | I7: 768 | J7: =SUM(G7:I7) -> 7271 | K7: 7271 | L7: =+J7-K7 -> 0 | M7: MXN | P7: 0 | Q7: 1703 | S7: 4800 | T7: 0 | U7: 0 | V7: 0 | W7: 0 | X7: 0 | Y7: 0 | Z7: 0 | AA7: 0 | AB7: 0 | AC7: 0 | AD7: 0 | AE7: 0 | AF7: 0 | AG7: 0 | AH7: 0 | AI7: =+SUM(S7:AH7)-H7 -> 0 | AK7: RECONOCIMIENTO ADUANERO | AL7: =+X153 -> 44200 | AN7: =SUM(AL7:AM7) -> 44200 | AO7: =+AN7/AN20 -> 0.0069761501
A8: 2 | B8: 2-002896 | C8: CGL25052975 | D8: 45842 | E8: C0002 | F8: NAPS-GUANAJUATO CAM | G8: 336 | H8: 4800 | I8: 768 | J8: =SUM(G8:I8) -> 5904 | K8: 5904 | L8: =+J8-K8 -> 0 | M8: MXN | P8: 0 | Q8: 336 | S8: 4800 | T8: 0 | U8: 0 | V8: 0 | W8: 0 | X8: 0 | Y8: 0 | Z8: 0 | AA8: 0 | AB8: 0 | AC8: 0 | AD8: 0 | AE8: 0 | AF8: 0 | AG8: 0 | AH8: 0 | AI8: =+SUM(S8:AH8)-H8 -> 0 | AK8: CONSOLIDACION DE ETRADAS | AL8: =+Y153 -> 43376 | AN8: =SUM(AL8:AM8) -> 43376 | AO8: =+AN8/AN20 -> 0.006846097
A9: 2 | B9: 2-002897 | C9: CGL25063069 | D9: 45842 | E9: C0002 | F9: NAPS-GUANAJUATO CAM | G9: 781 | H9: 7276 | I9: 1164.16 | J9: =SUM(G9:I9) -> 9221.16 | K9: 9221.16 | L9: =+J9-K9 -> 0 | M9: MXN | P9: 0 | Q9: 781 | S9: 4200 | T9: 0 | U9: 0 | V9: 0 | W9: 0 | X9: 0 | Y9: 1576 | Z9: 0 | AA9: 1500 | AB9: 0 | AC9: 0 | AD9: 0 | AE9: 0 | AF9: 0 | AG9: 0 | AH9: 0 | AI9: =+SUM(S9:AH9)-H9 -> 0 | AK9: DEMORAS | AL9: =+Z153 -> 5094 | AN9: =SUM(AL9:AM9) -> 5094 | AO9: =+AN9/AN20 -> 0.00080399341
A10: 2 | B10: 2-002898 | C10: CGL25063041 | D10: 45842 | E10: C0002 | F10: NAPS-GUANAJUATO CAM | G10: 781 | H10: 6100 | I10: 976 | J10: =SUM(G10:I10) -> 7857 | K10: 7857 | L10: =+J10-K10 -> 0 | M10: MXN | P10: 0 | Q10: 781 | S10: 4300 | T10: 0 | U10: 0 | V10: 0 | W10: 0 | X10: 1800 | Y10: 0 | Z10: 0 | AA10: 0 | AB10: 0 | AC10: 0 | AD10: 0 | AE10: 0 | AF10: 0 | AG10: 0 | AH10: 0 | AI10: =+SUM(S10:AH10)-H10 -> 0 | AK10: SERVICIOS EXTRAORDINARIO | AL10: =+AB153 -> 55215 | AN10: =SUM(AL10:AM10) -> 55215 | AO10: =+AN10/AN20 -> 0.0087146636
A11: 2 | B11: 2-002899 | C11: CGL25053012 | D11: 45842 | E11: C0002 | F11: NAPS-GUANAJUATO CAM | G11: 336 | H11: 8150 | I11: 1304 | J11: =SUM(G11:I11) -> 9790 | K11: 9790 | L11: =+J11-K11 -> 0 | M11: MXN | P11: 0 | Q11: 336 | S11: 4200 | T11: 0 | U11: 0 | V11: 0 | W11: 3950 | X11: 0 | Y11: 0 | Z11: 0 | AA11: 0 | AB11: 0 | AC11: 0 | AD11: 0 | AE11: 0 | AF11: 0 | AG11: 0 | AH11: 0 | AI11: =+SUM(S11:AH11)-H11 -> 0 | AK11: SERVICIOS COMPLEMENTARIOS | AL11: =+AB153 -> 55215 | AN11: =SUM(AL11:AM11) -> 55215 | AO11: =+AN11/AN20 -> 0.0087146636
A12: 2 | B12: 2-002900 | C12: CGL25063117 | D12: 45842 | E12: C0002 | F12: NAPS-GUANAJUATO CAM | G12: 336 | H12: 17300 | I12: 2768 | J12: =SUM(G12:I12) -> 20404 | K12: 20404 | L12: =+J12-K12 -> 0 | M12: MXN | P12: 0 | Q12: 336 | S12: 4800 | T12: 0 | U12: 0 | V12: 0 | W12: 12500 | X12: 0 | Y12: 0 | Z12: 0 | AA12: 0 | AB12: 0 | AC12: 0 | AD12: 0 | AE12: 0 | AF12: 0 | AG12: 0 | AH12: 0 | AI12: =+SUM(S12:AH12)-H12 -> 0 | AK12: LIMPIEZA DE CONTENEDOR | AL12: =+AC153 -> 20400 | AN12: =SUM(AL12:AM12) -> 20400 | AO12: =+AN12/AN20 -> 0.0032197616
A13: 2 | B13: 2-002901 | C13: CGL25063125 | D13: 45842 | E13: C0002 | F13: NAPS-GUANAJUATO CAM | G13: 336 | H13: 13600 | I13: 2176 | J13: =SUM(G13:I13) -> 16112 | K13: 16112 | L13: =+J13-K13 -> 0 | M13: MXN | P13: 0 | Q13: 336 | S13: 6000 | T13: 0 | U13: 3600 | V13: 0 | W13: 0 | X13: 0 | Y13: 0 | Z13: 0 | AA13: 4000 | AB13: 0 | AC13: 0 | AD13: 0 | AE13: 0 | AF13: 0 | AG13: 0 | AH13: 0 | AI13: =+SUM(S13:AH13)-H13 -> 0 | AK13: CUOTA | AL13: =+AD153 -> 4725 | AN13: =SUM(AL13:AM13) -> 4725 | AO13: =+AN13/AN20 -> 0.00074575361
A14: 2 | B14: 2-002902 | C14: CGL25053028 | D14: 45842 | E14: C0002 | F14: NAPS-GUANAJUATO CAM | G14: 782 | H14: 9600 | I14: 1536 | J14: =SUM(G14:I14) -> 11918 | K14: 11918 | L14: =+J14-K14 -> 0 | M14: MXN | P14: 0 | Q14: 782 | S14: 4800 | T14: 0 | U14: 0 | V14: 0 | W14: 4800 | X14: 0 | Y14: 0 | Z14: 0 | AA14: 0 | AB14: 0 | AC14: 0 | AD14: 0 | AE14: 0 | AF14: 0 | AG14: 0 | AH14: 0 | AI14: =+SUM(S14:AH14)-H14 -> 0 | AK14: LIBERACIONES DOCUMENTOS | AL14: =+AE153 -> 11025 | AM14: =+'JUL USD'!AE19 -> 1857.35 | AN14: =SUM(AL14:AM14) -> 12882.35 | AO14: =+AN14/AN20 -> 0.00203324
A15: 2 | B15: 2-002903 | C15: CGL25052984 | D15: 45842 | E15: C0002 | F15: NAPS-GUANAJUATO CAM | G15: 37467 | H15: 10800 | I15: 1728 | J15: =SUM(G15:I15) -> 49995 | K15: 49995 | L15: =+J15-K15 -> 0 | M15: MXN | P15: 0 | Q15: 37467 | S15: 4800 | T15: 0 | U15: 0 | V15: 0 | W15: 0 | X15: 0 | Y15: 6000 | Z15: 0 | AA15: 0 | AB15: 0 | AC15: 0 | AD15: 0 | AE15: 0 | AF15: 0 | AG15: 0 | AH15: 0 | AI15: =+SUM(S15:AH15)-H15 -> 0 | AK15: CERTIFICADO DE ORIGEN | AL15: =+AF153 -> 3540 | AN15: =SUM(AL15:AM15) -> 3540 | AO15: =+AN15/AN20 -> 0.00055872334
A16: 2 | B16: 2-002904 | C16: CGL25063161 | D16: 45842 | E16: C0081 | F16: JOINT PRODUCTION BLACK SMITH | G16: 0 | H16: 22000 | I16: 3520 | J16: =SUM(G16:I16) -> 25520 | K16: 25520 | L16: =+J16-K16 -> 0 | M16: MXN | P16: 0 | Q16: 0 | S16: 0 | T16: 0 | U16: 0 | V16: 0 | W16: 22000 | X16: 0 | Y16: 0 | Z16: 0 | AA16: 0 | AB16: 0 | AC16: 0 | AD16: 0 | AE16: 0 | AF16: 0 | AG16: 0 | AH16: 0 | AI16: =+SUM(S16:AH16)-H16 -> 0 | AK16: GASTOS EN DESTINO | AL16: =+AG153 -> 6346.6 | AM16: =+'JUL USD'!AG19 -> 21322.47 | AN16: =SUM(AL16:AM16) -> 27669.07 | AO16: =+AN16/AN20 -> 0.0043670495
A17: 2 | B17: 2-002905 | C17: CGL25063164 | D17: 45842 | E17: C0081 | F17: JOINT PRODUCTION BLACK SMITH | G17: 0 | H17: 22000 | I17: 3520 | J17: =SUM(G17:I17) -> 25520 | K17: 25520 | L17: =+J17-K17 -> 0 | M17: MXN | P17: 0 | Q17: 0 | S17: 0 | T17: 0 | U17: 0 | V17: 0 | W17: 22000 | X17: 0 | Y17: 0 | Z17: 0 | AA17: 0 | AB17: 0 | AC17: 0 | AD17: 0 | AE17: 0 | AF17: 0 | AG17: 0 | AH17: 0 | AI17: =+SUM(S17:AH17)-H17 -> 0 | AK17: RECTIFICACIONES | AL17: =+AH153 -> 1900 | AN17: =SUM(AL17:AM17) -> 1900 | AO17: =+AN17/AN20 -> 0.00029987976
A18: 2 | B18: 2-002906 | C18: CGL25063106 | D18: 45842 | E18: C0069 | F18: JOINT PRODUCTION HONOR | G18: 336 | H18: 9600 | I18: 1536 | J18: =SUM(G18:I18) -> 11472 | K18: 11472 | L18: =+J18-K18 -> 0 | M18: MXN | P18: 0 | Q18: 336 | S18: =4800+4800 -> 9600 | T18: 0 | U18: 0 | V18: 0 | W18: 0 | X18: 0 | Y18: 0 | Z18: 0 | AA18: 0 | AB18: 0 | AC18: 0 | AD18: 0 | AE18: 0 | AF18: 0 | AG18: 0 | AH18: 0 | AI18: =+SUM(S18:AH18)-H18 -> 0 | AK18: SEGURO | AM18: =+'JUL USD'!AC19 -> 6552 | AN18: =SUM(AL18:AM18) -> 6552 | AO18: =+AN18/AN20 -> 0.0010341117
A19: 2 | B19: 2-002907 | C19: CGL25063040 | D19: 45842 | E19: C0002 | F19: NAPS-GUANAJUATO CAM | G19: 336 | H19: 8300 | I19: 1328 | J19: =SUM(G19:I19) -> 9964 | K19: 9964 | L19: =+J19-K19 -> 0 | M19: MXN | P19: 0 | Q19: 336 | S19: 4800 | T19: 0 | U19: 0 | V19: 0 | W19: 0 | X19: 2300 | Y19: 1200 | Z19: 0 | AA19: 0 | AB19: 0 | AC19: 0 | AD19: 0 | AE19: 0 | AF19: 0 | AG19: 0 | AH19: 0 | AI19: =+SUM(S19:AH19)-H19 -> 0 | AK19: GASTOS EN ORIGEN | AM19: =+'JUL USD'!AF19 -> 101530.55 | AN19: =SUM(AL19:AM19) -> 101530.55 | AO19: =+AN19/AN20 -> 0.016024714
A20: 2 | B20: 2-002908 | C20: CGL25063033 | D20: 45842 | E20: C0002 | F20: NAPS-GUANAJUATO CAM | G20: 0 | H20: 8600 | I20: 1376 | J20: =SUM(G20:I20) -> 9976 | K20: 9976 | L20: =+J20-K20 -> 0 | M20: MXN | P20: 0 | Q20: 0 | S20: 4800 | T20: 0 | U20: 0 | V20: 0 | W20: 3800 | X20: 0 | Y20: 0 | Z20: 0 | AA20: 0 | AB20: 0 | AC20: 0 | AD20: 0 | AE20: 0 | AF20: 0 | AG20: 0 | AH20: 0 | AI20: =+SUM(S20:AH20)-H20 -> 0 | AL20: =+SUM(AL2:AL19) -> 5668143.2 | AM20: =+SUM(AM2:AM19) -> 667729.64 | AN20: =+SUM(AN2:AN19) -> 6335872.8 | AO20: =+SUM(AO2:AO19) -> 1
A21: 2 | B21: 2-002909 | C21: CGL25063038 | D21: 45842 | E21: C0002 | F21: NAPS-GUANAJUATO CAM | G21: 781 | H21: 4800 | I21: 768 | J21: =SUM(G21:I21) -> 6349 | K21: 6349 | L21: =+J21-K21 -> 0 | M21: MXN | P21: 0 | Q21: 781 | S21: 4800 | T21: 0 | U21: 0 | V21: 0 | W21: 0 | X21: 0 | Y21: 0 | Z21: 0 | AA21: 0 | AB21: 0 | AC21: 0 | AD21: 0 | AE21: 0 | AF21: 0 | AG21: 0 | AH21: 0 | AI21: =+SUM(S21:AH21)-H21 -> 0
A22: 2 | B22: 2-002910 | C22: CGL25053004 | D22: 45842 | E22: C0002 | F22: NAPS-GUANAJUATO CAM | G22: 44608 | H22: 17500 | I22: 2800 | J22: =SUM(G22:I22) -> 64908 | K22: 64778 | L22: =+J22-K22 -> 130 | M22: MXN | P22: 0 | Q22: 44608 | S22: 4900 | T22: 0 | U22: 0 | V22: 0 | W22: 0 | X22: 0 | Y22: 12600 | Z22: 0 | AA22: 0 | AB22: 0 | AC22: 0 | AD22: 0 | AE22: 0 | AF22: 0 | AG22: 0 | AH22: 0 | AI22: =+SUM(S22:AH22)-H22 -> 0
A23: 2 | B23: 2-002911 | C23: CGL25063126 | D23: 45845 | E23: C0002 | F23: NAPS-GUANAJUATO CAM | G23: 336 | H23: 8000 | I23: 1280 | J23: =SUM(G23:I23) -> 9616 | K23: 9616 | L23: =+J23-K23 -> 0 | M23: MXN | P23: 0 | Q23: 336 | S23: 4800 | T23: 0 | U23: 0 | V23: 0 | W23: 3200 | X23: 0 | Y23: 0 | Z23: 0 | AA23: 0 | AB23: 0 | AC23: 0 | AD23: 0 | AE23: 0 | AF23: 0 | AG23: 0 | AH23: 0 | AI23: =+SUM(S23:AH23)-H23 -> 0
A24: 2 | B24: 2-002912 | C24: CGL25063121 | D24: 45845 | E24: C0002 | F24: NAPS-GUANAJUATO CAM | G24: 12907 | H24: 7700 | I24: 1232 | J24: =SUM(G24:I24) -> 21839 | K24: 21839 | L24: =+J24-K24 -> 0 | M24: MXN | P24: 0 | Q24: 12907 | S24: 4200 | T24: 0 | U24: 0 | V24: 0 | W24: 0 | X24: 2300 | Y24: 1200 | Z24: 0 | AA24: 0 | AB24: 0 | AC24: 0 | AD24: 0 | AE24: 0 | AF24: 0 | AG24: 0 | AH24: 0 | AI24: =+SUM(S24:AH24)-H24 -> 0
A25: 2 | B25: 2-002913 | C25: CGL25063147 | D25: 45845 | E25: C0001 | F25: ARMOR MEXICO IMAGING SUPPLIES | G25: 0 | H25: 42100 | I25: 6736 | J25: =SUM(G25:I25) -> 48836 | K25: 0 | L25: =+J25-K25 -> 48836 | M25: MXN | P25: 0 | Q25: 0 | S25: 4600 | T25: 0 | U25: 0 | V25: 0 | W25: 37500 | X25: 0 | Y25: 0 | Z25: 0 | AA25: 0 | AB25: 0 | AC25: 0 | AD25: 0 | AE25: 0 | AF25: 0 | AG25: 0 | AH25: 0 | AI25: =+SUM(S25:AH25)-H25 -> 0
A26: 2 | B26: 2-002914 | C26: CGL25063148 | D26: 45845 | E26: C0001 | F26: ARMOR MEXICO IMAGING SUPPLIES | G26: 0 | H26: 25200 | I26: 4032 | J26: =SUM(G26:I26) -> 29232 | K26: 0 | L26: =+J26-K26 -> 29232 | M26: MXN | P26: 0 | Q26: 0 | S26: 4400 | T26: 0 | U26: 0 | V26: 0 | W26: 19000 | X26: 1800 | Y26: 0 | Z26: 0 | AA26: 0 | AB26: 0 | AC26: 0 | AD26: 0 | AE26: 0 | AF26: 0 | AG26: 0 | AH26: 0 | AI26: =+SUM(S26:AH26)-H26 -> 0
A27: 2 | B27: 2-002915 | C27: CGL25063173 | D27: 45845 | E27: C0081 | F27: JOINT PRODUCTION BLACK SMITH | G27: 0 | H27: 22000 | I27: 3520 | J27: =SUM(G27:I27) -> 25520 | K27: 25520 | L27: =+J27-K27 -> 0 | M27: MXN | P27: 0 | Q27: 0 | S27: 0 | T27: 0 | U27: 0 | V27: 0 | W27: 22000 | X27: 0 | Y27: 0 | Z27: 0 | AA27: 0 | AB27: 0 | AC27: 0 | AD27: 0 | AE27: 0 | AF27: 0 | AG27: 0 | AH27: 0 | AI27: =+SUM(S27:AH27)-H27 -> 0
A28: 1 | B28: 1-002916 | C28: CGL25063111 | D28: 45845 | E28: C0069 | F28: JOINT PRODUCTION HONOR | G28: 2116 | H28: 15499.2 | I28: 2479.87 | J28: =SUM(G28:I28) -> 20095.07 | K28: 51832 | L28: =+J28-K28 -> -31736.93 | M28: MXN | P28: 0 | Q28: 2116 | S28: 7200 | T28: 0 | U28: 5299.2 | V28: 0 | W28: 0 | X28: 3000 | Y28: 0 | Z28: 0 | AA28: 0 | AB28: 0 | AC28: 0 | AD28: 0 | AE28: 0 | AF28: 0 | AG28: 0 | AH28: 0 | AI28: =+SUM(S28:AH28)-H28 -> 0
A29: 2 | B29: 2-002917 | C29: CGL25063171 | D29: 45846 | E29: C0001 | F29: ARMOR MEXICO IMAGING SUPPLIES | G29: 0 | H29: =4400+1800+19000 -> 25200 | I29: 4032 | J29: =SUM(G29:I29) -> 29232 | K29: 0 | L29: =+J29-K29 -> 29232 | M29: MXN | P29: 0 | Q29: 0 | S29: 4400 | T29: 0 | U29: 0 | V29: 0 | W29: 19000 | X29: 1800 | Y29: 0 | Z29: 0 | AA29: 0 | AB29: 0 | AC29: 0 | AD29: 0 | AE29: 0 | AF29: 0 | AG29: 0 | AH29: 0 | AI29: =+SUM(S29:AH29)-H29 -> 0
A30: 2 | B30: 2-002918 | C30: CGL25063128 | D30: 45846 | E30: C0002 | F30: NAPS-GUANAJUATO CAM | G30: 336 | H30: =12000+1250 -> 13250 | I30: 2120 | J30: =SUM(G30:I30) -> 15706 | K30: 32480 | L30: =+J30-K30 -> -16774 | M30: MXN | P30: 0 | Q30: 336 | S30: 12000 | T30: 0 | U30: 1250 | V30: 0 | W30: 0 | X30: 0 | Y30: 0 | Z30: 0 | AA30: 0 | AB30: 0 | AC30: 0 | AD30: 0 | AE30: 0 | AF30: 0 | AG30: 0 | AH30: 0 | AI30: =+SUM(S30:AH30)-H30 -> 0
A31: 1 | B31: 1-002919 | C31: CGL25063138 | D31: 45846 | E31: C0069 | F31: JOINT PRODUCTION HONOR | G31: 781 | H31: =6872.32+2530.65+3915+608.92 -> 13926.89 | I31: 2228.3 | J31: =SUM(G31:I31) -> 16936.19 | K31: 28294.3 | L31: =+J31-K31 -> -11358.11 | M31: MXN | P31: 0 | Q31: 781 | S31: 6872.32 | T31: 608.92 | U31: 2530.65 | V31: 0 | W31: 3915 | X31: 0 | Y31: 0 | Z31: 0 | AA31: 0 | AB31: 0 | AC31: 0 | AD31: 0 | AE31: 0 | AF31: 0 | AG31: 0 | AH31: 0 | AI31: =+SUM(S31:AH31)-H31 -> 0
A32: 2 | B32: 2-002920 | C32: CGL25052978 | D32: 45847 | E32: C0002 | F32: NAPS-GUANAJUATO CAM | G32: 336 | H32: 14103 | I32: 2256.48 | J32: =SUM(G32:I32) -> 16695.48 | K32: 16695.48 | L32: =+J32-K32 -> 0 | M32: MXN | P32: 0 | Q32: 336 | S32: 5903 | T32: 0 | U32: 0 | V32: 0 | W32: 6200 | X32: 2000 | Y32: 0 | Z32: 0 | AA32: 0 | AB32: 0 | AC32: 0 | AD32: 0 | AE32: 0 | AF32: 0 | AG32: 0 | AH32: 0 | AI32: =+SUM(S32:AH32)-H32 -> 0
A33: 1 | B33: 1-002921 | C33: CGL25063085 | D33: 45847 | E33: C0069 | F33: JOINT PRODUCTION HONOR | G33: 781 | H33: 18041.65 | I33: 2886.67 | J33: =SUM(G33:I33) -> 21709.32 | K33: 35051.8 | L33: =+J33-K33 -> -13342.48 | M33: MXN | P33: 0 | Q33: 781 | S33: 6887.41 | T33: 0 | U33: 5739.24 | V33: 0 | W33: 3915 | X33: 1500 | Y33: 0 | Z33: 0 | AA33: 0 | AB33: 0 | AC33: 0 | AD33: 0 | AE33: 0 | AF33: 0 | AG33: 0 | AH33: 0 | AI33: =+SUM(S33:AH33)-H33 -> 0
A34: 1 | B34: 1-002922 | C34: CGL25063145 | D34: 45848 | E34: C0069 | F34: JOINT PRODUCTION HONOR | G34: 0 | H34: 37539.64 | I34: 6006.34 | J34: =SUM(G34:I34) -> 43545.98 | K34: 71832 | L34: =+J34-K34 -> -28286.02 | M34: MXN | P34: 0 | Q34: 0 | S34: 7200 | T34: 0 | U34: 30339.64 | V34: 0 | W34: 0 | X34: 0 | Y34: 0 | Z34: 0 | AA34: 0 | AB34: 0 | AC34: 0 | AD34: 0 | AE34: 0 | AF34: 0 | AG34: 0 | AH34: 0 | AI34: =+SUM(S34:AH34)-H34 -> 0
A35: 1 | B35: 1-002923 | C35: CGL25063146 | D35: 45848 | E35: C0069 | F35: JOINT PRODUCTION HONOR | G35: 0 | H35: 43320.06 | I35: 6931.21 | J35: =SUM(G35:I35) -> 50251.27 | K35: 71832 | L35: =+J35-K35 -> -21580.73 | M35: MXN | P35: 0 | Q35: 0 | S35: 7200 | T35: 0 | U35: 36120.06 | V35: 0 | W35: 0 | X35: 0 | Y35: 0 | Z35: 0 | AA35: 0 | AB35: 0 | AC35: 0 | AD35: 0 | AE35: 0 | AF35: 0 | AG35: 0 | AH35: 0 | AI35: =+SUM(S35:AH35)-H35 -> 0
A36: 1 | B36: 1-002924 | C36: CGL25063151 | D36: 45848 | E36: C0069 | F36: JOINT PRODUCTION HONOR | G36: 0 | H36: 27429.66 | I36: 4388.75 | J36: =SUM(G36:I36) -> 31818.41 | K36: 61832 | L36: =+J36-K36 -> -30013.59 | M36: MXN | P36: 0 | Q36: 0 | S36: 7200 | T36: 0 | U36: 20229.66 | V36: 0 | W36: 0 | X36: 0 | Y36: 0 | Z36: 0 | AA36: 0 | AB36: 0 | AC36: 0 | AD36: 0 | AE36: 0 | AF36: 0 | AG36: 0 | AH36: 0 | AI36: =+SUM(S36:AH36)-H36 -> 0
A37: 1 | B37: 1-002925 | C37: CGL25063162 | D37: 45848 | E37: C0069 | F37: JOINT PRODUCTION HONOR | G37: 0 | H37: 22871.13 | I37: 3659.38 | J37: =SUM(G37:I37) -> 26530.51 | K37: 58352 | L37: =+J37-K37 -> -31821.49 | M37: MXN | P37: 0 | Q37: 0 | S37: 7200 | T37: 0 | U37: 15671.13 | V37: 0 | W37: 0 | X37: 0 | Y37: 0 | Z37: 0 | AA37: 0 | AB37: 0 | AC37: 0 | AD37: 0 | AE37: 0 | AF37: 0 | AG37: 0 | AH37: 0 | AI37: =+SUM(S37:AH37)-H37 -> 0
A38: 1 | B38: 1-002926 | C38: CGL25063169 | D38: 45848 | E38: C0069 | F38: JOINT PRODUCTION HONOR | G38: 0 | H38: 17287.9 | I38: 2766.06 | J38: =SUM(G38:I38) -> 20053.96 | K38: 98352 | L38: =+J38-K38 -> -78298.04 | M38: MXN | P38: 0 | Q38: 0 | S38: 7200 | T38: 0 | U38: 10087.9 | V38: 0 | W38: 0 | X38: 0 | Y38: 0 | Z38: 0 | AA38: 0 | AB38: 0 | AC38: 0 | AD38: 0 | AE38: 0 | AF38: 0 | AG38: 0 | AH38: 0 | AI38: =+SUM(S38:AH38)-H38 -> 0
A39: 2 | B39: 2-002927 | C39: CGL25053030 | D39: 45848 | E39: C0002 | F39: NAPS-GUANAJUATO CAM | G39: 336 | H39: 8300 | I39: 1328 | J39: =SUM(G39:I39) -> 9964 | K39: 9964 | L39: =+J39-K39 -> 0 | M39: MXN | P39: 0 | Q39: 336 | S39: 3000 | T39: 0 | U39: 0 | V39: 0 | W39: 3950 | X39: 0 | Y39: 0 | Z39: 1350 | AA39: 0 | AB39: 0 | AC39: 0 | AD39: 0 | AE39: 0 | AF39: 0 | AG39: 0 | AH39: 0 | AI39: =+SUM(S39:AH39)-H39 -> 0
A40: 2 | B40: 2-002929 | C40: CGL25053013 | D40: 45849 | E40: C0002 | F40: NAPS-GUANAJUATO CAM | G40: 336 | H40: 8150 | I40: 1304 | J40: =SUM(G40:I40) -> 9790 | K40: 9790 | L40: =+J40-K40 -> 0 | M40: MXN | P40: 0 | Q40: 336 | S40: 4200 | T40: 0 | U40: 0 | V40: 0 | W40: 3950 | X40: 0 | Y40: 0 | Z40: 0 | AA40: 0 | AB40: 0 | AC40: 0 | AD40: 0 | AE40: 0 | AF40: 0 | AG40: 0 | AH40: 0 | AI40: =+SUM(S40:AH40)-H40 -> 0
A41: 2 | B41: 2-002930 | C41: CGL25063127 | D41: 45849 | E41: C0002 | F41: NAPS-GUANAJUATO CAM | G41: 336 | H41: 8000 | I41: 1280 | J41: =SUM(G41:I41) -> 9616 | K41: 9616 | L41: =+J41-K41 -> 0 | M41: MXN | P41: 0 | Q41: 336 | S41: 4800 | T41: 0 | U41: 0 | V41: 0 | W41: 3200 | X41: 0 | Y41: 0 | Z41: 0 | AA41: 0 | AB41: 0 | AC41: 0 | AD41: 0 | AE41: 0 | AF41: 0 | AG41: 0 | AH41: 0 | AI41: =+SUM(S41:AH41)-H41 -> 0
A42: 1 | B42: 1-002931 | C42: CGL25063139 | D42: 45849 | E42: C0069 | F42: JOINT PRODUCTION HONOR | G42: 2116 | H42: 25060.27 | I42: 4009.64 | J42: =SUM(G42:I42) -> 31185.91 | K42: 60000 | L42: =+J42-K42 -> -28814.09 | M42: MXN | P42: 0 | Q42: 2116 | S42: 7200 | T42: 0 | U42: 17860.27 | V42: 0 | W42: 0 | X42: 0 | Y42: 0 | Z42: 0 | AA42: 0 | AB42: 0 | AC42: 0 | AD42: 0 | AE42: 0 | AF42: 0 | AG42: 0 | AH42: 0 | AI42: =+SUM(S42:AH42)-H42 -> 0
A43: 2 | B43: 2-002932 | C43: CGL25073204 | D43: 45849 | E43: C0081 | F43: JOINT PRODUCTION BLACK SMITH | G43: 0 | H43: 22000 | I43: 3520 | J43: =SUM(G43:I43) -> 25520 | K43: 25520 | L43: =+J43-K43 -> 0 | M43: MXN | P43: 0 | Q43: 0 | S43: 0 | T43: 0 | U43: 0 | V43: 0 | W43: 22000 | X43: 0 | Y43: 0 | Z43: 0 | AA43: 0 | AB43: 0 | AC43: 0 | AD43: 0 | AE43: 0 | AF43: 0 | AG43: 0 | AH43: 0 | AI43: =+SUM(S43:AH43)-H43 -> 0
... A47: 2 | B47: 2-002936 | C47: CGL25063130 | D47: 45852 | E47: C0002 | F47: NAPS-GUANAJUATO CAM | G47: 336 | H47: 6800 | I47: 1088 | J47: =SUM(G47:I47) -> 8224 | K47: 8224 | L47: =+J47-K47 -> 0 | M47: MXN | P47: 0 | Q47: 336 | S47: 6800 | T47: 0 | U47: 0 | V47: 0 | W47: 0 | X47: 0 | Y47: 0 | Z47: 0 | AA47: 0 | AB47: 0 | AC47: 0 | AD47: 0 | AE47: 0 | AF47: 0 | AG47: 0 | AH47: 0 | AI47: =+SUM(S47:AH47)-H47 -> 0
A48: 2 | B48: 2-002937 | C48: CGL25063158 | D48: 45852 | E48: C0002 | F48: NAPS-GUANAJUATO CAM | G48: 336 | H48: =4200+6400 -> 10600 | I48: 1696 | J48: =SUM(G48:I48) -> 12632 | K48: 12632 | L48: =+J48-K48 -> 0 | M48: MXN | P48: 0 | Q48: 336 | S48: 4200 | T48: 0 | U48: 0 | V48: 0 | W48: 6400 | X48: 0 | Y48: 0 | Z48: 0 | AA48: 0 | AB48: 0 | AC48: 0 | AD48: 0 | AE48: 0 | AF48: 0 | AG48: 0 | AH48: 0 | AI48: =+SUM(S48:AH48)-H48 -> 0
A49: 2 | B49: 2-002938 | C49: CGL25063176 | D49: 45852 | E49: C0002 | F49: NAPS-GUANAJUATO CAM | G49: 0 | H49: =4200+3950 -> 8150 | I49: 1304 | J49: =SUM(G49:I49) -> 9454 | K49: 9454 | L49: =+J49-K49 -> 0 | M49: MXN | P49: 0 | Q49: 0 | S49: 4200 | T49: 0 | U49: 0 | V49: 0 | W49: 3950 | X49: 0 | Y49: 0 | Z49: 0 | AA49: 0 | AB49: 0 | AC49: 0 | AD49: 0 | AE49: 0 | AF49: 0 | AG49: 0 | AH49: 0 | AI49: =+SUM(S49:AH49)-H49 -> 0
A50: 1 | B50: 1-002939 | C50: CGL25073185 | D50: 45852 | E50: C0004 | F50: NAPS-GUANAJUATO AMERICAN BOA | G50: 55513 | H50: =6785.39+4811.6 -> 11596.99 | I50: 1855.52 | J50: =SUM(G50:I50) -> 68965.51 | K50: 76724.05 | L50: =+J50-K50 -> -7758.54 | M50: MXN | P50: 0 | Q50: 55513 | S50: 6785.39 | T50: 0 | U50: 4811.6 | V50: 0 | W50: 0 | X50: 0 | Y50: 0 | Z50: 0 | AA50: 0 | AB50: 0 | AC50: 0 | AD50: 0 | AE50: 0 | AF50: 0 | AG50: 0 | AH50: 0 | AI50: =+SUM(S50:AH50)-H50 -> 0
A51: 1 | B51: 1-002940 | C51: CGL25052995 | D51: 45853 | E51: C0069 | F51: JOINT PRODUCTION HONOR | G51: =428+2561 -> 2989 | H51: =3000+7200+65160.52 -> 75360.52 | I51: 12057.68 | J51: =SUM(G51:I51) -> 90407.2 | K51: 90407.2 | L51: =+J51-K51 -> 0 | M51: MXN | P51: 0 | Q51: =428+2561 -> 2989 | S51: =3000+7200 -> 10200 | T51: 0 | U51: 65160.52 | V51: 0 | W51: 0 | X51: 0 | Y51: 0 | Z51: 0 | AA51: 0 | AB51: 0 | AC51: 0 | AD51: 0 | AE51: 0 | AF51: 0 | AG51: 0 | AH51: 0 | AI51: =+SUM(S51:AH51)-H51 -> 0
A52: 2 | B52: 2-002941 | C52: CGL25073230 | D52: 45853 | E52: C0081 | F52: JOINT PRODUCTION BLACK SMITH | G52: 0 | H52: 22000 | I52: 3520 | J52: =SUM(G52:I52) -> 25520 | K52: 25520 | L52: =+J52-K52 -> 0 | M52: MXN | P52: 0 | Q52: 0 | S52: 0 | T52: 0 | U52: 0 | V52: 0 | W52: 22000 | X52: 0 | Y52: 0 | Z52: 0 | AA52: 0 | AB52: 0 | AC52: 0 | AD52: 0 | AE52: 0 | AF52: 0 | AG52: 0 | AH52: 0 | AI52: =+SUM(S52:AH52)-H52 -> 0
A53: 2 | B53: 2-002942 | C53: CGL25063137 | D53: 45853 | E53: C0001 | F53: ARMOR MEXICO IMAGING SUPPLIES | G53: 0 | H53: =4200+1900+37500 -> 43600 | I53: 6976 | J53: =SUM(G53:I53) -> 50576 | K53: 0 | L53: =+J53-K53 -> 50576 | M53: MXN | P53: 0 | Q53: 0 | S53: 4200 | T53: 0 | U53: 0 | V53: 0 | W53: 37500 | X53: 0 | Y53: 0 | Z53: 0 | AA53: 0 | AB53: 0 | AC53: 0 | AD53: 0 | AE53: 0 | AF53: 0 | AG53: 0 | AH53: 1900 | AI53: =+SUM(S53:AH53)-H53 -> 0
A54: 2 | B54: 2-002943 | C54: CGL25073184 | D54: 45853 | E54: C0001 | F54: ARMOR MEXICO IMAGING SUPPLIES | G54: 0 | H54: 4000 | I54: 640 | J54: =SUM(G54:I54) -> 4640 | K54: 0 | L54: =+J54-K54 -> 4640 | M54: MXN | P54: 0 | Q54: 0 | S54: 4000 | T54: 0 | U54: 0 | V54: 0 | W54: 0 | X54: 0 | Y54: 0 | Z54: 0 | AA54: 0 | AB54: 0 | AC54: 0 | AD54: 0 | AE54: 0 | AF54: 0 | AG54: 0 | AH54: 0 | AI54: =+SUM(S54:AH54)-H54 -> 0
A55: 1 | B55: 1-002944 | C55: CGL25073202 | D55: 45853 | E55: C0012 | F55: MEGALUMINIO SERVICIOS | G55: 6063 | H55: =6500+9300+2200+1500 -> 19500 | I55: 3120 | J55: =SUM(G55:I55) -> 28683 | K55: 28901 | L55: =+J55-K55 -> -218 | M55: MXN | P55: 0 | Q55: 6063 | S55: 6500 | T55: 1500 | U55: 9300 | V55: 0 | W55: 2200 | X55: 0 | Y55: 0 | Z55: 0 | AA55: 0 | AB55: 0 | AC55: 0 | AD55: 0 | AE55: 0 | AF55: 0 | AG55: 0 | AH55: 0 | AI55: =+SUM(S55:AH55)-H55 -> 0
A56: 2 | B56: 2-002945 | C56: CGL25073201 | D56: 45853 | E56: C0084 | F56: JOINT PRODUCTION TECTRAN | G56: 0 | H56: 11640.93 | I56: 1862.55 | J56: =SUM(G56:I56) -> 13503.48 | K56: 13503.48 | L56: =+J56-K56 -> 0 | M56: MXN | P56: 0 | Q56: 0 | S56: 0 | T56: 0 | U56: 0 | V56: 0 | W56: 11640.93 | X56: 0 | Y56: 0 | Z56: 0 | AA56: 0 | AB56: 0 | AC56: 0 | AD56: 0 | AE56: 0 | AF56: 0 | AG56: 0 | AH56: 0 | AI56: =+SUM(S56:AH56)-H56 -> 0
A57: 1 | B57: 1-002946 | C57: CGL25063140 | D57: 45854 | E57: C0069 | F57: JOINT PRODUCTION HONOR | G57: 0 | H57: =7200+52251.85 -> 59451.85 | I57: 9512.3 | J57: =SUM(G57:I57) -> 68964.15 | K57: 72272 | L57: =+J57-K57 -> -3307.85 | M57: MXN | P57: 0 | Q57: 0 | S57: 7200 | T57: 0 | U57: 52251.85 | V57: 0 | W57: 0 | X57: 0 | Y57: 0 | Z57: 0 | AA57: 0 | AB57: 0 | AC57: 0 | AD57: 0 | AE57: 0 | AF57: 0 | AG57: 0 | AH57: 0 | AI57: =+SUM(S57:AH57)-H57 -> 0
A58: 2 | B58: 2-002948 | C58: CGL25042786 | D58: 45854 | E58: C0002 | F58: NAPS-GUANAJUATO CAM | G58: 18384 | H58: =4900+1800+2800+1500 -> 11000 | I58: 1760 | J58: =SUM(G58:I58) -> 31144 | K58: 31144 | L58: =+J58-K58 -> 0 | M58: MXN | P58: 0 | Q58: 18384 | S58: 4900 | T58: 0 | U58: 1500 | V58: 0 | W58: 0 | X58: 1800 | Y58: 2800 | Z58: 0 | AA58: 0 | AB58: 0 | AC58: 0 | AD58: 0 | AE58: 0 | AF58: 0 | AG58: 0 | AH58: 0 | AI58: =+SUM(S58:AH58)-H58 -> 0
A59: 2 | B59: 2-002949 | C59: CGL25063065 | D59: 45854 | E59: C0002 | F59: NAPS-GUANAJUATO CAM | G59: 781 | H59: =4800+1200 -> 6000 | I59: 960 | J59: =SUM(G59:I59) -> 7741 | K59: 7741 | L59: =+J59-K59 -> 0 | M59: MXN | P59: 0 | Q59: 781 | S59: 4800 | T59: 0 | U59: 0 | V59: 0 | W59: 0 | X59: 0 | Y59: 1200 | Z59: 0 | AA59: 0 | AB59: 0 | AC59: 0 | AD59: 0 | AE59: 0 | AF59: 0 | AG59: 0 | AH59: 0 | AI59: =+SUM(S59:AH59)-H59 -> 0
A60: 1 | B60: 1-002950 | C60: CGL25073231 | D60: 45854 | E60: C0005 | F60: HAHN AUTOMATION GROUP | G60: 2463 | H60: =4450+4198.47+2800 -> 11448.47 | I60: 1831.76 | J60: =SUM(G60:I60) -> 15743.23 | K60: 29810 | L60: =+J60-K60 -> -14066.77 | M60: MXN | P60: 0 | Q60: 2463 | S60: 4450 | T60: 0 | U60: 4198.47 | V60: 0 | W60: 2800 | X60: 0 | Y60: 0 | Z60: 0 | AA60: 0 | AB60: 0 | AC60: 0 | AD60: 0 | AE60: 0 | AF60: 0 | AG60: 0 | AH60: 0 | AI60: =+SUM(S60:AH60)-H60 -> 0
